Workbook

Sheet Form responses 1
A1: Timestamp | B1: Email address | C1: Full Name (in Block Letters) | D1: Roll Number / Enrollment ID | E1: Course | F1: Contact Number | G1: Email | H1: Attending Convocation | I1: Hobbies & Personal Interests | J1: Sports & Games / Notable Achievements | K1: Hometown | L1: Passport Size Photo Upload | M1: Family Photo Upload | N1: Father's Name | O1: Father's Occupation / Designation & Affiliation | P1: Father's City / Place of Residence | Q1: Father's Contact Number | R1: Mother's Name | S1: Mother's Occupation / Designation & Affiliation | T1: Mother's City / Place of Residence | U1: Mother's Contact Number | V1: Number of Accompanying Guests | W1: Guest 1 Full Name | X1: Relation with the Student | Y1: Guest 2 Full Name | Z1: Relation with the Student 2 | AA1: Student Meal/Food Preference | AB1: Guest 1 Meal/Food Preference | AC1: Guest 2 Meal/Food Preference | AD1: Bus Drop Service Required on 15.09.2026 at 8:00 PM? | AE1: Number of Passengers for Bus Service
A2: 46258.758 | B2: aryalekshmi.micro_pgt23@aiimskalyani.edu.in | C2: Dr. ARYALEKSHMI. P | D2: 20230317 | E2: MD/MS/MDS 2023 | F2: 8547621028 | G2: draryalekshmi.p2020@gmail.com | H2: Yes | K2: Thiruvananthapuram | L2: https://drive.google.com/open?id=1Ve3rgelDyUKPtFnAdnGfSgKUXegGOroA | M2: https://drive.google.com/open?id=1hs75SNotCZp_qyhtSsg4KkQ1TyUXiwzD | N2: K.R. Praveen Kumar | O2: Business | P2: Thiruvananthapuram | Q2: 8078178289 | R2: S. Padmakumari Amma | S2: Business | T2: Thiruvananthapuram | U2: 9497639529 | V2: 2 | W2: Dr. Kannan. V. B | X2: Husband | Y2: Arjun. V. B | Z2: Brother | AA2: Non-Veg | AB2: Non-Veg | AC2: Non-Veg | AD2: Bus Drop Service not needed | AE2: 0
A3: 46258.788 | B3: tutul.9711@gmail.com | C3: ARUNDHATI MUKHERJEE | D3: 2023032 | E3: MD/MS/MDS 2023 | F3: 9051909471 | G3: tutul.9711@gmail.com | H3: Yes | I3: Drawing/Painting, Singing, Writing and Reading | J3: ACHIEVEMENTS - · PAPERS PRESENTED o Presented at Late Brig. Prof. G.S. Gopal Award for Best Post-Graduate Research Paper at SEOCON 2025. o Presented at the Resident Paper Award at NESCON 2025. o Presented at the Dr. Sandra Nisha D’Souza PG Award paper and the Dr. Anoop Raj and Dr. S.L. Chopra E-poster competitions at the 76th AOICON 2025 held at Kochi, Kerala. o Presented at Major KK Ghosh PGT paper presentation and E-poster presentation competitions at 52nd AOIWB 2025 held at Haldia, West Bengal. o Presented at Major KK Ghosh PGT paper presentation at 51st AOIWB, 2024 held at Kolkata. · AWARDS AND ACCOLADES o Participated at the 18th Dr. SM Sen and Dr. Tarun Palit Temporal Bone Dissection Competition by AOIWB, in March 2026 held at Kolkata. o Winner of RHINOAESTHETICON 2025, Quiz held at AIIMS Kalyani in November, 2025. o Winner of Late Brig. Prof. G.S. Gopal Award for Best Post-Graduate Research Paper at SEOCON 2025, held at Pune, Maharashtra. o Winner of SEOCON 2025 ENT quiz, held at Pune, Maharashtra. o Winner of NESCON 2025 Quiz competition. o 2nd runner up in Resident Paper Award at NESCON 2025. o Winner of the Prof SN Choudhury and Dr. P Chatterjee, 52nd AOIWB ENT quiz 2025 held at Haldia, West Bengal. o Participated at the Rhinology quiz and the Dr. Prem Kakkar ENT quiz held at the 76th AOICON 2025 held at Kochi, Kerala. o Participated at the 17th Dr. SM Sen and Dr. Tarun Palit Temporal Bone Dissection Competition by AOIWB, in April 2025 held at Kolkata. o Participated at the Prof SN Choudhury and Dr. P Chatterjee, 51st AOIWBCON ENT quiz 2024 at Kolkata, West Bengal . COMPETITIVE EXAMS: Achieved AML Rank 11 in INI-SS July, 2026 exams. Currently pursuing MCh Plastic Surgery and Reconstructive Surgery at AIIMS Raipur. · ACADEMIC ACHIEVEMENTS AND AWARDS o Honors in MBBS in the subjects of Biochemistry, Pathology, Pharmacology, Forensic Medicine and Technology, Otorhinolaryngology, Ophthalmology, Community and Family Medicine, General Medicine, General Surgery and Paediatric Medicine and Neonatology. o Obtained highest marks and gold medals in MBBS in the subjects of Forensic Medicine and Technology, Otorhinolaryngology, Ophthalmology, Community and Family Medicine, General Medicine, General Surgery and Paediatric Medicine and Neonatology. o University topper in Paediatric medicine and Neonatology in MBBS. o Scored 75% in post-graduate exit exam for MS Otorhinolaryngology from AIIMS Kalyani | K3: Kolkata | L3: https://drive.google.com/open?id=1_j5e_JX1--W1J-lrq1oLNLFeWOWMawCh | M3: https://drive.google.com/open?id=1uY7TeX8m5oAoS51y5th6r-EeTDoPFDvM | N3: SAUBHIK MUKHERJEE | O3: RETIRED | P3: KOLKATA, WEST BENGAL | Q3: 9830298198 | R3: BAISHAKHI MUKHERJEE | S3: HOMEMAKER | T3: KOLKATA, WEST BENGAL | U3: 9830108655 | V3: 2 | W3: SAUBHIK MUKHERJEE | X3: FATHER | Y3: BAISHAKHI MUKHERJEE | Z3: MOTHER | AA3: Non-Veg | AB3: Non-Veg | AC3: Non-Veg | AD3: Bus Drop Service not needed | AE3: 0
A4: 46258.79 | B4: shivani.mbbs-2020@aiimskalyani.edu.in | C4: SHIVANI KUMARI | D4: 202001142 | E4: MBBS 2020 | F4: 9199180555 | G4: shivani.mbbs-2020@aiimskalyani.edu.in | H4: Yes | I4: Listening to music | K4: Patna | L4: https://drive.google.com/open?id=1RfJBGbLf99R16v5n9J2VAwbNPAdqNGMh | M4: https://drive.google.com/open?id=1STTeHRjW4WNongEoGig9psCiKAfLb4Xu | N4: Santosh Kumar | O4: Business man | P4: Patna | Q4: 9934802080 | R4: Ruby Kumari | S4: Housemaker | T4: Patna | U4: 7857869034 | V4: 2 | W4: Santosh Kumar | X4: Father | Y4: Ruby kumari | Z4: Mother | AA4: Veg | AB4: Veg | AC4: Veg | AD4: Bus Drop Service not needed | AE4: 0
A5: 46258.791 | B5: aman2.mbbs-2020@aiimskalyani.edu.in | C5: AMAN KUMAR | D5: 20200161 | E5: MBBS 2020 | F5: 8637357310 | G5: aman2.mbbs-2020@aiimskalyani.edu.in | H5: Yes | I5: Making connections with people, making memes, organising events. | J5: Worked as Cultural Representative for 1 year. | K5: Samastipur | L5: https://drive.google.com/open?id=1suZL-X0BxCLmYfcwzUijOzMezxZEVbSW | M5: https://drive.google.com/open?id=1ReqtzHanLhryyFBG63TCBQgMGflMz5Pd | N5: Ajay Kumar Yadav | O5: Lawyer | P5: Samastipur, Bihar | Q5: 9852206837 | R5: Poonam Devi | S5: Homemaker | T5: Samastipur,Bihar | U5: 9431815713 | V5: 2 | W5: Ajay Kumar Yadav | X5: Father | Y5: Poonam Devi | Z5: Mother | AA5: Non-Veg | AB5: Non-Veg | AC5: Non-Veg | AD5: Drop at Kalyani Railway Station | AE5: 3
A6: 46258.793 | B6: tanishabiswas2412@gmail.com | C6: TANISHA BISWAS | D6: 20210256 | E6: B.Sc (Hons) Nursing 2021 | F6: 9735901944 | G6: tanishabiswas2412@gmail.com | H6: Yes | I6: I enjoy working out and staying active, with a particular interest in strength training and fitness. I also like cooking and art. | J6: I do like to play badminton (won badminton doubles in the college annual sports ) | K6: Krishnanagar, Nadia | L6: https://drive.google.com/open?id=1NCOOa_8VmPy1X5FhFx0U4oSo3SKqIgY8 | M6: https://drive.google.com/open?id=17i92BzKwyN2k5VhycQ5DI3h-7HMpDCX2 | N6: TAPAN KUMAR BISWAS | O6: Govt. Services ( Income Tax Office Superintendent ) | P6: Krishnanagar, Nadia | Q6: 9477330097 | R6: SUPRIYA BISWAS | S6: Home maker | T6: Krishnanagar | U6: 9775529810 | V6: 2 | W6: SUPRIYA BISWAS | X6: Mother | Y6: TAPAN KUMAR BISWAS | Z6: Father | AA6: Non-Veg | AB6: Non-Veg | AC6: Non-Veg | AD6: Bus Drop Service not needed | AE6: 0
A7: 46258.796 | B7: sandeepp.mbbs-2020@aiimskalyani.edu.in | C7: SANDEEP KUMAR PATRO | D7: 202001133 | E7: MBBS 2020 | F7: 7205409551 | G7: sandeepp.mbbs-2020@aiimskalyani.edu.in | H7: Yes | I7: Swimming | J7: Nothing | K7: Bhubaneswar | L7: https://drive.google.com/open?id=1eN9KhEi0TCm-OcRLJmS5rKVoLJwRf1mI | M7: https://drive.google.com/open?id=1Ri09OkjQVrb-B_-sNHrLb7K3aF2Lqv5V | N7: Rabindra Nath Patro | O7: Pharmacist | P7: Bhubaneswar | Q7: 9438602542 | R7: Sarita Patro | S7: Housewife | T7: Bhubaneswar | U7: 9692630419 | V7: 2 | W7: Rabindra Nath Patro | X7: Father | Y7: Sarita Patro | Z7: Mother | AA7: Non-Veg | AB7: Non-Veg | AC7: Non-Veg | AD7: Drop at Kalyani Railway Station | AE7: 3
A8: 46258.801 | B8: kaki.mbbs-2020@aiimskalyani.edu.in | C8: Kaki Jessica Pal | D8: 55/ 202001105 | E8: MBBS 2020 | F8: 8328165594 | G8: kaki.mbbs-2020@aiimskalyani.edu.in | H8: Yes | K8: Hyderabad, Telangana | L8: https://drive.google.com/open?id=1h4VpzyKvgyDNNcYVeW6ly6tOWqJOXtMs | M8: https://drive.google.com/open?id=1RcZNsQ-1elCc1ADBnjl4hCbodpnOgm9- | N8: Kaki V Jayapal Babu | O8: DGM, CSD department, ECIL, Hyderabad. | P8: Hyderabad | Q8: 9441666885 | R8: N Yesumanimma | S8: Senior Assistant, Smt. Durgabai Deshmukh Government Women's Technical Training Institute of technology and science, Hyderabad | T8: Hyderabad | U8: 9246348343 | V8: 2 | W8: Kaki V Jayapal Babu | X8: Father | Y8: N Yesumanimma | Z8: Mother | AA8: Non-Veg | AB8: Non-Veg | AC8: Non-Veg | AD8: Bus Drop Service not needed
A9: 46258.805 | B9: pritharoy426@gmail.com | C9: PRITHA ROY | D9: 20210238 | E9: B.Sc (Hons) Nursing 2021 | F9: 8777026833 | G9: pritha1405@gmail.com | H9: Yes | I9: Doodling,Crafting,Gardening,Digital Video Editing | J9: Scouts and Guide Certified and Crafting Certificate and Organisation Certificate | K9: Kolkata | L9: https://drive.google.com/open?id=1YRRwubDBrdrwOYwpaBVXTz6uwcv90LO- | M9: https://drive.google.com/open?id=1Tt51dZ7qtQV2avZFs44rQOLmeiBAiqLl | N9: Mr. Dipak Kumar Roy | O9: Retired Optometrist | P9: Kolkata | Q9: 9830349736 | R9: Mrs. Soma Roy | S9: Staff Nurse | T9: Kolkata | U9: 9051166452 | V9: 2 | W9: Mr. Dipak Kumar Roy | X9: Father | Y9: Mrs. Soma Roy | Z9: Mother | AA9: Non-Veg | AB9: Non-Veg | AC9: Non-Veg | AD9: Bus Drop Service not needed | AE9: 0
A10: 46258.874 | B10: anirudh.mbbs-2020@aiimskalyani.edu.in | C10: ANIRUDH GUPTA | D10: 17 / 20200167 | E10: MBBS 2020 | F10: 9464906137 | G10: anirudh.mbbs-2020@aiimskalyani.edu.in | H10: Yes | I10: I like travelling, aviation and watching sitcoms. | J10: - Joint organising secretary of "Elyssia" 1.0 - Editor-in-chief of "Samhita" 2.0 | K10: Chandigarh | L10: https://drive.google.com/open?id=1PSXf2zicyWI65fLmGUfogSav7KQ6IW7Y | M10: https://drive.google.com/open?id=1nSrmZabl9dLEuU_jVo6OP4hFGyxYvmcW | N10: Dr. Vivek Gupta | O10: Additional Director Interventional Neuroradiology Fortis Hospital Mohali Punjab | P10: Chandigarh | Q10: 7087009871 | R10: Dr. Madhu Gupta | S10: Professor Department of Community Medicine and School of Public Health PGIMER, Chandigarh | T10: Chandigarh | U10: 7087008223 | V10: 2 | W10: Dr. Vivek Gupta | X10: Father | Y10: Dr. Madhu Gupta | Z10: Mother | AA10: Non-Veg | AB10: Veg | AC10: Veg | AD10: Drop at Kolkata Airport | AE10: 3
A11: 46258.875 | B11: sandeep.mbbs-2020@aiimskalyani.edu.in | C11: SANDEEP KUMAR | D11: 202001132 | E11: MBBS 2020 | F11: 9142602801 | G11: sandeep.mbbs-2020@aiimskalyani.edu.in | H11: Yes | I11: Sports,Watching movies,Singing and many other. | J11: Gully cricket | K11: Jehanabad | L11: https://drive.google.com/open?id=1kqkAzE1eOmrtdmrzRw8esKmszv6pTXiS | M11: https://drive.google.com/open?id=1Bt6RqjcZymSOtepnin9GtCneOooOhk1b | N11: Shree Upendra prasad | O11: Farmer | P11: Jehanabad | Q11: 8427188157 | R11: Shreemati Neelam Kumari | S11: Auxiliary Nurse Midwife | T11: Jehanabad | U11: 9572285253 | V11: 2 | W11: Shree Upendra Prasad | X11: Father | Y11: Shreemati Neelam kumari | Z11: Mother | AA11: Non-Veg | AB11: Veg | AC11: Veg | AD11: Bus Drop Service not needed
A12: 46258.883 | B12: megha.bscnursing-2021@aiimskalyani.edu.in | C12: MEGHA MAITI | D12: 20210221 | E12: B.Sc (Hons) Nursing 2021 | F12: 9593286407 | G12: meghamaiti288@gmail.com | H12: Yes | I12: Drawing | J12: NA | K12: Dakshin Mechogram, Panskura, Purba Medinipur | L12: https://drive.google.com/open?id=1yx_mTJmpBlS7Ehjr2FkvxGn7j9Nj2wg3 | M12: https://drive.google.com/open?id=1r05u7kaR07v-0XzX50YXDcEiRVbJywIM | N12: NITAI CHARAN MAITI | O12: Retired Bank employee | P12: Dakshin Mechogram, Panskura, Purba Medinipur | Q12: 9434804867 | R12: LATE NABANITA MAITI | S12: NA | T12: NA | U12: 9434129205 | V12: 2 | W12: SUSAMA GHORAI | X12: Sister | Y12: SOURYA MAITI | Z12: Brother | AA12: Non-Veg | AB12: Non-Veg | AC12: Non-Veg | AD12: Bus Drop Service not needed | AE12: 0
A13: 46258.883 | B13: mukherjeeadrita8@gmail.com | C13: ADRITA MUKHERJEE | D13: 20210202 | E13: B.Sc (Hons) Nursing 2021 | F13: 9382419184 | G13: mukherjeeadrita8@gmail.com | H13: Yes | I13: Drawing | K13: Midnapore | L13: https://drive.google.com/open?id=1gZ6v76lU3CFE6kKfseufO2_k_gc7KcL8 | M13: https://drive.google.com/open?id=1DFJGA8riZ87Ou3GVZQWgBDMuQAqU9SFj | N13: ANIRBAN MUKHERJEE | O13: Senior Technician Incharge signal department Railway employee kgp junction | P13: Midnapore | Q13: 7595081828 | R13: MAHUA MUKHERJEE | S13: HOUSEWIFE | T13: MIDNAPORE | U13: 9434139015 | V13: 2 | W13: ANIRBAN MUKHERJEE | X13: Father | Y13: MAHUA MUKHERJEE | Z13: Mother | AA13: Non-Veg | AB13: Veg | AC13: Non-Veg | AD13: Bus Drop Service not needed | AE13: 0
A14: 46258.884 | B14: souvik.patho_pgt23@aiimskalyani.edu.in | C14: SOUVIK BHATTACHARYA | D14: 20230315 | E14: MD/MS/MDS 2023 | F14: 8017164337 | G14: svkbhttchr@live.in | H14: Yes | I14: Gardening | J14: NA | K14: Kolkata | L14: https://drive.google.com/open?id=1hExh2JwuT6TMN4Mg4IBFwmLaqAZa85G0 | M14: https://drive.google.com/open?id=1u_rmdsZQkqSLw89Wr3hh4895kQxU6rCH | N14: Saswata Bhattacharyya | O14: Doctor | P14: Kolkata | Q14: 9433879722 | R14: Sanghamitra Bhattacharya | S14: Teacher | T14: Kolkata | U14: 9433336318 | V14: 2 | W14: Saswata Bhattacharyya | X14: Father | Y14: Sanghamitra Bhattacharya | Z14: Mother | AA14: Non-Veg | AB14: Veg | AC14: Non-Veg | AD14: Drop at Kolkata Airport | AE14: 3
A15: 46258.889 | B15: soumya.mbbs-2020@aiimskalyani.edu.in | C15: SOUMYA PARIDA | D15: 202001148 | E15: MBBS 2020 | F15: 7735479962 | G15: paridasoumya1@gmail.com | H15: Yes | K15: Kendrapada , Odisha | L15: https://drive.google.com/open?id=1zTOBxVNCXt22Rwj7Pl1gpjJkQa8kWMSn | M15: https://drive.google.com/open?id=1UJUiJTyL0PYyi87H4TV5zhX-DzbNR0lw | N15: Pravat Kumar Parida | O15: Physics lecture | P15: Kendrapada, Odisha | Q15: 7008620644 | R15: Bandita Routray | S15: Teacher | T15: Kendrapada, Odisha | U15: 7008072294 | V15: 2 | W15: Shraddha saraswati Parida | X15: Sister | Y15: Pravat Kumar Parida | Z15: Father | AA15: Veg | AB15: Veg | AC15: Veg | AD15: Drop at Kolkata Airport | AE15: 3
A16: 46258.935 | B16: aditi.bscnursing-2021@aiimskalyani.edu.in | C16: ADITI MANDAL | D16: 20210201 | E16: B.Sc (Hons) Nursing 2021 | F16: 7584874474 | G16: aditimandal0328@gmail.com | H16: Yes | I16: Painting | K16: Purba Barddhaman, West Bengal | L16: https://drive.google.com/open?id=1jTIq7YFhMjFF20qzi_laHszNnwT09IJ5 | M16: https://drive.google.com/open?id=1jY1Pfr68oNoCTqmnwGvgYXorqJPrNTfD | N16: Sakti Pada Mandal | O16: Ex service man | P16: Purba Barddhaman | Q16: 7477517960 | R16: Shyamali Mandal | S16: Housewife | T16: Purba Barddhaman | U16: 9732142457 | V16: 2 | W16: Sakti Pada Mandal | X16: Father | Y16: Shyamali Mandal | Z16: Mother | AA16: Non-Veg | AB16: Non-Veg | AC16: Non-Veg | AD16: Bus Drop Service not needed | AE16: 0
A17: 46258.977 | B17: prasu1999cmc@gmail.com | C17: PRASANJIT DAS | D17: 20230320 | E17: MD/MS/MDS 2023 | F17: 9476084509 | G17: docprasanjitdas@gmail.com | H17: Yes | I17: Online educator, Researcher, Poet and Quiz master | J17: ICTD QUIZ COORDINATOR FOR AIIMS UG STUDENTS FOR TWO CONSECUTIVE YEARS, AUTHOR OF COLLECTION OF POEMS NAMED WINGS OF IMAGINATION PART 1,2 and 3, T-SHIRT BRAND OWNER, CREATOR | K17: PORT BLAIR | L17: https://drive.google.com/open?id=1SWuwHRxyno1L65hUqbVUCARa8kB9WwfS | M17: https://drive.google.com/open?id=1eN3XM3FDAfnjuzltq2F02E95vygNgK8o | N17: PRASANTA KUMAR DAS | O17: GOVERNMENT SERVANT ASSISTANT INCHARGE | P17: PORT BLAIR | Q17: 9434264702 | R17: TAPASI RANI DAS | S17: RETIRED GOVERNMENT SERVANT | T17: PORT BLAIR | U17: 9474231697 | V17: 2 | W17: PRASANTA KUMAR DAS | X17: FATHER | Y17: TAPASI RANI DAS | Z17: MOTHER | AA17: Non-Veg | AB17: Non-Veg | AC17: Non-Veg | AD17: Bus Drop Service not needed | AE17: 0
A18: 46259.029 | B18: chayanika.bscnursing-2021@aiimskalyani.edu.in | C18: CHAYANIKA BHATTACHARYYA | D18: 20210210 | E18: B.Sc (Hons) Nursing 2021 | F18: 9830079476 | G18: chayanikabhattacharyya4948@gmail.com | H18: Yes | I18: I am an avid listener of audio stories, enjoy expressing my thoughts through poetry, and love dancing occasionally. | J18: Nothing as such | K18: Sodepur | L18: https://drive.google.com/open?id=1LwqSTi2fSQe0ScwNC2r5BtXOsq_ISJ1o | M18: https://drive.google.com/open?id=1t8EZibcMxmHBFmMnZsEeQLKarEkZlhfi | N18: Biswajit Bhattacharyya | O18: Government service, Assistant Secretary, department of Public Health Engineering( PHE) , West Bengal government | P18: Sodepur | Q18: 9830035498 | R18: Aparna Bhattacharyya | S18: Government service, police in Department of Disaster Management and Civil Defence , West Bengal government | T18: Sodepur | U18: 7980652856 | V18: 2 | W18: Aparna bhattacharyya | X18: Mother | Y18: Kosturi singha roy | Z18: Aunt | AA18: Non-Veg | AB18: Non-Veg | AC18: Non-Veg | AD18: Drop at Kalyani Railway Station | AE18: 3
A19: 46259.385 | B19: shabnam.bscnursing-2021@aiimskalyani.edu.in | C19: SHABNAM PARVIN | D19: 20210248 | E19: B.Sc (Hons) Nursing 2021 | F19: 6297820802 | G19: parvinshabnam2002@gmail.com | H19: Yes | I19: Story reading | J19: No | K19: Bharatpur | L19: https://drive.google.com/open?id=1bo6OujeREw0L8EjGlISNIBR_OR-ZWkZg | M19: https://drive.google.com/open?id=1tb-MIGQ5GOylf6dZBWRVO2WA8GCWKCDi | N19: IDRISH ALI | O19: Retired headmaster | P19: Bharatpur | Q19: 9474314028 | R19: JESMINNHAR BEGUM | S19: NURSE | T19: Bharatpur | U19: 9564131918 | V19: 2 | W19: IDRISH ALI | X19: Father | Y19: JESMINNHAR BEGUM | Z19: Mother | AA19: Non-Veg | AB19: Non-Veg | AC19: Non-Veg | AD19: Bus Drop Service not needed | AE19: 0
A20: 46259.424 | B20: ghoshankita9732@gmail.com | C20: ANKITA GHOSH | D20: 20210205 | E20: B.Sc (Hons) Nursing 2021 | F20: 7550811864 | G20: ghoshankita9732@gmail.com | H20: Yes | I20: Drawing | J20: NA | K20: Howrah | L20: https://drive.google.com/open?id=12mVENRztApFqkfMj-N-EbI99DcOAnjQI | M20: https://drive.google.com/open?id=1sN-R1iU5tJvTKcjxNc8GxGMrBfPDcM1S | N20: Amit Ghosh | O20: Law clerk | P20: Howrah | Q20: 9732648905 | R20: Krishna Ghosh | S20: House wife | T20: Howrah | U20: 8509374801 | V20: 2 | W20: Amit Ghosh | X20: Father | Y20: Krishna Ghosh | Z20: Mother | AA20: Non-Veg | AB20: Non-Veg | AC20: Non-Veg | AD20: Bus Drop Service not needed | AE20: 0
A21: 46259.424 | B21: harukinanase1999@gmail.com | C21: Shreyasi Hati | D21: 20210260 | E21: B.Sc (Hons) Nursing 2021 | F21: 6297209181 | G21: harukinanase1999@gmail.com | H21: Yes | I21: Singing, Dancing, and writing stories. | J21: Sports- District level kabaddi and shot put player. Cultural - State level extempore and recitation winner, District level declamation winner 2024 in YPC. Various winning positions held in solo classical dance, drama, singing, literary hunt, quiz, debate, extempore, poem writing, slogan writing in inter house competitions during 4 years of college journey. Notable Achievements:- Traditionally published international novelist. Total books and anthology published - 6+. Books have been published in 133 countries including UK, USA, Canada, Japan, Australia and India through Ukiyoto Publishing India( An indian branch of Ukiyoto Japan) and featured in Amazon, Flipkart, Kobo Japan, Google books, Walmart etc. Awards & Honors:- Rising Star Award – 2020 Twisted Awards – 2020 Special Mention, Marine Awards (Short Story Category) – 2021 Women Icon Award – 2024 Golden Heritage Award – 2024 (Blue Star Publication) The Leading Attainers Award – “The Budding Author of the Year” – JEC Publications 7th Place, National Poetry Contest by S7 Rabindranath Tagore Hall of Fame Award – Welred Foundation International Recognition:- Invited Author, International Writers Assembly – Beijing, China (2025) Professional Affiliations:- Exclusive Author, A&D Entertainment Company (Webnovel Contract) | K21: Jamuria, Asansol | L21: https://drive.google.com/open?id=15VzPSTgmPpWXI6z2gRrbuOfp-S0xeTX8 | M21: https://drive.google.com/open?id=1kV_ewUUdJaWU4DsSMykLEI-oa4NRfwnQ | N21: Subrata Hati | O21: Gov. High School Teacher/ Assistant teacher in Birkulti N.G.M High School | P21: Jamuria, Asansol | Q21: 9474179653 | R21: Ivi Hati | S21: Home maker | T21: Jamuria, Asansol | U21: 7001010315 | V21: 2 | W21: Subrata Hati | X21: Father | Y21: Ivi Hati | Z21: Mother | AA21: Non-Veg | AB21: Non-Veg | AC21: Non-Veg | AD21: Bus Drop Service not needed | AE21: 0
A22: 46259.435 | B22: suchismitatikadar06@gmail.com | C22: SUCHISMITA TIKADAR | D22: 20210252 | E22: B.Sc (Hons) Nursing 2021 | F22: 8167823201 | G22: suchismitatikadar06@gmail.com | H22: Yes | I22: Listening to music | J22: CR in 4th year | K22: Barrackpore | L22: https://drive.google.com/open?id=1in8EqddpfEgt0T8H8C9u4-s47ybeLQym | M22: https://drive.google.com/open?id=1PfFNHgJaZ24VQtrXvxJkCNPtDZdprTPV | N22: Ramesh Chandra Tikadar | O22: Retired Railway Employee | P22: Barrackpore | Q22: 8101896944 | R22: Sima Tikadar | S22: House wife | T22: Barrackpore | U22: 7029022292 | V22: 2 | W22: Ramesh Chandra Tikadar | X22: Father | Y22: Sima Tikadar | Z22: Mother | AA22: Non-Veg | AB22: Non-Veg | AC22: Non-Veg | AD22: Drop at Kalyani Railway Station | AE22: 3
A23: 46259.437 | B23: amrit.mbbs-2020@aiimskalyani.edu.in | C23: AMRIT RAJ ANAND | D23: 20200163 | E23: MBBS 2020 | F23: 7484027360 | G23: amritrajanand51054@gmail.com | H23: Yes | I23: Football and Music | K23: Chhapra | L23: https://drive.google.com/open?id=1ebUTdcQyNy1kHGDWLP7si5Lr08i6dGfS | M23: https://drive.google.com/open?id=1_LznKduDz5f4pghoIv7j-MlwomF_NOaA | N23: CHANDAN SHARMA | O23: FARMER | P23: CHHAPRA | Q23: 8002729788 | R23: MANORMA SHARMA | S23: HOUSEWIFE | T23: CHHAPRA | U23: 8002729788 | V23: 2 | W23: RAM ANOOP SHRMA | X23: Grandfather | Y23: Nirmal Sharma | Z23: Uncle | AA23: Non-Veg | AB23: Veg | AC23: Veg | AD23: Bus Drop Service not needed | AE23: 0
A24: 46259.461 | B24: tuabanerjee1998@gmail.com | C24: SUKANYA BANERJEE | D24: 20210254 | E24: B.Sc (Hons) Nursing 2021 | F24: 8967823183 | G24: tuabanerjee1998@gmail.com | H24: Yes | I24: Reading books | K24: Basirhat | L24: https://drive.google.com/open?id=18VpKBK02odLSuP_Vz9lZWXzo-g8-Ho2p | M24: https://drive.google.com/open?id=15YmVzTzAigXyrk6ABa9nTOXGTUBg4ydd | N24: TAPAS BANERJEE | O24: Retired Government Employee | P24: Barasat | Q24: 9051225778 | R24: CHAITALI BANERJEE | S24: House Wife | T24: Barasat | U24: 9083248006 | V24: 2 | W24: Tapas Banerjee | X24: Father | Y24: Sreerup Banerjee | Z24: Brother | AA24: Non-Veg | AB24: Non-Veg | AC24: Non-Veg | AD24: Bus Drop Service not needed | AE24: 0
A25: 46259.468 | B25: awantika.mbbs-2020@aiimskalyani.edu.in | C25: AWANTIKA JHA | D25: Enrolment number: 20200181 | E25: MBBS 2020 | F25: 8918275082 | G25: awantika.mbbs-2020@aiimskalyani.edu.in | H25: Yes | I25: Poem writing, listening to music | K25: Durgapur | L25: https://drive.google.com/open?id=1swgdXG5ahfxdANZb31Jij9iuAiMrQ-GJ | M25: https://drive.google.com/open?id=1T6W7gCxCxiXRzLWClR30gfBGvOB7xvpI | N25: Vimalesh Kumar | O25: Deputy Accountant General/IAAS | P25: KOLKATA | Q25: 9434200996 | R25: Guriya Kumari | S25: Homemaker | T25: Durgapur | U25: 9339372714 | V25: 2 | W25: Vimalesh Kumar | X25: Father | Y25: Guriya Kumari | Z25: Mother | AA25: Veg | AB25: Veg | AC25: Veg | AD25: Bus Drop Service not needed | AE25: 0
A26: 46259.731 | B26: aritpriyo.mbbs-2020@aiimskalyani.edu.in | C26: ARITPRIYO GHOSH | D26: 24 | E26: MBBS 2020 | F26: 7339814841 | G26: rikghosh2015@gmail.com | H26: Yes | K26: Kalyani | L26: https://drive.google.com/open?id=1_lO5SQB-zGnpvwJKVcDPzkTOs5OgzmxX | M26: https://drive.google.com/open?id=1lM_Pqa4APkRd4ud8x3cCNVqZaH20aqcU | N26: Rajib Ghosh | O26: Government service | P26: Kalyani | Q26: 8017553865 | R26: Madhumita Ghosh | S26: Home maker | T26: Kalyani | U26: 6289116611 | V26: 2 | W26: Madhumita Ghosh | X26: Mother | Y26: Rajib Ghosh | Z26: Father | AA26: Non-Veg | AB26: Non-Veg | AC26: Non-Veg | AE26: 0
A27: 46259.739 | B27: samina.bscnursing-2021@aiimskalyani.edu.in | C27: SAMINA YASMIN | D27: 20210243 | E27: B.Sc (Hons) Nursing 2021 | F27: 8529460880 | G27: yasminsamina2312@gmail.com | H27: Yes | I27: Travelling and exploring new places Cooking and listening music | J27: NA | K27: Uttar Dinajpur | L27: https://drive.google.com/open?id=1ff7w9oWM0zZamED4L5zGFL1ShxRfELVm | M27: https://drive.google.com/open?id=15g0VUuS3eWOtYa4xYiE-49HMFJkGPJ_H | N27: MD.Islamuddin | O27: Servicemen ( Kolkata police) | P27: Uttar Dinajpur | Q27: 8777838566 | R27: Manwara Begam | S27: Housewife | T27: Uttar Dinajpur | U27: 9679153471 | V27: 1 | W27: MD . Islamuddin | X27: Father | Y27: NA | Z27: NA | AA27: Non-Veg | AB27: Non-Veg | AD27: Bus Drop Service not needed | AE27: 0
A28: 46259.76 | B28: mansi.singh2021@gmail.com | C28: DR MANSHI KUMARI | D28: 2023037 | E28: MD/MS/MDS 2023 | F28: 8207207670 | G28: mansi.singh2021@gmail.com | H28: Yes | K28: Varanasi,Uttar Pradesh | L28: https://drive.google.com/open?id=1l5jAcXwoQ-cvT-9G8LAGLweeEyCOYRNI | M28: https://drive.google.com/open?id=1SefSF4GXvJgrmCLfFNmLeUBeigtkZDqN | N28: Mr Raj Kumar Singh | O28: Civil Engineer | P28: Aurangabad ,Bihar | Q28: 9801120313 | R28: Geeta Singh | S28: Housewife | T28: Aurangabad,Bihar | U28: 9199013095 | V28: 2 | W28: Mr. Raj Kumar Singh | X28: Father | Y28: Dr Rishi Singh | Z28: Husband | AA28: Veg | AB28: Veg | AC28: Non-Veg | AD28: Bus Drop Service not needed | AE28: 0
A29: 46259.899 | B29: satyajit.mbbs-2020@aiimskalyani.edu.in | C29: SATYAJIT BEHERA | D29: 86(202001136) | E29: MBBS 2020 | F29: 8984155610 | G29: satyajit.mbbs-2020@aiimskalyani.edu.in | H29: Yes | I29: Studying | K29: Bhadrak | L29: https://drive.google.com/open?id=1pTCiAxTmh72cd1ew5dqtKt5o63zF4DVl | M29: https://drive.google.com/open?id=18yGlpiRX8BvHeQapF545hc1x-tS2uJog | N29: Ramakanta Behera | O29: Farmer | P29: Bhadrak | Q29: 8598018028 | R29: Minati Behera | S29: Housewife | T29: Bhadrak | U29: 8598018028 | V29: 2 | W29: Sasmita Barik | X29: Sister | Y29: Kashinath Barik | Z29: Brother | AA29: Non-Veg | AB29: Veg | AC29: Non-Veg | AD29: Bus Drop Service not needed | AE29: 0
A30: 46260.065 | B30: krishnas.mbbs-2020@aiimskalyani.edu.in | C30: KRISHNAS MAHI | D30: 58/202001108 | E30: MBBS 2020 | F30: 9110167850 | G30: krishnasmahi1@gmail.com | H30: Yes | I30: Cooking &Baking, makeup, painting | J30: No such | K30: Bhagalpur | L30: https://drive.google.com/open?id=1XTyHx4GbZQFlgWAkfnY_3DnqsZBqeupP | M30: https://drive.google.com/open?id=1P_X0YDbiCrcY9oVeF1sWkeovZYgKMExE | N30: Mr. Anupam Kumar Veena | O30: Businessman | P30: Bhagalpur | Q30: 7488610832 | R30: Mrs Pankhuri Verma | S30: Teacher | T30: Bhagalpur | U30: 9110904670 | V30: 2 | W30: Mr Anupam Kumar Verma | X30: Father | Y30: Mrs Pankhuri Verma | Z30: Mother | AA30: Non-Veg | AB30: Non-Veg | AC30: Non-Veg | AD30: Bus Drop Service not needed | AE30: 0
A31: 46260.109 | B31: riya.mbbs-2020@aiimskalyani.edu.in | C31: RIYA BEN | D31: 202001127 | E31: MBBS 2020 | F31: 8606774642 | G31: riya.mbbs-2020@aiimskalyani.edu.in | H31: Yes | I31: I play musical instruments like Keyboard and do Classical Dance. | J31: Achievements in Clinical case presentations and Quiz competitions. | K31: Palakkad,Kerala | L31: https://drive.google.com/open?id=1fxh5-Uv1aPb30bXsySbDnRVK9Y3Kg_gX | M31: https://drive.google.com/open?id=1b2PmDTvfM0tx4EnfWQ5zBGcJFZ-e_yhI | N31: BEN | O31: Doctor[Consultant Radiologist] & Owner[Ideal Diagnostics Centre] | P31: Madurai,Tamil Nadu | Q31: 9447277746 | R31: RANI BEN | S31: Administrator [Ideal Diagnostics Centre] | T31: Ernakulam,Kerala | U31: 9895637636 | V31: 2 | W31: BEN | X31: Father | Y31: RANI BEN | Z31: Mother | AA31: Non-Veg | AB31: Non-Veg | AC31: Non-Veg | AD31: Bus Drop Service not needed
A32: 46260.359 | B32: monalisa.biochem_pgt23@aiimskalyani.edu.in | C32: DR. MONALISA MAHAJAN | D32: 20230319 | E32: MD/MS/MDS 2023 | F32: 9531754461 | G32: monalisa.biochem_pgt23@aiimskalyani.edu.in | H32: Yes | I32: Art and craft | K32: Bankura | L32: https://drive.google.com/open?id=1Bjvem_I_ilRINZh5ay3Gh2MmbqyI_ZM5 | M32: https://drive.google.com/open?id=1w5oxEG3Y_3QnTCazzcYgvScpQnlHlUCB | N32: MADHAB KUMAR MAHAJAN | O32: BANK MANAGER (RETIRED) | P32: BANKURA | Q32: 9474185735 | R32: SOMA MAHAJAN | S32: HOME MAKER | T32: BANKURA | U32: 9475346936 | V32: 2 | W32: MADHAB KUMAR MAHAJAN | X32: FATHER | Y32: SOMA MAHAJAN | Z32: MOTHER | AA32: Non-Veg | AB32: Non-Veg | AC32: Non-Veg | AD32: Bus Drop Service not needed
A33: 46260.495 | B33: priyanka.bscnursing-2021@aiimskalyani.edu.in | C33: PRIYANKA | D33: 20210240 | E33: B.Sc (Hons) Nursing 2021 | F33: 9521473400 | G33: priyankasura11@gmail.com | H33: No
A34: 46260.558 | B34: subhodip.mbbs-2020@aiimskalyani.edu.in | C34: SUBHODIP DAS | D34: 101/202001151 | E34: MBBS 2020 | F34: 9679602964 | G34: subhodip.mbbs-2020@aiimskalyani.edu.in | H34: Yes | I34: Strong interest in football and video gaming. | J34: Football | K34: Asansol | L34: https://drive.google.com/open?id=1P6zVDGzkvgIb6Tdpk3ftQTaZgIxa5RHn | M34: https://drive.google.com/open?id=1pWB5DAklFhIBCDY88-lVSMw6USUqOUwf | N34: Uday Chand Das | O34: Retired Railway Personal | P34: Asansol | Q34: 7365841536 | R34: Archana Das | S34: Housewife | T34: Asansol | U34: 9832715653 | V34: 2 | W34: Uday Chand Das | X34: Father | Y34: Archana Das | Z34: Mother | AA34: Non-Veg | AB34: Non-Veg | AC34: Non-Veg | AD34: Bus Drop Service not needed | AE34: 0
A35: 46260.618 | B35: saravana.dentistry_pgt23@aiimskalyani.edu.in | C35: B.SARAVANA PRATHAP | D35: 20230313 | E35: MD/MS/MDS 2023 | F35: 9789409492 | G35: saravana.dentistry_pgt23@aiimskalyani.edu.in | H35: Yes | K35: Coimbatore | L35: https://drive.google.com/open?id=1thgAXDqCeAa3Di76_D8nIFLshDuiWyFK | M35: https://drive.google.com/open?id=1y7cM_212CUes9lf3DFTsE1oQt_gVIrf- | N35: C.Balachandran | O35: - | P35: - | Q35: 9566607472 | R35: B.Parvathi | S35: House wife | T35: Coimbatore | U35: 9566607472 | V35: 0 | AA35: Veg | AD35: Bus Drop Service not needed | AE35: 0
A36: 46260.675 | B36: megha.mbbs-2020@aiimskalyani.edu.in | C36: MEGHA HAZARIKA | D36: 202001112 | E36: MBBS 2020 | F36: 9518596484 | G36: meghahazarika270701@gmail.com | H36: Yes | I36: Dancing, Poetry | K36: Guwahati | L36: https://drive.google.com/open?id=1nBinud0RE0f_0prwiaAI5ZZNJcp5dUd7 | M36: https://drive.google.com/open?id=17NwuQxURpwnFXAM2DiR5BSKfqwrc4IpS | N36: Dr. Alokesh Hazarika | O36: Retired as CMO In-charge | P36: Dibrugarh | Q36: 9975994611 | R36: Shivani Hazarika | S36: Home maker | T36: Agra | U36: 9421192706 | V36: 2 | W36: Dr. Alokesh Hazarika | X36: Father | Y36: Diya | Z36: Cousin | AA36: Veg | AB36: Veg | AC36: Non-Veg | AD36: Bus Drop Service not needed | AE36: 0
A37: 46260.695 | B37: divyansh.mbbs-2020@aiimskalyani.edu.in | C37: DIVYANSH CHARAN | D37: 202001168 | E37: MBBS 2020 | F37: 8824714602 | G37: divyansh.mbbs-2020@aiimskalyani.edu.in | H37: Yes | I37: Singing | K37: Pali, Rajasthan | L37: https://drive.google.com/open?id=1I2vyciA0tArPcdiQVStjSbGUrAuBO1gl | M37: https://drive.google.com/open?id=18ktayzQ3enUk0YBzZUCarsxwHROZtm_i | N37: Mahesh Singh | O37: Police Inspector | P37: Jaipur | Q37: 9829045528 | R37: Kiran Charan | S37: Yoga Instructor | T37: Jaipur | U37: 9799096666 | V37: 2 | W37: Kiran Charan | X37: Mother | Y37: Mahesh Singh | Z37: Father | AA37: Veg | AB37: Veg | AC37: Veg | AD37: Bus Drop Service not needed | AE37: 0
A38: 46260.72 | B38: shraddha.mbbs-2020@aiimskalyani.edu.in | C38: SHRADDHA MATSYAPAL | D38: 93/202001143 | E38: MBBS 2020 | F38: 8319646271 | G38: shraddha.mbbs-2020@aiimskalyani.edu.in | H38: Yes | I38: Dancing, sketching and traveling | K38: Dhamtari | L38: https://drive.google.com/open?id=1IGN8QQZm9ZLtGrUOJzX5EeRq2LTFOeS9 | M38: https://drive.google.com/open?id=1sEgVY-mkTmcFAlq_VHH_zH8V7NRcRTZB | N38: Hemant Matsyapal | O38: Additional Collector | P38: Dhamtari | Q38: 9424220390 | R38: Ishwari Matsyapal | S38: Teacher | T38: Dhamtari | U38: 9406373960 | V38: 1 | W38: Ishwari Matsyapal | X38: Mother | AA38: Non-Veg | AB38: Non-Veg | AD38: Bus Drop Service not needed | AE38: 0
A39: 46260.721 | B39: ananya.mbbs-2020@aiimskalyani.edu.in | C39: ANANYA ARYANKITA | D39: 20200164 | E39: MBBS 2020 | F39: 9078841355 | G39: aryankita5@gmail.com | H39: Yes | I39: Reading novels, painting | J39: 1st position in 1st year MBBS professional exams. 3rd position in 4th year MBBS professional exams. | K39: Bhubaneswar | L39: https://drive.google.com/open?id=17b6bIqVkWSIkAmF68CQSxQ6jnC29-46V | M39: https://drive.google.com/open?id=15mg3M5L4ukDORUqgR1KRrFy6NNLA9FaA | N39: Krishna Prasad Samantaray | O39: Bank employee, Assistant General Manager | P39: Bhubaneswar | Q39: 9937014472 | R39: Jyotirmayee Nayak | S39: Homemaker | T39: Bhubaneswar | U39: 9937732588 | V39: 2 | W39: Krishna Prasad Samantaray | X39: Father | Y39: Jyotirmayee Nayak | Z39: Mother | AA39: Veg | AB39: Veg | AC39: Veg | AD39: Bus Drop Service not needed | AE39: 0
A40: 46260.835 | B40: paromitaghoshal10@gmail.com | C40: PAROMITA GHOSHAL | D40: 20210234 | E40: B.Sc (Hons) Nursing 2021 | F40: 6289704330 | G40: paromitaghoshal10@gmail.com | H40: Yes | I40: Listening music | J40: None | K40: Baruipur | L40: https://drive.google.com/open?id=1ndP96MZXOCBl_KkpL18Kdf8jW7Rmw5yY | M40: https://drive.google.com/open?id=1Nw6P4AOw8_4vSJ2OdAQZZ2qgMF3T045K | N40: Prabir Kumar Ghoshal | O40: Service | P40: Baruipur | Q40: 9836179253 | R40: Purnima Ghoshal | S40: Homemaker | T40: Baruipur | U40: 8013378159 | V40: 2 | W40: Prabir Kumar Ghoshal | X40: Father | Y40: Purnima Ghoshal | Z40: Mother | AA40: Non-Veg | AB40: Non-Veg | AC40: Non-Veg | AD40: Bus Drop Service not needed
A41: 46260.851 | B41: puspitatitli@gmail.com | C41: PUSPITA BISWAS | D41: 20210242 | E41: B.Sc (Hons) Nursing 2021 | F41: 7001892495 | G41: puspitatitli@gmail.com | H41: Yes | I41: Listening to music and singing | J41: 2nd position in Inter College Quiz Competition in LIMBUS, 2024 2nd position in Quiz competition in annual interhouse competition, 2024 | K41: Adra, Purulia, West Bengal | L41: https://drive.google.com/open?id=12BNG6P5xXWi32CK6CXgPf4UawJfUZFmi | M41: https://drive.google.com/open?id=1YVDOVy1dIyuZ3_6xtT8zIma4Kr9-z6Ab | N41: PINAKI BISWAS | O41: Assistant Divisional Electrical Engineer (ADEE), South Eastern Railway. | P41: Jamshedpur, Jharkhand | Q41: 8967152595 | R41: KAKALI BISWAS | S41: Homemaker | T41: Jamshedpur, Jharkhand | U41: 7001663505 | V41: 2 | W41: KAKALI BISWAS | X41: Mother | Y41: PINAKI BISWAS | Z41: Father | AA41: Non-Veg | AB41: Non-Veg | AC41: Non-Veg | AD41: Drop at Kalyani Railway Station | AE41: 3
A42: 46261.441 | B42: priyakshi.bscnursing-2021@aiimskalyani.edu.in | C42: PRIYAKSHI SHARMA | D42: 20210239 | E42: B.Sc (Hons) Nursing 2021 | F42: 6002985622 | G42: sharmapriyakshi33@gmail.com | H42: No
A43: 46261.456 | B43: chingkhongsai00@gmail.com | C43: NEMBOICHING KHONGSAI | D43: 20210232 | E43: B.Sc (Hons) Nursing 2021 | F43: 7005655420 | G43: chingkhongsai00@gmail.com | H43: No
A44: 46261.465 | B44: kritirani09@gmail.com | C44: KRITI RANI | D44: 20210218 | E44: B.Sc (Hons) Nursing 2021 | F44: 8017475967 | G44: kritirani09@gmail.com | H44: Yes | I44: Reading, singing | K44: Patna, Kolkata | L44: https://drive.google.com/open?id=1EQsc_fYLaTRd_kbeacLyeEIpYs-q_N7E | M44: https://drive.google.com/open?id=1t7sh8VESGNONWELAVzkctbPURibtLjDj | N44: Om Prakash Sinha | O44: Senior Audit Officer | P44: Kolkata | Q44: 9339610211 | R44: Sujeeti Devi | S44: Homemaker | T44: Kolkata | U44: 9339980074 | V44: 2 | W44: Sujeeti Devi | X44: Mother | Y44: Om Prakash Sinha | Z44: Father | AA44: Veg | AB44: Veg | AC44: Non-Veg | AD44: Bus Drop Service not needed | AE44: 0
A45: 46261.479 | B45: krishnendu.mbbs-2020@aiimskalyani.edu.in | C45: Krishnendu Mondal | D45: 202001109 | E45: MBBS 2020 | F45: 6294794461 | G45: mondalkrish958@gmail.com | H45: Yes | I45: My favourite hobby is photography. I enjoy capturing beautiful moments, interesting places, and everyday scenes through my camera. Photography allows me to observe the world more carefully and express my creativity. It gives me a sense of relaxation and satisfaction, especially when I capture a picture exactly the way I imagined it. | K45: Bardhaman | L45: https://drive.google.com/open?id=1GIGpB-tlDRzkPCSVeWaPPwsNnFMrCLdR | M45: https://drive.google.com/open?id=1EGPEv54gplcZHH1Y3Nr8DfNpueu5PTVN | N45: Raghupati Mondal | O45: Teacher | P45: Bardhaman | Q45: 9732084464 | R45: Susmita Mondal | S45: Home Maker | T45: Bardhaman | U45: 8001666664 | V45: 2 | W45: Raghupati Mondal | X45: Father | Y45: Susmita Mondal | Z45: Mother | AA45: Non-Veg | AB45: Non-Veg | AC45: Non-Veg | AD45: Bus Drop Service not needed | AE45: 0
A46: 46261.53 | B46: mukherjeeadrita8@gmail.com | C46: ADRITA MUKHERJEE | D46: 20210202 | E46: B.Sc (Hons) Nursing 2021 | F46: 9382419184 | G46: mukherjeeadrita8@gmail.com | H46: Yes | I46: Drawing | J46: NIL | K46: MIDNAPORE | L46: https://drive.google.com/open?id=1oMT5M4kV0RkssJ0_QzythLc9C0HuyymA | M46: https://drive.google.com/open?id=1g5LOAHxF_ScybXMcwE2e_uMicFRl2JzV | N46: ANIRBAN MUKHERJEE | O46: SENIOR Technician Incharge signal department Railway employee kgp junction | P46: MIDNAPORE | Q46: 7595081828 | R46: MAHUA MUKHERJEE | S46: Housewife | T46: MIDNAPORE | U46: 9434139015 | V46: 2 | W46: ANIRBAN MUKHERJEE | X46: Father | Y46: MAHUA MUKHERJEE | Z46: Mother | AA46: Non-Veg | AB46: Veg | AC46: Non-Veg | AD46: Bus Drop Service not needed | AE46: 0
A47: 46261.65 | B47: nabanita.bscnursing-2021@aiimskalyani.edu.in | C47: NABANITA DE | D47: 20210259 | E47: B.Sc (Hons) Nursing 2021 | F47: 9163114520 | G47: denabanita2020@gmail.com | H47: Yes | I47: Singing | J47: Chess | K47: DumDum west bengal | L47: https://drive.google.com/open?id=1PfkJCRRfe6_PizYazTm6-jWa8yEryYt8 | M47: https://drive.google.com/open?id=1z0m__2Kf-p6DA6y2VeswitaQCVWSvvAf | N47: Nirapada De | O47: Retired Teacher | P47: DumDum west bengal | Q47: 9143568373 | R47: Sulekha De | S47: Teacher | T47: DumDum west bengal | U47: 9836581215 | V47: 2 | W47: Nirapada De | X47: Father | Y47: Sulekha De | Z47: Mother | AA47: Non-Veg | AB47: Non-Veg | AC47: Non-Veg | AD47: Drop at Kolkata Airport | AE47: 3
A48: 46261.694 | B48: jagruti.mbbs-2020@aiimskalyani.edu.in | C48: JAGRUTI BISWAL | D48: 53/202001103 | E48: MBBS 2020 | F48: 7848081502 | G48: jagruti.mbbs-2020@aiimskalyani.edu.in | H48: Yes | I48: Art and poster | K48: Khamar , Dist- Angul , Odisha | L48: https://drive.google.com/open?id=17ExJneL3SUtqC9Qf7axOqaajenbgeByB | M48: https://drive.google.com/open?id=10CRwIMWLrQ1rlIWdSN3Q5Rc9IDxk7hD_ | N48: Jayadeb Biswal | O48: Lecture in Physics | P48: Khamar ,Dist -Angul ,Odisha | Q48: 6370124355 | R48: Geetanjali Pradhan | S48: Teacher | T48: Khamar ,Dist -Angul ,Odisha | U48: 6372837323 | V48: 2 | W48: Jayadeb Biswal | X48: Father | Y48: Geetanjali Pradhan | Z48: Mother | AA48: Veg | AB48: Veg | AC48: Veg | AD48: Bus Drop Service not needed
A49: 46261.709 | B49: chandakumari01122002@gmail.com | C49: Chanda Kumari | D49: 20210209 | E49: B.Sc (Hons) Nursing 2021 | F49: 9142488342 | G49: chandakumari01122002@gmail.com | H49: No
A50: 46261.725 | B50: abhishek.comjnmh@gmail.com | C50: Abhishek Kumar Giri | D50: 20230316 | E50: MD/MS/MDS 2023 | F50: 7686943337 | G50: ABHISHEK.COMJNMH@GMAIL.COM | H50: Yes | K50: Kolkata | L50: https://drive.google.com/open?id=1CQbRk21X5nqkp45p_2xoY_EvlMSNqf-n | M50: https://drive.google.com/open?id=1f5C8dZdGLRKVJM6yCk1O-96zo49IXahL | N50: HRIDYA SHANKER GIRI | O50: Advocate | P50: Kolkata | Q50: 9430010033 | R50: Rani Giri | S50: House wife | T50: Kalyani | U50: 7258843968 | V50: 2 | W50: HRIDYA SHANKER GIRI | X50: Father | Y50: Rani Giri | Z50: Mother | AA50: Non-Veg | AB50: Non-Veg | AC50: Non-Veg | AD50: Bus Drop Service not needed | AE50: 0
A51: 46261.732 | B51: kshetrimayum.micro_pgt23@aiimskalyani.edu.in | C51: KSHETRIMAYUM AMMY | D51: 2023036 | E51: MD/MS/MDS 2023 | F51: 8979219518 | G51: kshetrimayum.micro_pgt23@aiimskalyani.edu.in | H51: Yes | K51: Manipur | L51: https://drive.google.com/open?id=1oTJeS8X8zWGi3Pgc67CPklkSSF98dFZT | M51: https://drive.google.com/open?id=1l5rZmmtfg3Bm95Nn38SAfiFNS5hhXCD7 | N51: Kshetrimayum Topeswor Singh | O51: Business | P51: Imphal | Q51: 9436026654 | R51: Kshetrimayum (O) Meiteileima Devi | S51: Senior accountant | T51: Imphal | U51: 9436026559 | V51: 0 | AA51: Non-Veg | AD51: Bus Drop Service not needed | AE51: 0
A52: 46261.75 | B52: ashok.mbbs-2020@aiimskalyani.edu.in | C52: ASHOK KUMAR | D52: 20200177 | E52: MBBS 2020 | F52: 9610132738 | G52: ashok.mbbs-2020@aiimskalyani.edu.in | H52: Yes | I52: Playing cricket | J52: Cricket | K52: Gudamalani, Barmer, Rajasthan | L52: https://drive.google.com/open?id=1DCVm9ykzqDErz0EjbdSm9jvVk0ZLCDza | M52: https://drive.google.com/open?id=1TUTEY9I_2s5assnVLiXCGzIDtFy0AZ6k | N52: BAGA RAM | O52: Farmer | P52: Gudamalani | Q52: 9610132738 | R52: LEELU DEVI | S52: Housewife | T52: Gudamalani | U52: 9549454347 | V52: 1 | W52: ISHWAR | X52: Brother | AA52: Veg | AB52: Veg | AC52: Veg | AD52: Bus Drop Service not needed | AE52: 0
A53: 46261.843 | B53: abil.mbbs-2020@aiimskalyani.edu.in | C53: ABIL KUMAR | D53: 20200152 | E53: MBBS 2020 | F53: 9671886427 | G53: abhisaini00011@gmail.com | H53: Yes | K53: Yamunanagar (haryana) | L53: https://drive.google.com/open?id=1zwdEFcV9P321Q6Jkzx-Cv1wnMXEHxajP | M53: https://drive.google.com/open?id=1IFG8feelFIXlMM6oKKg5CWGBzzIZIh4e | N53: Jaikishan saini | O53: Engineer | P53: Yamunanagar ( Haryana) | Q53: 8059817590 | R53: Raj dulari | S53: Homemaker | T53: Yamunanagar (Haryana) | U53: 8168011490 | V53: 0 | AA53: Veg | AD53: Bus Drop Service not needed | AE53: 0
A54: 46261.977 | B54: sanandaavidipta@gmail.com | C54: SANANDA DAS | D54: 20210244 | E54: B.Sc (Hons) Nursing 2021 | F54: 9330715505 | G54: sanandaavidipta@gmail.com | H54: Yes | I54: Listening music , crafting | K54: Tarakeswar | L54: https://drive.google.com/open?id=1z1xB5-MdjChXJLkgsNr-19kq0-G3lMxB | M54: https://drive.google.com/open?id=1oAextmrjXqAddypCl1SQWYtScP-7FjVd | N54: Sushanta Das | O54: Retired subedar Major from Indian Army | P54: Tarakeswar | Q54: 6284416397 | R54: Piyali Das | S54: Home maker | T54: Tarakeswar | U54: 8910037049 | V54: 2 | W54: Sushanta Das | X54: Father | Y54: Piyali Das | Z54: Mother | AA54: Non-Veg | AB54: Non-Veg | AC54: Non-Veg | AD54: Drop at Kalyani Railway Station | AE54: 3
A55: 46261.985 | B55: bidisha.bscnursing-2021@aiimskalyani.edu.in | C55: BIDISHA CHUNARI | D55: 20210208 | E55: B.Sc (Hons) Nursing 2021 | F55: 6295520563 | G55: bidishachunari46@gmail.com | H55: Yes | I55: Singing and dancing | K55: Krishnanagar | L55: https://drive.google.com/open?id=1bwx5q9n2bwNAABsvPhSADC1hY7hWzzHG | M55: https://drive.google.com/open?id=1wrF__61hq-wpg3zhkDMrs0OSYRla9JTh | N55: Botan Chunari | O55: Retired Service man | P55: Krishnanagar | Q55: 8348678398 | R55: Pintu Chunari | S55: Homemaker | T55: Krishnanagar | U55: 9475821651 | V55: 2 | W55: Botan Chunari | X55: Father | Y55: Pintu Chunari | Z55: Mother | AA55: Non-Veg | AB55: Non-Veg | AC55: Non-Veg | AD55: Drop at Kalyani Railway Station | AE55: 3
A56: 46262.39 | B56: akshay.mbbs-2020@aiimskalyani.edu.in | C56: AKSHAY SHARMA | D56: 20200157 | E56: MBBS 2020 | F56: 8016283467 | G56: xaysharma6365@gmail.com | H56: Yes | I56: Sports | J56: Cricket | K56: Sikar | L56: https://drive.google.com/open?id=1ItmdZQFTymSYMMTI1_Y7PkbVoZ62MP4z | M56: https://drive.google.com/open?id=1E0Vszup2lQLfdpgMIBj2WugQ756uMslC | N56: Anil Kumar Sharma | O56: Farmer | P56: Sikar | Q56: 8016283467 | R56: Kiran Sharma | S56: House maker | T56: Sikar | U56: 8016283467 | V56: 2 | W56: Kiran Sharma | X56: Mother | Y56: Anil kumar sharma | Z56: Father | AA56: Veg | AB56: Veg | AC56: Veg | AD56: Bus Drop Service not needed | AE56: 0
A57: 46262.417 | B57: sanandaavidipta@gmail.com | C57: SANANDA DAS | D57: 20210244 | E57: B.Sc (Hons) Nursing 2021 | F57: 9330715505 | G57: sanandaavidipta@gmail.com | H57: Yes | I57: Listening music, crafting (hobbies) | J57: NA | K57: Tarakeswar | L57: https://drive.google.com/open?id=1mByFASwogNgPgDp3ASra5Yi99XMaHEJr | M57: https://drive.google.com/open?id=1fZ5OB9vLnev-bJ1nlJk4fGZXjbpDEO-c | N57: Sushanta Das | O57: Retired Subedar Major from Indian Army | P57: Tarakeswar | Q57: 6284416397 | R57: Piyali Das | S57: House wife | T57: Tarakeswar | U57: 8910037049 | V57: 2 | W57: Sushanta Das | X57: Father | Y57: Piyali Das | Z57: Mother | AA57: Non-Veg | AB57: Non-Veg | AC57: Non-Veg | AD57: Drop at Kalyani Railway Station | AE57: 3
A58: 46262.418 | B58: chingkhongsai00@gmail.com | C58: NEMBOICHING KHONGSAI | D58: 20210232 | E58: B.Sc (Hons) Nursing 2021 | F58: 7005655420 | G58: chingkhongsai00@gmail.com | H58: No
A59: 46262.49 | B59: nilesh.mbbs-2020@aiimskalyani.edu.in | C59: NILESH BHARTI | D59: 202001116 | E59: MBBS 2020 | F59: 7292903856 | G59: nilesh.mbbs-2020@aiimskalyani.edu.in | H59: Yes | K59: Samastipur, Bihar | L59: https://drive.google.com/open?id=1KztgL8OEke4hZZMua6o0pKtkGrhe4WAN | M59: https://drive.google.com/open?id=16QJxFRyFat2-vQbJCjTv_aoucODfuX6d | N59: Ashok Kumar Choudhary | O59: Grocery Shop | P59: Samastipur, Bihar | Q59: 8210741328 | R59: Sudha Rani | S59: House wife | T59: Samastipur, Bihar | U59: 9934034117 | V59: 2 | W59: Ashok Kumar Choudhary | X59: Father | Y59: Sudha Rani | Z59: Mother | AA59: Non-Veg | AB59: Veg | AC59: Veg | AD59: Bus Drop Service not needed | AE59: 0
A60: 46262.493 | B60: ananyap.mbbs-2020@aiimskalyani.edu.in | C60: ANANYA PANDEY | D60: 20200165 | E60: MBBS 2020 | F60: 8855042775 | G60: quantum101p@gmail.com | H60: Yes | K60: Ahilyanagar,Maharashtra | L60: https://drive.google.com/open?id=1HfIVNeMB_ECzHMzWa-6GJ_qgAMlIU_n0 | M60: https://drive.google.com/open?id=1PFDlujHx6D2q1D7mezqt7rCMaq5Nffsv | N60: PROVASH CHANDRA PANDEY | O60: Station Manager, Akolner, Maharashtra | P60: Ahilyanagar, Maharashtra | Q60: 7397872775 | R60: BITHIKA PANDEY | S60: Pharmacy buiseness | T60: Ahilyanagar, Maharashtra | U60: 8983503476 | V60: 2 | W60: Bithika Pandey | X60: Mother | Y60: Aditi Pandey | Z60: Sister | AA60: Veg | AB60: Non-Veg | AC60: Non-Veg | AD60: Drop at Kolkata Airport | AE60: 3
A61: 46262.498 | B61: manisha.mbbs-2020@aiimskalyani.edu.in | C61: MANISHA KANWAR | D61: 202001172 | E61: MBBS 2020 | F61: 8100143700 | G61: manisha.mbbs-2020@aiimskalyani.edu.in | H61: Yes | K61: Nagaur Rajasthan | L61: https://drive.google.com/open?id=1rAVplwsISXN9YIFzRlgWKf7L2pj15DSl | M61: https://drive.google.com/open?id=1KSVGFNkqmgnIfvuHe2oNtxoHgQth5juD | N61: Mool Singh | O61: Businessman | P61: Nagaur Rajasthan | Q61: 8100143700 | R61: Kiran Kanwar | S61: Homemaker | T61: Nagaur Rajasthan | U61: 7976150128 | V61: 2 | W61: Mool Singh | X61: Father | Y61: Kiran Kanwar | Z61: Mother | AA61: Veg | AB61: Veg | AC61: Veg | AD61: Bus Drop Service not needed | AE61: 0
A62: 46262.604 | B62: rajpurohitnagina@gmail.com | C62: NAGEENA KANWAR | D62: 20210226 | E62: B.Sc (Hons) Nursing 2021 | F62: 8239420354 | G62: rajpurohitnagina@gmail.com | H62: No
A63: 46262.607 | B63: nandini.bscnursing-2021@aiimskalyani.edu.in | C63: NANDINI DAS | D63: 20210228 | E63: B.Sc (Hons) Nursing 2021 | F63: 7029310734 | G63: nandini.bscnursing-2021@aiimskalyani.edu.in | H63: No
A64: 46262.619 | B64: aprajitapal01@gmail.com | C64: Aprajita Pal | D64: 20230401 | E64: M.Sc. Nursing 2023 | F64: 8294678844 | G64: aprajitapal01@gmail.com | H64: Yes | I64: Reading and gardening | K64: Bhagalpur | L64: https://drive.google.com/open?id=1r_tAll3oKhxHO6BWB4Hy0FpJ9xy06lPP | M64: https://drive.google.com/open?id=1GHxARDGpeigN3bmOaGRUMWlmc6f6V254 | N64: Subodh Kumar Pal | O64: Retired Govt Teacher | P64: Bhagalpur | Q64: 9931406986 | R64: Pushpa Rajpali | S64: Homemaker | T64: Bhagalpur | U64: 8102463085 | V64: 2 | W64: Subodh Kumar Pal | X64: Father | Y64: Pushpa Rajpali | Z64: Mother | AA64: Non-Veg | AB64: Veg | AC64: Veg | AD64: Drop at Kalyani Railway Station | AE64: 2
A65: 46262.677 | B65: prabesh.mbbs-2020@aiimskalyani.edu.in | C65: PRABESH KUMAR SAHU | D65: 68/202001118 | E65: MBBS 2020 | F65: 7752071706 | G65: prabeshk99@gmail.com | H65: Yes | I65: Bike riding, Music | J65: ICMR STS 2022 | K65: Bahalda, Mayurbhanj, Odisha | L65: https://drive.google.com/open?id=1hhVYne8osDPO8Bx14dmu7ItoD8rDQomg | M65: https://drive.google.com/open?id=1OSErYJ1q5eyzKWBvZ-27mXecsNEeej7i | N65: Mr Ananda Bihari Sahu | O65: Business | P65: Bahalda, Mayurbhanj, Odisha | Q65: 9777507049 | R65: Mrs Mamata Sahu | S65: Homemaker | T65: Bahalda, Mayurbhanj, Odisha | U65: 7978063537 | V65: 2 | W65: Mr Ananda Bihari Sahu | X65: Father | Y65: Mrs Mamata Sahu | Z65: Mother | AA65: Non-Veg | AB65: Veg | AC65: Veg | AD65: Drop at Kalyani Railway Station | AE65: 3
A66: 46262.689 | B66: naman.mbbs-2020@aiimskalyani.edu.in | C66: NAMAN CHUGH | D66: 65/202001115 | E66: MBBS 2020 | F66: 7015830025 | G66: naman.mbbs-2020@aiimskalyani.edu.in | H66: Yes | I66: Playing Table tennis, cricket, drums. Participating in quizzes | J66: 1st position in interhouse Table tennis and cricket | K66: Gohana | L66: https://drive.google.com/open?id=1xwTvH0UHuOuHTemjNyYAvkgpCvGtFFUq | M66: https://drive.google.com/open?id=1H_khFxRF9EcRpryKoyQHwFotoxkr_7f7 | N66: Madan Chugh | O66: Businessman | P66: Gohana | Q66: 9416314424 | R66: Geeta Chugh | S66: Teacher | T66: Gohana | U66: 9812467167 | V66: 2 | W66: Madan Chugh | X66: Father | Y66: Geeta Chugh | Z66: Mother | AA66: Non-Veg | AB66: Veg | AC66: Veg | AD66: Bus Drop Service not needed | AE66: 0
A67: 46262.836 | B67: mansi.singh2021@gmail.com | C67: DR MANSHI KUMARI | D67: 2023037 | E67: MD/MS/MDS 2023 | F67: 8207207670 | G67: mansi.singh2021@gmail.com | H67: Yes | K67: VARANASI,UTTAR PRADESH | L67: https://drive.google.com/open?id=1nKfebNHsjLdXOG-kfFUb6nUXdGBLIZ90 | M67: https://drive.google.com/open?id=18sG2dhPmRPBY_1avWO-Ok0VgU7YGhMMr | N67: MR. RAJ KUMAR SINGH | O67: CIVIL ENGINEER | P67: AURANGABAD,BIHAR | Q67: 9801120313 | R67: GEETA SINGH | S67: HOUSE WIFE | T67: AURANGABAD,BIHAR | U67: 9199013095 | V67: 2 | W67: MR.RAJ KUMAR SINGH | X67: FATHER | Y67: DR RISHI SINGH | Z67: HUSBAND | AA67: Veg | AB67: Veg | AC67: Non-Veg | AD67: Bus Drop Service not needed | AE67: 0
A68: 46262.882 | B68: sonam.bscnursing-2021@aiimskalyani.edu.in | C68: SONAM KUMARI | D68: 20210250 | E68: B.Sc (Hons) Nursing 2021 | F68: 8404882688 | G68: sonamriva20@gmail.com | H68: Yes | I68: Traveling and photography | J68: Chess and volleyball | K68: Bihar | L68: https://drive.google.com/open?id=1AboCbMf3z59BPRrgyU-WmaaHQXIfcFWl | M68: https://drive.google.com/open?id=1bWTUr93keviUY0wPZjsrGyOdNGtayJXM | N68: Ranjan Kumar | O68: Businessmen | P68: Bhagalpur | Q68: 9931076395 | R68: Rani Devi | S68: Homemaker | T68: Bhagalpur | U68: 7488505863 | V68: 2 | W68: Ranjan Kumar | X68: Father | Y68: Rani Devi | Z68: Mother | AA68: Non-Veg | AB68: Non-Veg | AC68: Veg | AD68: Bus Drop Service not needed | AE68: 0
A69: 46263 | B69: bharathkrishna500@gmail.com | C69: BHARATH KRISHNA | D69: 20200186 | E69: MBBS 2020 | F69: 9526106877 | G69: bharathkrishna500@gmail.com | H69: Yes | I69: Football, Drawing, Watching series | J69: One time winner of football house tournament | K69: Kerala | L69: https://drive.google.com/open?id=1mooE5TomVolzpVAYGxoBnfGZoiuiEYwa | M69: https://drive.google.com/open?id=1b1VAZPhPPMzCLahin7wlrEP6ooPciPU1 | N69: M.Somaprasad | O69: Branch manager united india insurance( Retired ) | P69: Malappuram, kerala | Q69: 9447106877 | R69: Bindu s menon | S69: Higher secondary school teacher(retired) | T69: Malappuram,kerala | U69: 9447289191 | V69: 1 | W69: Bindu s menon | X69: Mother | AA69: Non-Veg | AB69: Non-Veg | AD69: Bus Drop Service not needed | AE69: 0
A70: 46263.411 | B70: avtans.mbbs-2020@aiimskalyani.edu.in | C70: Avtans Khajuria | D70: 20200180 | E70: MBBS 2020 | F70: 9622113289 | G70: avtans.mbbs-2020@aiimskalyani.edu.in | H70: Yes | I70: Playing volleyball and Travelling | K70: Kathua J and K | L70: https://drive.google.com/open?id=19LVDSS8uhFIpMrRJFs2VDpOruOFW8x7D | M70: https://drive.google.com/open?id=1WUfTc0UTv4bn9f4QhA9YscJZ_gz2Dfu7 | N70: Pawan Kumar | O70: Government Lecturer | P70: Kathua J and K | Q70: 7889551033 | R70: Sudha Bala | S70: Government Teacher | T70: Kathua J and K | U70: 7889872015 | V70: 0 | AA70: Veg | AD70: Drop at Kolkata Airport | AE70: 1
A71: 46263.424 | B71: grace.ophthal_pgt23@aiimskalyani.edu.in | C71: GRACE LHINGHOITHEM HAOKIP | D71: 2023033 | E71: MD/MS/MDS 2023 | F71: 9831529419 | G71: gracehaokip8@gmail.com | H71: Yes | K71: CHURACHANDPUR , MANIPUR | L71: https://drive.google.com/open?id=1tJzycF8wTukxcHtvCxx2YjnVGm2tWdib | M71: https://drive.google.com/open?id=1s9Ebe8xltDlsotZ3crK3wUEUpXtRXJoA | N71: (L) T ALUN HAOKIP | O71: None | P71: None | Q71: 8014502465 | R71: LALAM HAOKIP | S71: HOMEMAKER | T71: CHURACHANDPUR,MANIPUR | U71: 8014502465 | V71: 2 | W71: LALAM HAOKIP | X71: MOTHER | Y71: NENGZALAM | Z71: GRANDMOTHER | AA71: Non-Veg | AB71: Non-Veg | AC71: Non-Veg | AD71: Bus Drop Service not needed | AE71: 0
A72: 46263.485 | B72: shifana.mbbs-2020@aiimskalyani.edu.in | C72: SHIFANA T | D72: 202001140 | E72: MBBS 2020 | F72: 6238885248 | G72: shifana.mbbs-2020@aiimskalyani.edu.in | H72: Yes | I72: Passionate about photography, videography, and creative editing, with a particular interest in capturing and preserving meaningful moments with friends and family. Created and dedicated a farewell documentary for the senior batch, which was deeply appreciated and emotionally memorable for everyone. I enjoy cooking and exploring different cuisines, applying mehendi, spending time with children, and maintaining an active lifestyle through regular gym workouts. Naturally curious and enthusiastic about experiencing new things, exploring diverse interests, and continuously learning new skills, including activities such as skating. I value kindness, empathy, and friendly communication, and enjoy building a warm and comfortable rapport with patients. Research & Academic Achievement Published a research paper in Pathology . "Comparative Evaluation of Gram Stain and Conventional Pap Stain in Diagnosing Bacterial Vaginosis and Candidiasis: A Cross-Sectional Study". | J72: Actively involved in sports and cultural activities. Secured 1st Prize in Kho-Kho and Musical Chairs, and participated in marathons, running events, badminton, cycling races, tug of war, and lemon and spoon races. Enthusiastically participated in college fests, drama, and dance events. | K72: Kerala | L72: https://drive.google.com/open?id=1j_6KyPRejnXCr7eFpem9o5GnC1qR6c77 | M72: https://drive.google.com/open?id=1OkLu-ptgMZQw7pT7GsaSjllY8wXroPNL | N72: Muhammedali T | O72: Business man | P72: Palakkad, Kerala | Q72: 9946362171 | R72: Mariya PT | S72: Home-maker | T72: Palakkad, Kerala | U72: 9747151399 | V72: 2 | W72: Mariya PT | X72: Mother | Y72: Abdul Vahid T | Z72: Brother | AA72: Non-Veg | AB72: Non-Veg | AC72: Non-Veg | AD72: Drop at Kalyani Railway Station | AE72: 1
A73: 46263.506 | B73: basira.bscnursing-2021@aiimskalyani.edu.in | C73: BASIRA SULTANA | D73: 20210207 | E73: B.Sc (Hons) Nursing 2021 | F73: 8945998122 | G73: sultanabasira803@gmail.com | H73: Yes | I73: Reading novels, Gardening | J73: No | K73: Bagnan, Howrah,west bengal | L73: https://drive.google.com/open?id=1VZYGH72dNxSBH5qzEkCmugohgZSlXur0 | M73: https://drive.google.com/open?id=1qRsZT9XjUPmj65nV7EWEiTNyeeUYSqZ2 | N73: SK ABUL BASAR | O73: School Teacher, HM (MSK) | P73: Bagnan, Howrah, west bengal | Q73: 9073939324 | R73: SABINA IYASMIN BEGAM | S73: House wife | T73: Bagnan, Howrah,west bengal | U73: 8945998122 | V73: 2 | W73: SK ABUL BASAR | X73: Father | Y73: SABINA IYASMIN BEGAM | Z73: Mother | AA73: Non-Veg | AB73: Non-Veg | AC73: Veg | AD73: Bus Drop Service not needed | AE73: 0
A74: 46263.568 | B74: sushmita.bscnursing-2021@aiimskalyani.edu.in | C74: SUSHMITA MONDAL | D74: 20210255 | E74: B.Sc (Hons) Nursing 2021 | F74: 7501786976 | G74: sushmitadna21@gmail.com | H74: Yes | I74: My hobbies and interests include reading, cooking, gardening and learning new things. In my free time, I like listening to music and spending quality time with my friends and family. I am always interested in developing new skills and improving both my personal and professional knowledge. Most importantly, whatever I do, I always strive to be happy and find joy and satisfaction in my life. | K74: Bagnan | L74: https://drive.google.com/open?id=1VJfeqrPpNmHa7SscTL8KCgUhAQiYU0Bx | M74: https://drive.google.com/open?id=1ajWQ3Z9aqj-RCpDrIAOXZH9HlJ2IIePU | N74: Tapas Mondal | O74: Farmer | P74: Bagnan | Q74: 7384357354 | R74: Namita Mondal | S74: Housewife | T74: Bagnan | U74: 8926111922 | V74: 2 | W74: Tapas Mondal | X74: Father | Y74: Namita Mondal | Z74: Mother | AA74: Non-Veg | AB74: Non-Veg | AC74: Non-Veg | AD74: Bus Drop Service not needed | AE74: 0
A75: 46263.572 | B75: rajshree.mbbs-2020@aiimskalyani.edu.in | C75: RAJSHREE | D75: 202001123 | E75: MBBS 2020 | F75: 6204953438 | G75: rajshree.mbbs-2020@aiimskalyani.edu.in | H75: Yes | K75: Patna, Bihar | L75: https://drive.google.com/open?id=1AEJWkIp2CdrFco8TmKGNB1wVy_07lL4i | M75: https://drive.google.com/open?id=1LZgv0JIoYsZBwvvIYjddDlYni48T09th | N75: Satish Kumar Verma | O75: Teacher ;Post Graduate Teacher( Physics) | P75: Patna | Q75: 9006630469 | R75: Ribha Kumari | S75: House wife | T75: Patna | U75: 8603283341 | V75: 2 | W75: Satish Kumar Verma | X75: Father | Y75: Ribha Kumari | Z75: Mother | AA75: Veg | AB75: Non-Veg | AC75: Veg | AD75: Bus Drop Service not needed | AE75: 0
A76: 46263.635 | B76: dipanjana.bscnursing-2021@aiimskalyani.edu.in | C76: DIPANJANA DEY | D76: 20210212 | E76: B.Sc (Hons) Nursing 2021 | F76: 6290455131 | G76: dipanjanad597@gmail.com | H76: Yes | I76: Listening Songs | K76: Madhyamgram | L76: https://drive.google.com/open?id=1MX9mhWJba8vTZsXTJGPr9vDlJyHZR8hZ | M76: https://drive.google.com/open?id=1vGFtlfh3GEMhuu440tPrjxHtpLkTnhSb | N76: DINABANDHU DEY | O76: Ex-Senior section Engineer/Eastern Railway/HQ | P76: Madhyamgram | Q76: 8981357710 | R76: Lt. Archita Dey | S76: House wife | T76: Madhyamgram | U76: 6290404676 | V76: 2 | W76: DINABANDHU DEY | X76: Father | Y76: Arup Dutta | Z76: Maternal Uncle | AA76: Non-Veg | AB76: Non-Veg | AC76: Non-Veg | AD76: Drop at Kolkata Airport | AE76: 2
A77: 46263.643 | B77: sarmin.bscnursing-2021@aiimskalyani.edu.in | C77: SARMIN SULTANA | D77: 20210247 | E77: B.Sc (Hons) Nursing 2021 | F77: 8436365622 | G77: sarmins2000@gmail.com | H77: Yes | I77: Reading books, listening music | K77: Barasat | L77: https://drive.google.com/open?id=1ayNmTeBQYcJdKiZR6EGzzcRuTQQTE9qU | M77: https://drive.google.com/open?id=1ZD3z5nf0pwc96d1HX7jqSXfk-ERO4_Oe | N77: BABLU MONDAL | O77: Bussiness | P77: Barasat | Q77: 8641982215 | R77: SAYRA KHATUN | S77: Para teacher | T77: Barasat | U77: 9143218559 | V77: 2 | W77: Bablu Mondal | X77: Father | Y77: Sayra khatun | Z77: Mother | AA77: Non-Veg | AB77: Non-Veg | AC77: Non-Veg | AD77: Bus Drop Service not needed | AE77: 0
A78: 46263.907 | B78: shawmegha451@gmail.com | C78: MEGHA SHAW | D78: 20210222 | E78: B.Sc (Hons) Nursing 2021 | F78: 7908304766 | G78: shawmegha451@gmail.com | H78: Yes | I78: Cooking, Reading a story book , crafting and drawing | J78: Got A PRIZE IN QUIZE COMPETITION , Rangoli making poster competition, work as organizer in different cultural events | K78: Kakdwip,south 24 pargana west bengal | L78: https://drive.google.com/open?id=17BdUijWLObfbTAKpcHr9mXHy1RK5gi2- | M78: https://drive.google.com/open?id=1XJonGXteDH9udDMLlJGeP_HfJwqiofaj | N78: Raman kumar shaw | O78: Business man | P78: Kakdwip | Q78: 9932803251 | R78: Jyoti shaw | S78: Housewife | T78: Kakdwip | U78: 9733291683 | V78: 2 | W78: Raman Kumar shaw | X78: Father | Y78: Jyoti shaw | Z78: Mother | AA78: Non-Veg | AB78: Non-Veg | AC78: Non-Veg | AD78: Drop at Kalyani Railway Station | AE78: 3
A79: 46264.547 | B79: samyamitra120598@gmail.com | C79: SAMYA MITRA | D79: 20230311 | E79: MD/MS/MDS 2023 | F79: 8967968556 | G79: samyamitra120598@gmail.com | H79: Yes | K79: RAIGANJ | L79: https://drive.google.com/open?id=1oTU0HnOhbkuJ3RhdmOb9qEbpezYQDMQw | M79: https://drive.google.com/open?id=1X4JWLItu9ghafqaLSkURBJcu5eETQID- | N79: DEBASISH MITRA | O79: SCHOOL TEACHER | P79: RAIGANJ | Q79: 8101805849 | R79: PARAMITA MITRA | S79: HOUSE WIFE | T79: RAIGANJ | U79: 8597421076 | V79: 1 | W79: MADHUMITA GUHA | X79: AUNT | Y79: ANWESHA MITRA | Z79: SISTER | AA79: Non-Veg | AB79: Non-Veg | AC79: Non-Veg
A80: 46264.644 | B80: shivam.mbbs-2020@aiimskalyani.edu.in | C80: SHIVAM RAJESH CHAUHAN | D80: 202001141 | E80: MBBS 2020 | F80: 9958065849 | G80: shivam10chauhan@gmail.com | H80: Yes | I80: Badminton | K80: Gurgaon | L80: https://drive.google.com/open?id=1u8imoqsNrP_lVTtGQ21ZqWYQszN6ixOv | M80: https://drive.google.com/open?id=11SIoYQq9hiWtLLY_sLjDOh8TbZ9sutr4 | N80: Rajesh Chauhan | O80: Wooden packaging Business/ MBA | P80: Gurgaon | Q80: 9350905790 | R80: Sangam Chauhan | S80: House wife/ Graduation | T80: Gurgaon | U80: 8076650205 | V80: 2 | W80: Rajesh Chauhan | X80: Father | Y80: Sangam Chauhan | Z80: Mother | AA80: Veg | AB80: Veg | AC80: Veg | AD80: Bus Drop Service not needed
A81: 46264.649 | B81: anoushka.mbbs-2020@aiimskalyani.edu.in | C81: ANOUSHKA CHAUDHURY | D81: 18/20200168 | E81: MBBS 2020 | F81: 8777643438 | G81: aan012013@gmail.com | H81: Yes | I81: Classical dance, quizzing | J81: Received the ICMR Short Term Studentship (STS) grant 2022, Completed an 8-year Bharatnatyam course at Kalamandalam Calcutta | K81: Kolkata | L81: https://drive.google.com/open?id=1agx6ZfcmuLblPYU7OsUM2ZwLLKrSIMl7 | M81: https://drive.google.com/open?id=1HpMDpGCD4c3_33yBOdQz4f5MkCXQfSgn | N81: Kaushik Chaudhury | O81: Software Engineer | P81: Kolkata | Q81: 7980342566 | R81: Olli Chaudhury | S81: Teacher | T81: Kolkata | U81: 8981063590 | V81: 2 | W81: Olli Chaudhury | X81: Mother | Y81: Kaushik Chaudhury | Z81: Father | AA81: Non-Veg | AB81: Non-Veg | AC81: Non-Veg | AD81: Bus Drop Service not needed
A82: 46264.653 | B82: sashi.mscnursing-2023@aiimskalyani.edu.in | C82: SASHI BAG | D82: 20230406 | E82: M.Sc. Nursing 2023 | F82: 8018894955 | G82: sashi.mscnursing-2023@aiimskalyani.edu.in | H82: Yes | I82: Dancing | J82: N/A | K82: Nuapada, Odisha | L82: https://drive.google.com/open?id=152MAZpjZvThK43BIDbogZ9khRdPP5tJ0 | M82: https://drive.google.com/open?id=1O7FYjFhVrWKHFRQ9RAu1l5ijTF1IDO4C | N82: Narsing Bag | O82: Farmer | P82: Semeria, Nuapada, Odisha | Q82: 7077135656 | R82: Shakuntala Bag | S82: Homemaker | T82: Semeria, Nuapada, Odisha | U82: 7077135656 | V82: 2 | W82: Narsing Bag | X82: Father | Y82: Shakuntala Bag | Z82: Mother | AA82: Veg | AB82: Veg | AC82: Veg | AD82: Bus Drop Service not needed | AE82: 0
A83: 46264.668 | B83: gowtham.mbbs-2020@aiimskalyani.edu.in | C83: GOWTHAM S | D83: 20200199 | E83: MBBS 2020 | F83: 8113071161 | G83: gowtham.mbbs-2020@aiimskalyani.edu.in | H83: Yes | I83: Football enthusiast, occasional quizzing, movies tv shows and animes, Novels and other stories | J83: Was in the aiims kalyani football team, was captain of the green house football team during 3rd year, led the team to the finals. Won football inter house house match in 2nd and final year | K83: Chathenkary, Thiruvalla, Kerala | L83: https://drive.google.com/open?id=14KxPGkJYWPipEttIFlq04mALjst5dPU7 | M83: https://drive.google.com/open?id=1Wqoq6QmYVL-NSZllrfdkNyK-hRfq1ihk | N83: Santhosh G | O83: Advocate | P83: Thiruvalla | Q83: 9847614625 | R83: Sobha VK | S83: Principal, Nellimoodu New B.Ed College | T83: Thiruvalla | U83: 8848466640 | V83: 2 | W83: Santhosh G | X83: Father | Y83: Sobha VK | Z83: Mother | AA83: Non-Veg | AB83: Non-Veg | AC83: Non-Veg | AD83: Bus Drop Service not needed | AE83: 0
A84: 46264.673 | B84: pritam.mbbs-2020@aiimskalyani.edu.in | C84: PRITAM KUMAR DAS | D84: 70 / 202001120 | E84: MBBS 2020 | F84: 9903416146 | G84: pritamkdas21@gmail.com | H84: Yes | K84: Ara - Bihar | L84: https://drive.google.com/open?id=1FeO19y_W8VWcjEZdY_YIZLqTIsi4H8S3 | M84: https://drive.google.com/open?id=1BZbbjvux3p2XroHfFauBl6n9_CcTVHFh | N84: Uma Shankar Das | O84: Govt. service / ATT | P84: Kolkata | Q84: 8272938340 | R84: Nilam Devi | S84: Housewife | T84: Kori ( Bihar) | U84: 9477399505 | V84: 2 | W84: Uma Shankar Das | X84: Father | Y84: Nilam devi | Z84: Mother | AA84: Non-Veg | AB84: Non-Veg | AC84: Non-Veg | AD84: Bus Drop Service not needed | AE84: 0
A85: 46264.721 | B85: anubhab.mbbs-2020@aiimskalyani.edu.in | C85: Anubhab Saha | D85: 20200169 | E85: MBBS 2020 | F85: 9591180260 | G85: anubhabsaha.med@gmail.com | H85: Yes | I85: Quizzing, Listening to Music and and playing Guitar, Reading Novels, Playing Football | J85: 1. Represented AIIMS Kalyani in various National Open Quizzes (Errol Cowper trophy, Kolkata International Quiz Festival, Kolkata International Sports quiz festival etc) 2. Won Solo Instrumental at JIPMER Intercollege fest (Spandan 2023) 3. Podium finishes in online and offline quizzes organised by AIIMS Bhubaneswar and JIPMER. 4. Represented AIIMS Kalyani in Intercollege Battle of Bands competition in JIPMER and AIIMS Bhubaneswar. 5. Music Club Head of AIIMS Kalyani (2024) | K85: Bangalore | L85: https://drive.google.com/open?id=1Y6ZcGc2riRBA1oJVHyZfsfZ4dY3i6fjT | M85: https://drive.google.com/open?id=1ERvGu6dTpc99Rnh9EJjqrc6E_swukhi7 | N85: Jayanta Kumar Saha | O85: Bank Employee, Senior Manager, Indian Bank | P85: Bangalore | Q85: 9945740299 | R85: Jayeeta Saha | S85: Teacher, Assistant teacher, Vidyodaya NAL Nursery School | T85: Bangalore | U85: 9731863312 | V85: 2 | W85: Jayanta Kumar Saha | X85: Father | Y85: Jayeeta Saha | Z85: Mother | AA85: Non-Veg | AB85: Non-Veg | AC85: Non-Veg | AD85: Bus Drop Service not needed | AE85: 0
A86: 46264.723 | B86: ashish.mbbs-2020@aiimskalyani.edu.in | C86: ASHISH GAURAV | D86: 20200176 | E86: MBBS 2020 | F86: 7352453050 | G86: gauravdrashish@gmail.com | H86: Yes | I86: Playing cricket | J86: Completed ICMR STS RESEARCH PROJECT | K86: Mashrak, chapra | L86: https://drive.google.com/open?id=1exP8iApsSJz-fQoCCg6_C_zjXxKagc7N | M86: https://drive.google.com/open?id=1cm90fqXv2zVDf7h9fbEs9F8ucMNpHqwB | N86: Jay kishor singh | O86: Professor | P86: Mashrak | Q86: 9334789078 | R86: Ahilya devi | S86: Housewife | T86: Mashrak | U86: 9334789078 | V86: 2 | W86: Jay kishor singh | X86: Father | Y86: Ahilya devi | Z86: Mother | AA86: Veg | AB86: Veg | AC86: Veg | AD86: Bus Drop Service not needed | AE86: 0
A87: 46264.761 | B87: abhilasha.mbbs-2020@aiimskalyani.edu.in | C87: ABHILASHA SABOTH | D87: 20200151 | E87: MBBS 2020 | F87: 9337129829 | G87: sabothabhilasha@gmail.com | H87: Yes | I87: I like to sing or run in my leisure times, I am interested in dance and glass painting. Besides, I like watching shows online, my favourite genres are action comedy, mystery, and fantasy drama. | J87: 1. Responsibility of Student Organising Secretary of Annual sociocultural fest - Elyssia 2024 2. Represented college in intercollege Band, Group Dance and Quiz competitions 3. Volunteered in free health checkup camps in Rural Bengal | K87: Bhubaneswar, Odisha | L87: https://drive.google.com/open?id=16__dhr2B7lDH-cZFXfDeVTeqcycri0Sm | M87: https://drive.google.com/open?id=1YgtgGM0BsLO_D9kRBIISiOo_pFEO2EhF | N87: Dr. Prasant Kumar Saboth | O87: MD Pediatrics, Professor at IMS and SUM hospital, Bhubaneswar | P87: Bhubaneswar | Q87: 7827575483 | R87: Sibani Satpathy | S87: Mental health counsellor | T87: Bhubaneswar | U87: 8895584818 | V87: 1 | W87: Prasant kumar Saboth | X87: Father | AA87: Veg | AB87: Veg | AD87: Bus Drop Service not needed | AE87: 0
A88: 46264.771 | B88: subhasis.mbbs-2020@aiimskalyani.edu.in | C88: SUBHASIS PANJA | D88: 100/202001150 | E88: MBBS 2020 | F88: 7908126837 | G88: subhasispanja11@gmail.com | H88: Yes | I88: Quiz, Badminton, Poems, Watching and analyzing Bayern Munich football games. | K88: Arambagh | L88: https://drive.google.com/open?id=124crok5AAw7ikRRjYsGq6nRYmxtyzGdL | M88: https://drive.google.com/open?id=1zW8WVLi6_3sWq2Ftmyb2_GxImDfZVuTc | N88: Sridhar Panja | O88: LIC AAO Officer | P88: Arambagh | Q88: 7908989497 | R88: Ambika Panja | S88: Nurse (West Bengal Staff Nurse) | T88: Arambagh | U88: 9474663399 | V88: 2 | W88: Sridhar Panja | X88: Father | Y88: Ambika Panja | Z88: Mother | AA88: Non-Veg | AB88: Non-Veg | AC88: Veg | AD88: Bus Drop Service not needed
A89: 46264.776 | B89: honkap.mbbs-2020@aiimskalyani.edu.in | C89: HONKAP WANGJEN | D89: 51/202001101 | E89: MBBS 2020 | F89: 9383106349 | G89: honkap.mbbs-2020@aiimskalyani.edu.in | H89: Yes | I89: photography, reading and following current affairs, hiking, travelling, listening to music, playing badminton, exercising, driving and fishing. | K89: Village- Hasse Russa, PS/PO-Kanubari, Pincode-792131, District-Longding, State- Arunachal Pradesh. | L89: https://drive.google.com/open?id=1evafgOkL5bzXnMIWfeJ-3EYX21EA1I4H | M89: https://drive.google.com/open?id=1oyRXm0T63v91E4r6-sJBAxNWs8edMhLB | N89: PHOTONG WANGJEN | O89: Farmer | P89: Village- Hasse Russa, PS/PO-Kanubari, Pincode-792131, District-Longding, State- Arunachal Pradesh. | Q89: 7005403521 | R89: PHEMUN WANGJEN | S89: Homemaker | T89: Village- Hasse Russa, PS/PO-Kanubari, Pincode-792131, District-Longding, State- Arunachal Pradesh. | U89: 9383106349 | V89: 1 | W89: Ngamlem Wangjen | X89: Elder sister | AA89: Non-Veg | AB89: Non-Veg | AD89: Bus Drop Service not needed
A90: 46264.802 | B90: disha.mbbs-2020@aiimskalyani.edu.in | C90: DISHA MANDAL | D90: 20200197 | E90: MBBS 2020 | F90: 9933492817 | G90: mandaldisha21@gmail.com | H90: Yes | I90: Reading Books, Listening music | K90: Bankura | L90: https://drive.google.com/open?id=1WAR3PH2PNje3aU1_IFAB6VIupB7ExLC9 | M90: https://drive.google.com/open?id=1vpUSj95DCgepZ11M33qVLLufnDIa6yfg | N90: MRINAL KANTI MANDAL | O90: ASSISTANT DIRECTOR AGRICULTURE, GOVT OF WEST BENGAL | P90: BANKURA | Q90: 9641492848 | R90: BABITA MANDAL | S90: HOMEMAKER | T90: BANKURA | U90: 7908035189 | V90: 2 | W90: MRINAL KANTI MANDAL | X90: Father | Y90: BABITA MANDAL | Z90: Mother | AA90: Non-Veg | AB90: Non-Veg | AC90: Non-Veg | AD90: Drop at Kalyani Railway Station | AE90: 3
A91: 46264.81 | B91: vulasala.mbbs-2020@aiimskalyani.edu.in | C91: VULASALA VENKATA SAI CHARAN | D91: 202001163 | E91: MBBS 2020 | F91: 8341737691 | G91: vulasala.mbbs-2020@aiimskalyani.edu.in | H91: Yes | I91: Music, Movies, doomscrolling | J91: College Research Poster presentation 2023 - 2nd prize | K91: Proddatur, Andhra Pradesh | L91: https://drive.google.com/open?id=1l-YPj1SujDEzufsgxinfewrNChZ44hmn | M91: https://drive.google.com/open?id=1vO3anu3uqZAN5tjSoc_FJhctZ6AmmyP6 | N91: Vulasala Sreenivasulu | O91: ADE in APGENCO | P91: Proddatur | Q91: 8919187309 | R91: Chimmani Annapurna | S91: Home maker | T91: Proddatur | U91: 8317611083 | V91: 2 | W91: Vulasala Sreenivasulu | X91: Father | Y91: Chimmani Lakshmi | Z91: Mother | AA91: Non-Veg | AB91: Non-Veg | AC91: Non-Veg | AD91: Drop at Kolkata Airport | AE91: 2
A92: 46264.815 | B92: sreeram.mbbs-2020@aiimskalyani.edu.in | C92: Sreeram R S | D92: 124 / 202001174 | E92: MBBS 2020 | F92: 9188573375 | G92: sreeram.mbbs-2020@aiimskalyani.edu.in | H92: Yes | K92: Kerala | L92: https://drive.google.com/open?id=1mMFiI51tsVW_TprZtopgXmH_Nn-I9Z7g | M92: https://drive.google.com/open?id=1l89BGnA4vKTlHGE5ICKyfo8hsSc3bLO6 | N92: Sangameswaran M R | O92: Mechanical Engineer ( Retired ) | P92: Palakkad , Kerala | Q92: 6235195823 | R92: Jayaseeta V N | S92: Bank employee , Kerala Gramin Bank | T92: Palakkad , Kerala | U92: 9633533665 | V92: 1 | W92: Jayaseeta V N | X92: Mother | AA92: Veg | AB92: Veg | AD92: Bus Drop Service not needed | AE92: 0
A93: 46264.828 | B93: rakesh.mbbs-2020@aiimskalyani.edu.in | C93: Rakesh Raushan | D93: 202001124 | E93: MBBS 2020 | F93: 9799092569 | G93: Rakeshraushan112@gmail.com | H93: Yes | I93: Travelling, Trekking, Playing Chess, Badminton, cricket, cooking, Photography | K93: Saharsa | L93: https://drive.google.com/open?id=1cei-PULn1wQVZbfJ-9M_omjOaQWjneMr | M93: https://drive.google.com/open?id=1xY-xUFjpIBv770_nomBwb-6qXCT6x8t2 | N93: Bijay Kumar | O93: Business | P93: Saharsa | Q93: 9431891302 | R93: Kumari Sunita | S93: Government Job | T93: Saharsa | U93: 8252876290 | V93: 0 | AA93: Non-Veg | AD93: Bus Drop Service not needed
A94: 46264.84 | B94: mourupa.mbbs-2020@aiimskalyani.edu.in | C94: MOURUPA SARKAR | D94: 20200114 | E94: MBBS 2020 | F94: 6295614611 | G94: mourupa.mbbs-2020@aiimskalyani.edu.in | H94: Yes | I94: Painting | J94: Won various competitions organised by Art Club in Aiims kalyani | K94: Alipur Duar | L94: https://drive.google.com/open?id=1EZl5dm09BGfE1LXPFGGzxMDkfjpRXEDL | M94: https://drive.google.com/open?id=1WfJdQ7lba38kSgsUtHTA0vyCO4jFnufI | N94: Mr Ratan Sarkar | O94: Government Service | P94: Alipur Duar | Q94: 6297473298 | R94: Mithu Das Sarkar | S94: Government service | T94: Alipur Duar | U94: 7908479314 | V94: 2 | W94: Mithu Das Sarkar | X94: Mother | Y94: Ratan Sarkar | Z94: Father | AA94: Non-Veg | AB94: Veg | AC94: Non-Veg | AD94: Bus Drop Service not needed
A95: 46264.851 | B95: bindukoyel2000@gmail.com | C95: KOYEL BINDU | D95: 20210217 | E95: B.Sc (Hons) Nursing 2021 | F95: 6295040670 | G95: bindukoyel2000@gmail.com | H95: Yes | I95: Playing badminton and reading books | J95: Nursing Sports Club Head | K95: Falta ( West Bengal ) | L95: https://drive.google.com/open?id=15o0a3fzy5LjwThrVuwlxE9rBOP_qlfuK | M95: https://drive.google.com/open?id=1C2qKVxFDxPhJY2kHo4pIgoCVLnztIcyb | N95: Salil Kumar Bindu | O95: Retired Central Government Employee | P95: Falta ( West Bengal ) | Q95: 8617659762 | R95: Kabita Bindu | S95: Housewife | T95: Falta ( West Bengal ) | U95: 8001512822 | V95: 2 | W95: Salil Kumar Bindu | X95: Father | Y95: Kabita Bindu | Z95: Mother | AA95: Non-Veg | AB95: Non-Veg | AC95: Non-Veg | AD95: Drop at Kalyani Railway Station | AE95: 3
A96: 46264.852 | B96: kumarikhushboo0123@gmail.com | C96: KHUSHBOO KUMARI | D96: 20210216 | E96: B.Sc (Hons) Nursing 2021 | F96: 9973417831 | G96: kumarikhushboo0123@gmail.com | H96: Yes | I96: Reading and playing Badminton | J96: Volleyball and Throwball winner | K96: Jogbani (Bihar) | L96: https://drive.google.com/open?id=14_7dNgH2jKaUTkEsmAia11nMGYHPwMPK | M96: https://drive.google.com/open?id=1dcUHRKQlHNXEiuCu8H4WDFnT5PQ9u3Cv | N96: Vijay sah | O96: Businessman | P96: Jogbani (bihar) | Q96: 7033232188 | R96: Urmila Devi | S96: Housewife | T96: Jogbani (Bihar) | U96: 8092010547 | V96: 1 | W96: Abhinav Kumar | X96: Brother | AA96: Non-Veg | AB96: Veg | AD96: Drop at Kalyani Railway Station | AE96: 2
A97: 46264.86 | B97: mansi.mbbs-2020@aiimskalyani.edu.in | C97: MANSI SUBBA | D97: 202001110 | E97: MBBS 2020 | F97: 9679315598 | G97: mansi.mbbs-2020@aiimskalyani.edu.in | H97: Yes | I97: Singing and playing guitar | J97: Notable achievements: School topper (10th standard) State topper NEET UG 2020 (Sikkim) | K97: Gangtok, Sikkim | L97: https://drive.google.com/open?id=1I9ykYpi52o7Ds7p8J3CIOEOxydSwibFL | M97: https://drive.google.com/open?id=1rYEhNu-GhsdymxAL2zGfa_aNIYGyLNnf | N97: Late Budhi Man Subba | O97: Deceased | P97: Chota Singtam, East Sikkim | Q97: 9593372255 | R97: Man Kumari Rai | S97: Government employee | T97: Chota Singtam, East Sikkim | U97: 9733064422 | V97: 2 | W97: Man Kumari Rai | X97: Mother | Y97: Allen Subba | Z97: Sibling (Brother) | AA97: Non-Veg | AB97: Non-Veg | AC97: Non-Veg
A98: 46264.86 | B98: preeti.bscnursing-2021@aiimskalyani.edu.in | C98: PREETI DUTTA | D98: 20210237 | E98: B.Sc (Hons) Nursing 2021 | F98: 7074977255 | G98: preetidutta2021@gmail.com | H98: Yes | I98: Love to Draw, | K98: Bankura | L98: https://drive.google.com/open?id=1hlJleNe4yhMsVtNy3uaRgEhaNrJjYvnE | M98: https://drive.google.com/open?id=16sG-VxDCwhU-_Qbejm3nJtZOo1f2_uO5 | N98: Satya charan Dutta | O98: Serviceman | P98: Bankura | Q98: 9474814312 | R98: Archana Dutta | S98: Housewife | T98: Bankura | U98: 9134190091 | V98: 2 | W98: Satya charan Dutta | X98: Father | Y98: Archana Dutta | Z98: Mother | AA98: Non-Veg | AB98: Non-Veg | AC98: Non-Veg
A99: 46264.896 | B99: altaf.mbbs-2020@aiimskalyani.edu.in | C99: ALTAF KHAN | D99: 20200158 | E99: MBBS 2020 | F99: 9453612551 | G99: Altaf.mbbs-2020@aiimskalyani.edu.in | H99: Yes | I99: None | J99: None | K99: Lucknow | L99: https://drive.google.com/open?id=1OKHYOcwxo5KX9hlTtCqE_9AV5KAEvPQt | M99: https://drive.google.com/open?id=1oE2EZGy9gu12RvtXM-WBxqvnrUSWKilB | N99: Lt. Dr. Dilshad Nabi Khan | O99: -- | P99: -- | Q99: 9453612551 | R99: Noorjahan Khan | S99: Home maker | T99: Lucknow | U99: 9125937130 | V99: 0 | AA99: Non-Veg | AD99: Bus Drop Service not needed
A100: 46264.898 | B100: tiyasha.mbbs-2020@aiimskalyani.edu.in | C100: TIYASHA CHATTERJEE | D100: 202001157 | E100: MBBS 2020 | F100: 9674622440 | G100: tiyasha.mbbs-2020@aiimskalyani.edu.in | H100: Yes | K100: Kolkata | L100: https://drive.google.com/open?id=1nmE9wXF0rSvMqTuC6uREA91cFeJXAsj6 | M100: https://drive.google.com/open?id=14RNrUN4mpkbO7eAM95HuFDkFOWUgWnaK | N100: Rahul Chatterjee | O100: Service | P100: Kolkata | Q100: 9874264360 | R100: Madhumita Chatterjee | S100: Entrepreneur | T100: Kolkata | U100: 9836080313 | V100: 2 | W100: Madhumita Chatterjee | X100: Mother | Y100: Rahul Chatterjee | Z100: Father | AA100: Non-Veg | AB100: Veg | AC100: Veg | AD100: Bus Drop Service not needed | AE100: 0
...

Sheet Responses
A1: Timestamp | B1: Email address | C1: Full Name (in Block Letters) | D1: Roll Number / Enrollment ID | E1: Course | F1: Contact Number | G1: Email | H1: Attending Convocation | I1: Hobbies & Personal Interests | J1: Sports & Games / Notable Achievements | K1: Hometown | L1: Passport Size Photo Upload | M1: Family Photo Upload | N1: Father's Name | O1: Father's Occupation / Designation & Affiliation | P1: Father's City / Place of Residence | Q1: Father's Contact Number | R1: Mother's Name | S1: Mother's Occupation / Designation & Affiliation | T1: Mother's City / Place of Residence | U1: Mother's Contact Number | V1: Number of Accompanying Guests | W1: Guest 1 Full Name | X1: Relation with the Student | Y1: Guest 2 Full Name | Z1: Relation with the Student 2 | AA1: Student Meal/Food Preference | AB1: Guest 1 Meal/Food Preference | AC1: Guest 2 Meal/Food Preference | AD1: Bus Drop Service Required on 15.09.2026 at 8:00 PM? | AE1: Number of Passengers for Bus Service
A2: =IFERROR(__xludf.DUMMYFUNCTION("LET( raw, FILTER('Form responses 1'!A2:AE293, 'Form responses 1'!H2:H293=""Yes""), sorted, SORT(raw, 1, FALSE), c, CHOOSECOLS(sorted, 3), e, CHOOSECOLS(sorted, 5), k, ARRAYFORMULA(c & ""|"" & e), FILTER(sorted, MATCH(k, k, 0) = SEQUENCE(ROWS(k"&"))) )"),46270.99212284722) -> 46270.992 | B2: =IFERROR(__xludf.DUMMYFUNCTION("""COMPUTED_VALUE"""),"patel.mbbs-2020@aiimskalyani.edu.in") -> patel.mbbs-2020@aiimskalyani.edu.in | C2: =IFERROR(__xludf.DUMMYFUNCTION("""COMPUTED_VALUE"""),"PATEL SHRUTI RUTANJU ") -> PATEL SHRUTI RUTANJU | D2: =IFERROR(__xludf.DUMMYFUNCTION("""COMPUTED_VALUE"""),2.02001117E8) -> 202001117 | E2: =IFERROR(__xludf.DUMMYFUNCTION("""COMPUTED_VALUE"""),"MBBS 2020") -> MBBS 2020 | F2: =IFERROR(__xludf.DUMMYFUNCTION("""COMPUTED_VALUE"""),7.644977977E9) -> 7644977977 | G2: =IFERROR(__xludf.DUMMYFUNCTION("""COMPUTED_VALUE"""),"starv2888@gmail.com") -> starv2888@gmail.com | H2: =IFERROR(__xludf.DUMMYFUNCTION("""COMPUTED_VALUE"""),"Yes") -> Yes | I2: =IFERROR(__xludf.DUMMYFUNCTION("""COMPUTED_VALUE"""),"I love diving into board games and lively debates, goofing around with dogs, dabbling in performance arts and acting, and enjoying a little baking and swimming. I also love hands-on activities like LEGO, macramé, diamond art, and puzzles.") -> I love diving into board games and lively debates, goofing around with dogs, dabbling in performance arts and acting, and enjoying a little baking and swimming. I also love hands-on activities like LEGO, macramé, diamond art, and puzzles. | J2: =IFERROR(__xludf.DUMMYFUNCTION("""COMPUTED_VALUE"""),"Participated in debates Although I have never competed professionally, I thoroughly enjoy swimming.") -> Participated in debates Although I have never competed professionally, I thoroughly enjoy swimming. | K2: =IFERROR(__xludf.DUMMYFUNCTION("""COMPUTED_VALUE"""),"Scarborough, Maine & Anand, Gujarat") -> Scarborough, Maine & Anand, Gujarat | L2: =IFERROR(__xludf.DUMMYFUNCTION("""COMPUTED_VALUE"""),"https://drive.google.com/open?id=1wvVMWKrnUjVgP1CfYWdd_E0vchEM9pi3") -> https://drive.google.com/open?id=1wvVMWKrnUjVgP1CfYWdd_E0vchEM9pi3 | M2: =IFERROR(__xludf.DUMMYFUNCTION("""COMPUTED_VALUE"""),"https://drive.google.com/open?id=1FD55F3mUjSvviBFvT0lmlP5qs97Jo6Rq") -> https://drive.google.com/open?id=1FD55F3mUjSvviBFvT0lmlP5qs97Jo6Rq | N2: =IFERROR(__xludf.DUMMYFUNCTION("""COMPUTED_VALUE"""),"Late Rutanju Patel ") -> Late Rutanju Patel | O2: =IFERROR(__xludf.DUMMYFUNCTION("""COMPUTED_VALUE"""),"Certified Public Accountant (CPA) ;") -> Certified Public Accountant (CPA) ; | P2: =IFERROR(__xludf.DUMMYFUNCTION("""COMPUTED_VALUE"""),"N/A ") -> N/A | Q2: =IFERROR(__xludf.DUMMYFUNCTION("""COMPUTED_VALUE"""),9.999999999E9) -> 9999999999 | R2: =IFERROR(__xludf.DUMMYFUNCTION("""COMPUTED_VALUE"""),"Trupti Patel ") -> Trupti Patel | S2: =IFERROR(__xludf.DUMMYFUNCTION("""COMPUTED_VALUE"""),"Entrepreneur & Business Owner") -> Entrepreneur & Business Owner | T2: =IFERROR(__xludf.DUMMYFUNCTION("""COMPUTED_VALUE"""),"Scarborough, Maine & Anand, Gujarat ") -> Scarborough, Maine & Anand, Gujarat | U2: =IFERROR(__xludf.DUMMYFUNCTION("""COMPUTED_VALUE"""),9.429181978E9) -> 9429181978 | V2: =IFERROR(__xludf.DUMMYFUNCTION("""COMPUTED_VALUE"""),2.0) -> 2 | W2: =IFERROR(__xludf.DUMMYFUNCTION("""COMPUTED_VALUE"""),"Trupti Patel") -> Trupti Patel | X2: =IFERROR(__xludf.DUMMYFUNCTION("""COMPUTED_VALUE"""),"Mother ") -> Mother | Y2: =IFERROR(__xludf.DUMMYFUNCTION("""COMPUTED_VALUE"""),"Pranathi Nambiar ") -> Pranathi Nambiar | Z2: =IFERROR(__xludf.DUMMYFUNCTION("""COMPUTED_VALUE"""),"Cousin") -> Cousin | AA2: =IFERROR(__xludf.DUMMYFUNCTION("""COMPUTED_VALUE"""),"Veg") -> Veg | AB2: =IFERROR(__xludf.DUMMYFUNCTION("""COMPUTED_VALUE"""),"Veg") -> Veg | AC2: =IFERROR(__xludf.DUMMYFUNCTION("""COMPUTED_VALUE"""),"Non-Veg") -> Non-Veg | AD2: =IFERROR(__xludf.DUMMYFUNCTION("""COMPUTED_VALUE"""),"Drop at Kolkata Airport") -> Drop at Kolkata Airport | AE2: =IFERROR(__xludf.DUMMYFUNCTION("""COMPUTED_VALUE"""),2.0) -> 2
A3: =IFERROR(__xludf.DUMMYFUNCTION("""COMPUTED_VALUE"""),46269.758121631945) -> 46269.758 | B3: =IFERROR(__xludf.DUMMYFUNCTION("""COMPUTED_VALUE"""),"soni.bscnursing-2021@aiimskalyani.edu.in") -> soni.bscnursing-2021@aiimskalyani.edu.in | C3: =IFERROR(__xludf.DUMMYFUNCTION("""COMPUTED_VALUE"""),"SONI KUMARI ") -> SONI KUMARI | D3: =IFERROR(__xludf.DUMMYFUNCTION("""COMPUTED_VALUE"""),2.0210261E7) -> 20210261 | E3: =IFERROR(__xludf.DUMMYFUNCTION("""COMPUTED_VALUE"""),"B.Sc (Hons) Nursing 2021") -> B.Sc (Hons) Nursing 2021 | F3: =IFERROR(__xludf.DUMMYFUNCTION("""COMPUTED_VALUE"""),9.660339459E9) -> 9660339459 | G3: =IFERROR(__xludf.DUMMYFUNCTION("""COMPUTED_VALUE"""),"sahnisoni05@gmail.com") -> sahnisoni05@gmail.com | H3: =IFERROR(__xludf.DUMMYFUNCTION("""COMPUTED_VALUE"""),"Yes") -> Yes | I3: =IFERROR(__xludf.DUMMYFUNCTION("""COMPUTED_VALUE"""),"Playing various sports and exploring new places. ") -> Playing various sports and exploring new places. | J3: =IFERROR(__xludf.DUMMYFUNCTION("""COMPUTED_VALUE"""),"Represented the Bihar Table Tennis Association in competitive events, achieving multiple championship titles across district and inter-school tournaments. Additionally, secured 1st place in both the Singles and Doubles TT at the College Annual Sports Meet"&".") -> Represented the Bihar Table Tennis Association in competitive events, achieving multiple championship titles across district and inter-school tournaments. Additionally, secured 1st place in both the Singles and Doubles TT at the College Annual Sports Meet. | K3: =IFERROR(__xludf.DUMMYFUNCTION("""COMPUTED_VALUE"""),"Patna, Bihar ") -> Patna, Bihar | L3: =IFERROR(__xludf.DUMMYFUNCTION("""COMPUTED_VALUE"""),"https://drive.google.com/open?id=14Mpb3mx408Fe669jtBDA3eVsM3JQv8Ei") -> https://drive.google.com/open?id=14Mpb3mx408Fe669jtBDA3eVsM3JQv8Ei | M3: =IFERROR(__xludf.DUMMYFUNCTION("""COMPUTED_VALUE"""),"https://drive.google.com/open?id=1ZXw5JDk3nfR9UiFRHkn90J-K9uCKlxRP") -> https://drive.google.com/open?id=1ZXw5JDk3nfR9UiFRHkn90J-K9uCKlxRP | N3: =IFERROR(__xludf.DUMMYFUNCTION("""COMPUTED_VALUE"""),"Ramdeo Prasad") -> Ramdeo Prasad | O3: =IFERROR(__xludf.DUMMYFUNCTION("""COMPUTED_VALUE"""),"Businessman") -> Businessman | P3: =IFERROR(__xludf.DUMMYFUNCTION("""COMPUTED_VALUE"""),"Patna,Bihar") -> Patna,Bihar | Q3: =IFERROR(__xludf.DUMMYFUNCTION("""COMPUTED_VALUE"""),7.488140191E9) -> 7488140191 | R3: =IFERROR(__xludf.DUMMYFUNCTION("""COMPUTED_VALUE"""),"Mira Devi") -> Mira Devi | S3: =IFERROR(__xludf.DUMMYFUNCTION("""COMPUTED_VALUE"""),"Homemaker ") -> Homemaker | T3: =IFERROR(__xludf.DUMMYFUNCTION("""COMPUTED_VALUE"""),"Patna, Bihar") -> Patna, Bihar | U3: =IFERROR(__xludf.DUMMYFUNCTION("""COMPUTED_VALUE"""),7.439357998E9) -> 7439357998 | V3: =IFERROR(__xludf.DUMMYFUNCTION("""COMPUTED_VALUE"""),1.0) -> 1 | W3: =IFERROR(__xludf.DUMMYFUNCTION("""COMPUTED_VALUE"""),"ABHAY KUMAR") -> ABHAY KUMAR | X3: =IFERROR(__xludf.DUMMYFUNCTION("""COMPUTED_VALUE"""),"Brother") -> Brother | AA3: =IFERROR(__xludf.DUMMYFUNCTION("""COMPUTED_VALUE"""),"Non-Veg") -> Non-Veg | AB3: =IFERROR(__xludf.DUMMYFUNCTION("""COMPUTED_VALUE"""),"Non-Veg") -> Non-Veg | AD3: =IFERROR(__xludf.DUMMYFUNCTION("""COMPUTED_VALUE"""),"Bus Drop Service not needed") -> Bus Drop Service not needed
A4: =IFERROR(__xludf.DUMMYFUNCTION("""COMPUTED_VALUE"""),46269.63215892361) -> 46269.632 | B4: =IFERROR(__xludf.DUMMYFUNCTION("""COMPUTED_VALUE"""),"sonam.bscnursing-2021@aiimskalyani.edu.in") -> sonam.bscnursing-2021@aiimskalyani.edu.in | C4: =IFERROR(__xludf.DUMMYFUNCTION("""COMPUTED_VALUE"""),"SONAM KUMARI ") -> SONAM KUMARI | D4: =IFERROR(__xludf.DUMMYFUNCTION("""COMPUTED_VALUE"""),2.021025E7) -> 20210250 | E4: =IFERROR(__xludf.DUMMYFUNCTION("""COMPUTED_VALUE"""),"B.Sc (Hons) Nursing 2021") -> B.Sc (Hons) Nursing 2021 | F4: =IFERROR(__xludf.DUMMYFUNCTION("""COMPUTED_VALUE"""),8.404882688E9) -> 8404882688 | G4: =IFERROR(__xludf.DUMMYFUNCTION("""COMPUTED_VALUE"""),"sonamriva20@gmail.com") -> sonamriva20@gmail.com | H4: =IFERROR(__xludf.DUMMYFUNCTION("""COMPUTED_VALUE"""),"Yes") -> Yes | I4: =IFERROR(__xludf.DUMMYFUNCTION("""COMPUTED_VALUE"""),"Traveling and photography ") -> Traveling and photography | J4: =IFERROR(__xludf.DUMMYFUNCTION("""COMPUTED_VALUE"""),"Chess") -> Chess | K4: =IFERROR(__xludf.DUMMYFUNCTION("""COMPUTED_VALUE"""),"Bhagalpur ") -> Bhagalpur | L4: =IFERROR(__xludf.DUMMYFUNCTION("""COMPUTED_VALUE"""),"https://drive.google.com/open?id=1HVrHS_D5ahC18Hz1pfvs1DxJc9iE3i90") -> https://drive.google.com/open?id=1HVrHS_D5ahC18Hz1pfvs1DxJc9iE3i90 | M4: =IFERROR(__xludf.DUMMYFUNCTION("""COMPUTED_VALUE"""),"https://drive.google.com/open?id=1sVVHIaGT7Z-sRVXgXVs4t5l8lNrSP3Pe") -> https://drive.google.com/open?id=1sVVHIaGT7Z-sRVXgXVs4t5l8lNrSP3Pe | N4: =IFERROR(__xludf.DUMMYFUNCTION("""COMPUTED_VALUE"""),"Ranjan Kumar ") -> Ranjan Kumar | O4: =IFERROR(__xludf.DUMMYFUNCTION("""COMPUTED_VALUE"""),"Businessmen ") -> Businessmen | P4: =IFERROR(__xludf.DUMMYFUNCTION("""COMPUTED_VALUE"""),"Shahkund ") -> Shahkund | Q4: =IFERROR(__xludf.DUMMYFUNCTION("""COMPUTED_VALUE"""),8.404882688E9) -> 8404882688 | R4: =IFERROR(__xludf.DUMMYFUNCTION("""COMPUTED_VALUE"""),"Rani Devi ") -> Rani Devi | S4: =IFERROR(__xludf.DUMMYFUNCTION("""COMPUTED_VALUE"""),"Homemaker") -> Homemaker | T4: =IFERROR(__xludf.DUMMYFUNCTION("""COMPUTED_VALUE"""),"Shahkund") -> Shahkund | U4: =IFERROR(__xludf.DUMMYFUNCTION("""COMPUTED_VALUE"""),7.488505863E9) -> 7488505863 | V4: =IFERROR(__xludf.DUMMYFUNCTION("""COMPUTED_VALUE"""),2.0) -> 2 | W4: =IFERROR(__xludf.DUMMYFUNCTION("""COMPUTED_VALUE"""),"Ranjan Kumar ") -> Ranjan Kumar | X4: =IFERROR(__xludf.DUMMYFUNCTION("""COMPUTED_VALUE"""),"Father") -> Father | Y4: =IFERROR(__xludf.DUMMYFUNCTION("""COMPUTED_VALUE"""),"Rani Devi ") -> Rani Devi | Z4: =IFERROR(__xludf.DUMMYFUNCTION("""COMPUTED_VALUE"""),"Mother") -> Mother | AA4: =IFERROR(__xludf.DUMMYFUNCTION("""COMPUTED_VALUE"""),"Non-Veg") -> Non-Veg | AB4: =IFERROR(__xludf.DUMMYFUNCTION("""COMPUTED_VALUE"""),"Non-Veg") -> Non-Veg | AC4: =IFERROR(__xludf.DUMMYFUNCTION("""COMPUTED_VALUE"""),"Veg") -> Veg | AD4: =IFERROR(__xludf.DUMMYFUNCTION("""COMPUTED_VALUE"""),"Bus Drop Service not needed") -> Bus Drop Service not needed | AE4: =IFERROR(__xludf.DUMMYFUNCTION("""COMPUTED_VALUE"""),0.0) -> 0
A5: =IFERROR(__xludf.DUMMYFUNCTION("""COMPUTED_VALUE"""),46268.72020755787) -> 46268.72 | B5: =IFERROR(__xludf.DUMMYFUNCTION("""COMPUTED_VALUE"""),"agnibha.bscnursing-2021@aiimskalyani.edu.in") -> agnibha.bscnursing-2021@aiimskalyani.edu.in | C5: =IFERROR(__xludf.DUMMYFUNCTION("""COMPUTED_VALUE"""),"AGNIBHA PAUL ") -> AGNIBHA PAUL | D5: =IFERROR(__xludf.DUMMYFUNCTION("""COMPUTED_VALUE"""),2.0210203E7) -> 20210203 | E5: =IFERROR(__xludf.DUMMYFUNCTION("""COMPUTED_VALUE"""),"B.Sc (Hons) Nursing 2021") -> B.Sc (Hons) Nursing 2021 | F5: =IFERROR(__xludf.DUMMYFUNCTION("""COMPUTED_VALUE"""),6.296247051E9) -> 6296247051 | G5: =IFERROR(__xludf.DUMMYFUNCTION("""COMPUTED_VALUE"""),"agnibha.bscnursing-2021@aiimskalyani.edu.in") -> agnibha.bscnursing-2021@aiimskalyani.edu.in | H5: =IFERROR(__xludf.DUMMYFUNCTION("""COMPUTED_VALUE"""),"Yes") -> Yes | I5: =IFERROR(__xludf.DUMMYFUNCTION("""COMPUTED_VALUE"""),"Sketching , watching movies ") -> Sketching , watching movies | K5: =IFERROR(__xludf.DUMMYFUNCTION("""COMPUTED_VALUE"""),"Coochbehar, West Bengal ") -> Coochbehar, West Bengal | L5: =IFERROR(__xludf.DUMMYFUNCTION("""COMPUTED_VALUE"""),"https://drive.google.com/open?id=14ns53xW0g5r7rsAieCJaIPrfcLHXNG38") -> https://drive.google.com/open?id=14ns53xW0g5r7rsAieCJaIPrfcLHXNG38 | M5: =IFERROR(__xludf.DUMMYFUNCTION("""COMPUTED_VALUE"""),"https://drive.google.com/open?id=1gI65Z8yykq8K_GRtHkP7n8FulaboQPE-") -> https://drive.google.com/open?id=1gI65Z8yykq8K_GRtHkP7n8FulaboQPE- | N5: =IFERROR(__xludf.DUMMYFUNCTION("""COMPUTED_VALUE"""),"Shyamal Chandra Paul") -> Shyamal Chandra Paul | O5: =IFERROR(__xludf.DUMMYFUNCTION("""COMPUTED_VALUE"""),"Teacher ") -> Teacher | P5: =IFERROR(__xludf.DUMMYFUNCTION("""COMPUTED_VALUE"""),"Coochbehar,West Bengal ") -> Coochbehar,West Bengal | Q5: =IFERROR(__xludf.DUMMYFUNCTION("""COMPUTED_VALUE"""),6.29467189E9) -> 6294671890 | R5: =IFERROR(__xludf.DUMMYFUNCTION("""COMPUTED_VALUE"""),"Jwelli Basu Paul") -> Jwelli Basu Paul | S5: =IFERROR(__xludf.DUMMYFUNCTION("""COMPUTED_VALUE"""),"Health worker") -> Health worker | T5: =IFERROR(__xludf.DUMMYFUNCTION("""COMPUTED_VALUE"""),"Coochbehar, West Bengal ") -> Coochbehar, West Bengal | U5: =IFERROR(__xludf.DUMMYFUNCTION("""COMPUTED_VALUE"""),7.363871933E9) -> 7363871933 | V5: =IFERROR(__xludf.DUMMYFUNCTION("""COMPUTED_VALUE"""),2.0) -> 2 | W5: =IFERROR(__xludf.DUMMYFUNCTION("""COMPUTED_VALUE"""),"1. Shyamal Chandra Paul ") -> 1. Shyamal Chandra Paul | X5: =IFERROR(__xludf.DUMMYFUNCTION("""COMPUTED_VALUE"""),"Father") -> Father | Y5: =IFERROR(__xludf.DUMMYFUNCTION("""COMPUTED_VALUE"""),"Jwelli Basu Paul ") -> Jwelli Basu Paul | Z5: =IFERROR(__xludf.DUMMYFUNCTION("""COMPUTED_VALUE"""),"Mother") -> Mother | AA5: =IFERROR(__xludf.DUMMYFUNCTION("""COMPUTED_VALUE"""),"Veg") -> Veg | AB5: =IFERROR(__xludf.DUMMYFUNCTION("""COMPUTED_VALUE"""),"Non-Veg") -> Non-Veg | AC5: =IFERROR(__xludf.DUMMYFUNCTION("""COMPUTED_VALUE"""),"Non-Veg") -> Non-Veg | AD5: =IFERROR(__xludf.DUMMYFUNCTION("""COMPUTED_VALUE"""),"Bus Drop Service not needed") -> Bus Drop Service not needed | AE5: =IFERROR(__xludf.DUMMYFUNCTION("""COMPUTED_VALUE"""),0.0) -> 0
A6: =IFERROR(__xludf.DUMMYFUNCTION("""COMPUTED_VALUE"""),46266.996902349536) -> 46266.997 | B6: =IFERROR(__xludf.DUMMYFUNCTION("""COMPUTED_VALUE"""),"sharmistha.mbbs-2020@aiimskalyani.edu.in") -> sharmistha.mbbs-2020@aiimskalyani.edu.in | C6: =IFERROR(__xludf.DUMMYFUNCTION("""COMPUTED_VALUE"""),"SHARMISTHA ROUT") -> SHARMISTHA ROUT | D6: =IFERROR(__xludf.DUMMYFUNCTION("""COMPUTED_VALUE"""),2.02001139E8) -> 202001139 | E6: =IFERROR(__xludf.DUMMYFUNCTION("""COMPUTED_VALUE"""),"MBBS 2020") -> MBBS 2020 | F6: =IFERROR(__xludf.DUMMYFUNCTION("""COMPUTED_VALUE"""),8.905157891E9) -> 8905157891 | G6: =IFERROR(__xludf.DUMMYFUNCTION("""COMPUTED_VALUE"""),"sharmistha.mbbs-2020@aiimskalyani.edu.in") -> sharmistha.mbbs-2020@aiimskalyani.edu.in | H6: =IFERROR(__xludf.DUMMYFUNCTION("""COMPUTED_VALUE"""),"Yes") -> Yes | I6: =IFERROR(__xludf.DUMMYFUNCTION("""COMPUTED_VALUE"""),"My hobbies include painting , public speaking and academic quizzing .") -> My hobbies include painting , public speaking and academic quizzing . | K6: =IFERROR(__xludf.DUMMYFUNCTION("""COMPUTED_VALUE"""),"Bhubaneswar ") -> Bhubaneswar | L6: =IFERROR(__xludf.DUMMYFUNCTION("""COMPUTED_VALUE"""),"https://drive.google.com/open?id=1nVM8n8zHwMihrktdkrp1SMFAISMWQPh3") -> https://drive.google.com/open?id=1nVM8n8zHwMihrktdkrp1SMFAISMWQPh3 | M6: =IFERROR(__xludf.DUMMYFUNCTION("""COMPUTED_VALUE"""),"https://drive.google.com/open?id=16kxxoRKzyYMnXX9WcQjINwavwF-UhTEN") -> https://drive.google.com/open?id=16kxxoRKzyYMnXX9WcQjINwavwF-UhTEN | N6: =IFERROR(__xludf.DUMMYFUNCTION("""COMPUTED_VALUE"""),"Surendra Kumar Rout") -> Surendra Kumar Rout | O6: =IFERROR(__xludf.DUMMYFUNCTION("""COMPUTED_VALUE"""),"Retired general manager at NTPC, Kaniha") -> Retired general manager at NTPC, Kaniha | P6: =IFERROR(__xludf.DUMMYFUNCTION("""COMPUTED_VALUE"""),"Bhubaneswar ") -> Bhubaneswar | Q6: =IFERROR(__xludf.DUMMYFUNCTION("""COMPUTED_VALUE"""),8.905157891E9) -> 8905157891 | R6: =IFERROR(__xludf.DUMMYFUNCTION("""COMPUTED_VALUE"""),"Dr.Krishna Patro") -> Dr.Krishna Patro | S6: =IFERROR(__xludf.DUMMYFUNCTION("""COMPUTED_VALUE"""),"Associate professor at Department of Ophthalmology, PGIMER Bhubaneswar ") -> Associate professor at Department of Ophthalmology, PGIMER Bhubaneswar | T6: =IFERROR(__xludf.DUMMYFUNCTION("""COMPUTED_VALUE"""),"Bhubaneswar ") -> Bhubaneswar | U6: =IFERROR(__xludf.DUMMYFUNCTION("""COMPUTED_VALUE"""),8.905157891E9) -> 8905157891 | V6: =IFERROR(__xludf.DUMMYFUNCTION("""COMPUTED_VALUE"""),2.0) -> 2 | W6: =IFERROR(__xludf.DUMMYFUNCTION("""COMPUTED_VALUE"""),"Surendra Kumar Rout") -> Surendra Kumar Rout | X6: =IFERROR(__xludf.DUMMYFUNCTION("""COMPUTED_VALUE"""),"Father") -> Father | Y6: =IFERROR(__xludf.DUMMYFUNCTION("""COMPUTED_VALUE"""),"Dr.Krishna Patro") -> Dr.Krishna Patro | Z6: =IFERROR(__xludf.DUMMYFUNCTION("""COMPUTED_VALUE"""),"Mother") -> Mother | AA6: =IFERROR(__xludf.DUMMYFUNCTION("""COMPUTED_VALUE"""),"Non-Veg") -> Non-Veg | AB6: =IFERROR(__xludf.DUMMYFUNCTION("""COMPUTED_VALUE"""),"Non-Veg") -> Non-Veg | AC6: =IFERROR(__xludf.DUMMYFUNCTION("""COMPUTED_VALUE"""),"Non-Veg") -> Non-Veg | AD6: =IFERROR(__xludf.DUMMYFUNCTION("""COMPUTED_VALUE"""),"Bus Drop Service not needed") -> Bus Drop Service not needed | AE6: =IFERROR(__xludf.DUMMYFUNCTION("""COMPUTED_VALUE"""),0.0) -> 0
A7: =IFERROR(__xludf.DUMMYFUNCTION("""COMPUTED_VALUE"""),46266.935814675926) -> 46266.936 | B7: =IFERROR(__xludf.DUMMYFUNCTION("""COMPUTED_VALUE"""),"chongtham.mbbs-2020@aiimskalyani.edu.in") -> chongtham.mbbs-2020@aiimskalyani.edu.in | C7: =IFERROR(__xludf.DUMMYFUNCTION("""COMPUTED_VALUE"""),"CHONGTHAM PARITIYA SINGH") -> CHONGTHAM PARITIYA SINGH | D7: =IFERROR(__xludf.DUMMYFUNCTION("""COMPUTED_VALUE"""),2.0200188E7) -> 20200188 | E7: =IFERROR(__xludf.DUMMYFUNCTION("""COMPUTED_VALUE"""),"MBBS 2020") -> MBBS 2020 | F7: =IFERROR(__xludf.DUMMYFUNCTION("""COMPUTED_VALUE"""),7.011342677E9) -> 7011342677 | G7: =IFERROR(__xludf.DUMMYFUNCTION("""COMPUTED_VALUE"""),"chongtham.mbbs-2020@aiimskalyani.edu.in") -> chongtham.mbbs-2020@aiimskalyani.edu.in | H7: =IFERROR(__xludf.DUMMYFUNCTION("""COMPUTED_VALUE"""),"Yes") -> Yes | I7: =IFERROR(__xludf.DUMMYFUNCTION("""COMPUTED_VALUE"""),"Reading books, Watching anime") -> Reading books, Watching anime | J7: =IFERROR(__xludf.DUMMYFUNCTION("""COMPUTED_VALUE"""),"Participated in and hosted multiple Quiz events") -> Participated in and hosted multiple Quiz events | K7: =IFERROR(__xludf.DUMMYFUNCTION("""COMPUTED_VALUE"""),"Imphal, Manipur") -> Imphal, Manipur | L7: =IFERROR(__xludf.DUMMYFUNCTION("""COMPUTED_VALUE"""),"https://drive.google.com/open?id=1N44T7YnTBgmkiTbItQKtEUNpjEDd0EUh") -> https://drive.google.com/open?id=1N44T7YnTBgmkiTbItQKtEUNpjEDd0EUh | M7: =IFERROR(__xludf.DUMMYFUNCTION("""COMPUTED_VALUE"""),"https://drive.google.com/open?id=17f6tVYwvx4UzQXlhJ9Z6B_eDtJe69uqQ") -> https://drive.google.com/open?id=17f6tVYwvx4UzQXlhJ9Z6B_eDtJe69uqQ | N7: =IFERROR(__xludf.DUMMYFUNCTION("""COMPUTED_VALUE"""),"Chongtham Pureihanba Singh ") -> Chongtham Pureihanba Singh | O7: =IFERROR(__xludf.DUMMYFUNCTION("""COMPUTED_VALUE"""),"Assistant Director, FSL Delhi") -> Assistant Director, FSL Delhi | P7: =IFERROR(__xludf.DUMMYFUNCTION("""COMPUTED_VALUE"""),"Rohini, Delhi") -> Rohini, Delhi | Q7: =IFERROR(__xludf.DUMMYFUNCTION("""COMPUTED_VALUE"""),9.717515666E9) -> 9717515666 | R7: =IFERROR(__xludf.DUMMYFUNCTION("""COMPUTED_VALUE"""),"Chongtham Lenjibala Devi") -> Chongtham Lenjibala Devi | S7: =IFERROR(__xludf.DUMMYFUNCTION("""COMPUTED_VALUE"""),"Homemaker") -> Homemaker | T7: =IFERROR(__xludf.DUMMYFUNCTION("""COMPUTED_VALUE"""),"Rohini, Delhi") -> Rohini, Delhi | U7: =IFERROR(__xludf.DUMMYFUNCTION("""COMPUTED_VALUE"""),9.968443102E9) -> 9968443102 | V7: =IFERROR(__xludf.DUMMYFUNCTION("""COMPUTED_VALUE"""),2.0) -> 2 | W7: =IFERROR(__xludf.DUMMYFUNCTION("""COMPUTED_VALUE"""),"Chongtham Pureihanba Singh ") -> Chongtham Pureihanba Singh | X7: =IFERROR(__xludf.DUMMYFUNCTION("""COMPUTED_VALUE"""),"Father") -> Father | Y7: =IFERROR(__xludf.DUMMYFUNCTION("""COMPUTED_VALUE"""),"Sreeja Sarkar") -> Sreeja Sarkar | Z7: =IFERROR(__xludf.DUMMYFUNCTION("""COMPUTED_VALUE"""),"Cousin") -> Cousin | AA7: =IFERROR(__xludf.DUMMYFUNCTION("""COMPUTED_VALUE"""),"Non-Veg") -> Non-Veg | AB7: =IFERROR(__xludf.DUMMYFUNCTION("""COMPUTED_VALUE"""),"Non-Veg") -> Non-Veg | AC7: =IFERROR(__xludf.DUMMYFUNCTION("""COMPUTED_VALUE"""),"Non-Veg") -> Non-Veg | AD7: =IFERROR(__xludf.DUMMYFUNCTION("""COMPUTED_VALUE"""),"Bus Drop Service not needed") -> Bus Drop Service not needed | AE7: =IFERROR(__xludf.DUMMYFUNCTION("""COMPUTED_VALUE"""),0.0) -> 0
A8: =IFERROR(__xludf.DUMMYFUNCTION("""COMPUTED_VALUE"""),46266.86402688657) -> 46266.864 | B8: =IFERROR(__xludf.DUMMYFUNCTION("""COMPUTED_VALUE"""),"sanandaavidipta@gmail.com") -> sanandaavidipta@gmail.com | C8: =IFERROR(__xludf.DUMMYFUNCTION("""COMPUTED_VALUE"""),"SANANDA DAS") -> SANANDA DAS | D8: =IFERROR(__xludf.DUMMYFUNCTION("""COMPUTED_VALUE"""),2.0210244E7) -> 20210244 | E8: =IFERROR(__xludf.DUMMYFUNCTION("""COMPUTED_VALUE"""),"B.Sc (Hons) Nursing 2021") -> B.Sc (Hons) Nursing 2021 | F8: =IFERROR(__xludf.DUMMYFUNCTION("""COMPUTED_VALUE"""),9.330715505E9) -> 9330715505 | G8: =IFERROR(__xludf.DUMMYFUNCTION("""COMPUTED_VALUE"""),"sanandaavidipta@gmail.com") -> sanandaavidipta@gmail.com | H8: =IFERROR(__xludf.DUMMYFUNCTION("""COMPUTED_VALUE"""),"Yes") -> Yes | I8: =IFERROR(__xludf.DUMMYFUNCTION("""COMPUTED_VALUE"""),"Listening music ") -> Listening music | K8: =IFERROR(__xludf.DUMMYFUNCTION("""COMPUTED_VALUE"""),"TARAKESWAR ") -> TARAKESWAR | L8: =IFERROR(__xludf.DUMMYFUNCTION("""COMPUTED_VALUE"""),"https://drive.google.com/open?id=1q7vxH_QYaEU34MHppSGzd3NaWZVy8P2T") -> https://drive.google.com/open?id=1q7vxH_QYaEU34MHppSGzd3NaWZVy8P2T | M8: =IFERROR(__xludf.DUMMYFUNCTION("""COMPUTED_VALUE"""),"https://drive.google.com/open?id=1X-UOXjb8Wn9jTSc3KAMcoMLGo_4sEAiO") -> https://drive.google.com/open?id=1X-UOXjb8Wn9jTSc3KAMcoMLGo_4sEAiO | N8: =IFERROR(__xludf.DUMMYFUNCTION("""COMPUTED_VALUE"""),"Sushanta Das ") -> Sushanta Das | O8: =IFERROR(__xludf.DUMMYFUNCTION("""COMPUTED_VALUE"""),"Retired Army person ") -> Retired Army person | P8: =IFERROR(__xludf.DUMMYFUNCTION("""COMPUTED_VALUE"""),"TARAKESWAR ") -> TARAKESWAR | Q8: =IFERROR(__xludf.DUMMYFUNCTION("""COMPUTED_VALUE"""),6.284416397E9) -> 6284416397 | R8: =IFERROR(__xludf.DUMMYFUNCTION("""COMPUTED_VALUE"""),"Piyali Das") -> Piyali Das | S8: =IFERROR(__xludf.DUMMYFUNCTION("""COMPUTED_VALUE"""),"House wife ") -> House wife | T8: =IFERROR(__xludf.DUMMYFUNCTION("""COMPUTED_VALUE"""),"TARAKESWAR ") -> TARAKESWAR | U8: =IFERROR(__xludf.DUMMYFUNCTION("""COMPUTED_VALUE"""),8.910037049E9) -> 8910037049 | V8: =IFERROR(__xludf.DUMMYFUNCTION("""COMPUTED_VALUE"""),2.0) -> 2 | W8: =IFERROR(__xludf.DUMMYFUNCTION("""COMPUTED_VALUE"""),"Sushanta Das ") -> Sushanta Das | X8: =IFERROR(__xludf.DUMMYFUNCTION("""COMPUTED_VALUE"""),"Father ") -> Father | Y8: =IFERROR(__xludf.DUMMYFUNCTION("""COMPUTED_VALUE"""),"Piyali Das ") -> Piyali Das | Z8: =IFERROR(__xludf.DUMMYFUNCTION("""COMPUTED_VALUE"""),"Mother ") -> Mother | AA8: =IFERROR(__xludf.DUMMYFUNCTION("""COMPUTED_VALUE"""),"Non-Veg") -> Non-Veg | AB8: =IFERROR(__xludf.DUMMYFUNCTION("""COMPUTED_VALUE"""),"Non-Veg") -> Non-Veg | AC8: =IFERROR(__xludf.DUMMYFUNCTION("""COMPUTED_VALUE"""),"Non-Veg") -> Non-Veg | AD8: =IFERROR(__xludf.DUMMYFUNCTION("""COMPUTED_VALUE"""),"Drop at Kalyani Railway Station") -> Drop at Kalyani Railway Station | AE8: =IFERROR(__xludf.DUMMYFUNCTION("""COMPUTED_VALUE"""),3.0) -> 3
A9: =IFERROR(__xludf.DUMMYFUNCTION("""COMPUTED_VALUE"""),46266.66389927083) -> 46266.664 | B9: =IFERROR(__xludf.DUMMYFUNCTION("""COMPUTED_VALUE"""),"mobina.bscnursing-2021@aiimskalyani.edu.in") -> mobina.bscnursing-2021@aiimskalyani.edu.in | C9: =IFERROR(__xludf.DUMMYFUNCTION("""COMPUTED_VALUE"""),"MOBINA PARVEEN ") -> MOBINA PARVEEN | D9: =IFERROR(__xludf.DUMMYFUNCTION("""COMPUTED_VALUE"""),2.0210224E7) -> 20210224 | E9: =IFERROR(__xludf.DUMMYFUNCTION("""COMPUTED_VALUE"""),"B.Sc (Hons) Nursing 2021") -> B.Sc (Hons) Nursing 2021 | F9: =IFERROR(__xludf.DUMMYFUNCTION("""COMPUTED_VALUE"""),9.593972644E9) -> 9593972644 | G9: =IFERROR(__xludf.DUMMYFUNCTION("""COMPUTED_VALUE"""),"mobinaparveen12@gmail.com") -> mobinaparveen12@gmail.com | H9: =IFERROR(__xludf.DUMMYFUNCTION("""COMPUTED_VALUE"""),"Yes") -> Yes | I9: =IFERROR(__xludf.DUMMYFUNCTION("""COMPUTED_VALUE"""),"Cooking ") -> Cooking | J9: =IFERROR(__xludf.DUMMYFUNCTION("""COMPUTED_VALUE"""),"Work as a organiser in poster competition ") -> Work as a organiser in poster competition | K9: =IFERROR(__xludf.DUMMYFUNCTION("""COMPUTED_VALUE"""),"West bengal ") -> West bengal | L9: =IFERROR(__xludf.DUMMYFUNCTION("""COMPUTED_VALUE"""),"https://drive.google.com/open?id=1PrxEnyumEcEKeHNEIieeKLWD7GBxKFFZ") -> https://drive.google.com/open?id=1PrxEnyumEcEKeHNEIieeKLWD7GBxKFFZ | M9: =IFERROR(__xludf.DUMMYFUNCTION("""COMPUTED_VALUE"""),"https://drive.google.com/open?id=1idiuvmOFbXcY0TIpPj8RQpAiwxjxYWvp") -> https://drive.google.com/open?id=1idiuvmOFbXcY0TIpPj8RQpAiwxjxYWvp | N9: =IFERROR(__xludf.DUMMYFUNCTION("""COMPUTED_VALUE"""),"Sk mahammad ali") -> Sk mahammad ali | O9: =IFERROR(__xludf.DUMMYFUNCTION("""COMPUTED_VALUE"""),"Farmer") -> Farmer | P9: =IFERROR(__xludf.DUMMYFUNCTION("""COMPUTED_VALUE"""),"West Bengal ") -> West Bengal | Q9: =IFERROR(__xludf.DUMMYFUNCTION("""COMPUTED_VALUE"""),9.735127557E9) -> 9735127557 | R9: =IFERROR(__xludf.DUMMYFUNCTION("""COMPUTED_VALUE"""),"Jahuran bibi") -> Jahuran bibi | S9: =IFERROR(__xludf.DUMMYFUNCTION("""COMPUTED_VALUE"""),"House wife") -> House wife | T9: =IFERROR(__xludf.DUMMYFUNCTION("""COMPUTED_VALUE"""),"West Bengal ") -> West Bengal | U9: =IFERROR(__xludf.DUMMYFUNCTION("""COMPUTED_VALUE"""),9.735127557E9) -> 9735127557 | V9: =IFERROR(__xludf.DUMMYFUNCTION("""COMPUTED_VALUE"""),2.0) -> 2 | W9: =IFERROR(__xludf.DUMMYFUNCTION("""COMPUTED_VALUE"""),"Sk Mahammad ali") -> Sk Mahammad ali | X9: =IFERROR(__xludf.DUMMYFUNCTION("""COMPUTED_VALUE"""),"Father") -> Father | Y9: =IFERROR(__xludf.DUMMYFUNCTION("""COMPUTED_VALUE"""),"Mobina parveen") -> Mobina parveen | Z9: =IFERROR(__xludf.DUMMYFUNCTION("""COMPUTED_VALUE"""),"Mother") -> Mother | AA9: =IFERROR(__xludf.DUMMYFUNCTION("""COMPUTED_VALUE"""),"Non-Veg") -> Non-Veg | AB9: =IFERROR(__xludf.DUMMYFUNCTION("""COMPUTED_VALUE"""),"Non-Veg") -> Non-Veg | AC9: =IFERROR(__xludf.DUMMYFUNCTION("""COMPUTED_VALUE"""),"Non-Veg") -> Non-Veg | AD9: =IFERROR(__xludf.DUMMYFUNCTION("""COMPUTED_VALUE"""),"Bus Drop Service not needed") -> Bus Drop Service not needed | AE9: =IFERROR(__xludf.DUMMYFUNCTION("""COMPUTED_VALUE"""),0.0) -> 0
A10: =IFERROR(__xludf.DUMMYFUNCTION("""COMPUTED_VALUE"""),46266.558665578705) -> 46266.559 | B10: =IFERROR(__xludf.DUMMYFUNCTION("""COMPUTED_VALUE"""),"zinadzidan04@gmail.com") -> zinadzidan04@gmail.com | C10: =IFERROR(__xludf.DUMMYFUNCTION("""COMPUTED_VALUE"""),"Zinadin Zidan T K") -> Zinadin Zidan T K | D10: =IFERROR(__xludf.DUMMYFUNCTION("""COMPUTED_VALUE"""),115.0) -> 115 | E10: =IFERROR(__xludf.DUMMYFUNCTION("""COMPUTED_VALUE"""),"MBBS 2020") -> MBBS 2020 | F10: =IFERROR(__xludf.DUMMYFUNCTION("""COMPUTED_VALUE"""),9.633760376E9) -> 9633760376 | G10: =IFERROR(__xludf.DUMMYFUNCTION("""COMPUTED_VALUE"""),"zinadzidan04@gmail.com") -> zinadzidan04@gmail.com | H10: =IFERROR(__xludf.DUMMYFUNCTION("""COMPUTED_VALUE"""),"Yes") -> Yes | I10: =IFERROR(__xludf.DUMMYFUNCTION("""COMPUTED_VALUE"""),"Sports, Arts, Music") -> Sports, Arts, Music | J10: =IFERROR(__xludf.DUMMYFUNCTION("""COMPUTED_VALUE"""),"Football ") -> Football | K10: =IFERROR(__xludf.DUMMYFUNCTION("""COMPUTED_VALUE"""),"Kerala") -> Kerala | L10: =IFERROR(__xludf.DUMMYFUNCTION("""COMPUTED_VALUE"""),"https://drive.google.com/open?id=1M-D4W3wo5ygIcbAyfOurXfqgDnkj9rSQ") -> https://drive.google.com/open?id=1M-D4W3wo5ygIcbAyfOurXfqgDnkj9rSQ | M10: =IFERROR(__xludf.DUMMYFUNCTION("""COMPUTED_VALUE"""),"https://drive.google.com/open?id=1989rqVJ9nuAXRtx40x4Jix1B8K1W6Ps5") -> https://drive.google.com/open?id=1989rqVJ9nuAXRtx40x4Jix1B8K1W6Ps5 | N10: =IFERROR(__xludf.DUMMYFUNCTION("""COMPUTED_VALUE"""),"Hamza T K") -> Hamza T K | O10: =IFERROR(__xludf.DUMMYFUNCTION("""COMPUTED_VALUE"""),"Doctor") -> Doctor | P10: =IFERROR(__xludf.DUMMYFUNCTION("""COMPUTED_VALUE"""),"Pattambi, Palakkad , Kerala") -> Pattambi, Palakkad , Kerala | Q10: =IFERROR(__xludf.DUMMYFUNCTION("""COMPUTED_VALUE"""),9.567736799E9) -> 9567736799 | R10: =IFERROR(__xludf.DUMMYFUNCTION("""COMPUTED_VALUE"""),"Rajeens K K") -> Rajeens K K | S10: =IFERROR(__xludf.DUMMYFUNCTION("""COMPUTED_VALUE"""),"Administrator") -> Administrator | T10: =IFERROR(__xludf.DUMMYFUNCTION("""COMPUTED_VALUE"""),"Pattambi, Palakkad , Kerala") -> Pattambi, Palakkad , Kerala | U10: =IFERROR(__xludf.DUMMYFUNCTION("""COMPUTED_VALUE"""),9.746380679E9) -> 9746380679 | V10: =IFERROR(__xludf.DUMMYFUNCTION("""COMPUTED_VALUE"""),2.0) -> 2 | W10: =IFERROR(__xludf.DUMMYFUNCTION("""COMPUTED_VALUE"""),"Hamza T K") -> Hamza T K | X10: =IFERROR(__xludf.DUMMYFUNCTION("""COMPUTED_VALUE"""),"Father") -> Father | Y10: =IFERROR(__xludf.DUMMYFUNCTION("""COMPUTED_VALUE"""),"Rajeena K K") -> Rajeena K K | Z10: =IFERROR(__xludf.DUMMYFUNCTION("""COMPUTED_VALUE"""),"Mother") -> Mother | AA10: =IFERROR(__xludf.DUMMYFUNCTION("""COMPUTED_VALUE"""),"Non-Veg") -> Non-Veg | AB10: =IFERROR(__xludf.DUMMYFUNCTION("""COMPUTED_VALUE"""),"Non-Veg") -> Non-Veg | AC10: =IFERROR(__xludf.DUMMYFUNCTION("""COMPUTED_VALUE"""),"Non-Veg") -> Non-Veg | AD10: =IFERROR(__xludf.DUMMYFUNCTION("""COMPUTED_VALUE"""),"Bus Drop Service not needed") -> Bus Drop Service not needed | AE10: =IFERROR(__xludf.DUMMYFUNCTION("""COMPUTED_VALUE"""),0.0) -> 0
A11: =IFERROR(__xludf.DUMMYFUNCTION("""COMPUTED_VALUE"""),46266.481394965274) -> 46266.481 | B11: =IFERROR(__xludf.DUMMYFUNCTION("""COMPUTED_VALUE"""),"siddharth.mbbs-2020@aiimskalyani.edu.in") -> siddharth.mbbs-2020@aiimskalyani.edu.in | C11: =IFERROR(__xludf.DUMMYFUNCTION("""COMPUTED_VALUE"""),"VADDE SIDDHARTH ROY") -> VADDE SIDDHARTH ROY | D11: =IFERROR(__xludf.DUMMYFUNCTION("""COMPUTED_VALUE"""),"109/ 202001159") -> 109/ 202001159 | E11: =IFERROR(__xludf.DUMMYFUNCTION("""COMPUTED_VALUE"""),"MBBS 2020") -> MBBS 2020 | F11: =IFERROR(__xludf.DUMMYFUNCTION("""COMPUTED_VALUE"""),9.866469739E9) -> 9866469739 | G11: =IFERROR(__xludf.DUMMYFUNCTION("""COMPUTED_VALUE"""),"imsidroy1@gmail.com") -> imsidroy1@gmail.com | H11: =IFERROR(__xludf.DUMMYFUNCTION("""COMPUTED_VALUE"""),"Yes") -> Yes | K11: =IFERROR(__xludf.DUMMYFUNCTION("""COMPUTED_VALUE"""),"Visakhapatnam") -> Visakhapatnam | L11: =IFERROR(__xludf.DUMMYFUNCTION("""COMPUTED_VALUE"""),"https://drive.google.com/open?id=10xhv7vy3irtFqB4uwlalaHDfwFIwiAco") -> https://drive.google.com/open?id=10xhv7vy3irtFqB4uwlalaHDfwFIwiAco | M11: =IFERROR(__xludf.DUMMYFUNCTION("""COMPUTED_VALUE"""),"https://drive.google.com/open?id=1i3I0yBWBZAUnQQN5VFngO53ZQQxoBL9S") -> https://drive.google.com/open?id=1i3I0yBWBZAUnQQN5VFngO53ZQQxoBL9S | N11: =IFERROR(__xludf.DUMMYFUNCTION("""COMPUTED_VALUE"""),"DR VC SEKHAR") -> DR VC SEKHAR | O11: =IFERROR(__xludf.DUMMYFUNCTION("""COMPUTED_VALUE"""),"DOCTOR, ADDITIONAL PROFESSOR, FMT, AIIMS DEOGARH") -> DOCTOR, ADDITIONAL PROFESSOR, FMT, AIIMS DEOGARH | P11: =IFERROR(__xludf.DUMMYFUNCTION("""COMPUTED_VALUE"""),"Deogarh") -> Deogarh | Q11: =IFERROR(__xludf.DUMMYFUNCTION("""COMPUTED_VALUE"""),9.985360834E9) -> 9985360834 | R11: =IFERROR(__xludf.DUMMYFUNCTION("""COMPUTED_VALUE"""),"VADDE SHILA ROY") -> VADDE SHILA ROY | S11: =IFERROR(__xludf.DUMMYFUNCTION("""COMPUTED_VALUE"""),"HOUSEWIFE") -> HOUSEWIFE | T11: =IFERROR(__xludf.DUMMYFUNCTION("""COMPUTED_VALUE"""),"Kolkata") -> Kolkata | U11: =IFERROR(__xludf.DUMMYFUNCTION("""COMPUTED_VALUE"""),9.392563015E9) -> 9392563015 | V11: =IFERROR(__xludf.DUMMYFUNCTION("""COMPUTED_VALUE"""),2.0) -> 2 | W11: =IFERROR(__xludf.DUMMYFUNCTION("""COMPUTED_VALUE"""),"Dr VC Sekhar") -> Dr VC Sekhar | X11: =IFERROR(__xludf.DUMMYFUNCTION("""COMPUTED_VALUE"""),"Father") -> Father | Y11: =IFERROR(__xludf.DUMMYFUNCTION("""COMPUTED_VALUE"""),"V Shila Roy") -> V Shila Roy | Z11: =IFERROR(__xludf.DUMMYFUNCTION("""COMPUTED_VALUE"""),"Mother") -> Mother | AA11: =IFERROR(__xludf.DUMMYFUNCTION("""COMPUTED_VALUE"""),"Non-Veg") -> Non-Veg | AB11: =IFERROR(__xludf.DUMMYFUNCTION("""COMPUTED_VALUE"""),"Non-Veg") -> Non-Veg | AC11: =IFERROR(__xludf.DUMMYFUNCTION("""COMPUTED_VALUE"""),"Non-Veg") -> Non-Veg | AD11: =IFERROR(__xludf.DUMMYFUNCTION("""COMPUTED_VALUE"""),"Bus Drop Service not needed") -> Bus Drop Service not needed | AE11: =IFERROR(__xludf.DUMMYFUNCTION("""COMPUTED_VALUE"""),0.0) -> 0
A12: =IFERROR(__xludf.DUMMYFUNCTION("""COMPUTED_VALUE"""),46266.46422628472) -> 46266.464 | B12: =IFERROR(__xludf.DUMMYFUNCTION("""COMPUTED_VALUE"""),"sony.mbbs-2020@aiimskalyani.edu.in") -> sony.mbbs-2020@aiimskalyani.edu.in | C12: =IFERROR(__xludf.DUMMYFUNCTION("""COMPUTED_VALUE"""),"SONY KHATOON ") -> SONY KHATOON | D12: =IFERROR(__xludf.DUMMYFUNCTION("""COMPUTED_VALUE"""),"97/202001147") -> 97/202001147 | E12: =IFERROR(__xludf.DUMMYFUNCTION("""COMPUTED_VALUE"""),"MBBS 2020") -> MBBS 2020 | F12: =IFERROR(__xludf.DUMMYFUNCTION("""COMPUTED_VALUE"""),8.709565947E9) -> 8709565947 | G12: =IFERROR(__xludf.DUMMYFUNCTION("""COMPUTED_VALUE"""),"sony.mbbs-2020@aiimskalyani.edu.in") -> sony.mbbs-2020@aiimskalyani.edu.in | H12: =IFERROR(__xludf.DUMMYFUNCTION("""COMPUTED_VALUE"""),"Yes") -> Yes | I12: =IFERROR(__xludf.DUMMYFUNCTION("""COMPUTED_VALUE"""),"Gyming and dance") -> Gyming and dance | J12: =IFERROR(__xludf.DUMMYFUNCTION("""COMPUTED_VALUE"""),"Marathons ") -> Marathons | K12: =IFERROR(__xludf.DUMMYFUNCTION("""COMPUTED_VALUE"""),"Siwan") -> Siwan | L12: =IFERROR(__xludf.DUMMYFUNCTION("""COMPUTED_VALUE"""),"https://drive.google.com/open?id=1CZRSnWf_Tvwz_LZCA7mBxfN3PmHu60v-") -> https://drive.google.com/open?id=1CZRSnWf_Tvwz_LZCA7mBxfN3PmHu60v- | M12: =IFERROR(__xludf.DUMMYFUNCTION("""COMPUTED_VALUE"""),"https://drive.google.com/open?id=1-0aJHuCjtlKlezrTUbLXkRpkdhAF4M-v") -> https://drive.google.com/open?id=1-0aJHuCjtlKlezrTUbLXkRpkdhAF4M-v | N12: =IFERROR(__xludf.DUMMYFUNCTION("""COMPUTED_VALUE"""),"MD Aslam ") -> MD Aslam | O12: =IFERROR(__xludf.DUMMYFUNCTION("""COMPUTED_VALUE"""),"Business man") -> Business man | P12: =IFERROR(__xludf.DUMMYFUNCTION("""COMPUTED_VALUE"""),"Siwan") -> Siwan | Q12: =IFERROR(__xludf.DUMMYFUNCTION("""COMPUTED_VALUE"""),8.084542094E9) -> 8084542094 | R12: =IFERROR(__xludf.DUMMYFUNCTION("""COMPUTED_VALUE"""),"Husan tara khatoon") -> Husan tara khatoon | S12: =IFERROR(__xludf.DUMMYFUNCTION("""COMPUTED_VALUE"""),"Housewife ") -> Housewife | T12: =IFERROR(__xludf.DUMMYFUNCTION("""COMPUTED_VALUE"""),"Siwan ") -> Siwan | U12: =IFERROR(__xludf.DUMMYFUNCTION("""COMPUTED_VALUE"""),7.739530495E9) -> 7739530495 | V12: =IFERROR(__xludf.DUMMYFUNCTION("""COMPUTED_VALUE"""),2.0) -> 2 | W12: =IFERROR(__xludf.DUMMYFUNCTION("""COMPUTED_VALUE"""),"MD Aslam ") -> MD Aslam | X12: =IFERROR(__xludf.DUMMYFUNCTION("""COMPUTED_VALUE"""),"Father ") -> Father | Y12: =IFERROR(__xludf.DUMMYFUNCTION("""COMPUTED_VALUE"""),"Husan tara khatoon ") -> Husan tara khatoon | Z12: =IFERROR(__xludf.DUMMYFUNCTION("""COMPUTED_VALUE"""),"Mother ") -> Mother | AA12: =IFERROR(__xludf.DUMMYFUNCTION("""COMPUTED_VALUE"""),"Non-Veg") -> Non-Veg | AB12: =IFERROR(__xludf.DUMMYFUNCTION("""COMPUTED_VALUE"""),"Non-Veg") -> Non-Veg | AC12: =IFERROR(__xludf.DUMMYFUNCTION("""COMPUTED_VALUE"""),"Non-Veg") -> Non-Veg | AD12: =IFERROR(__xludf.DUMMYFUNCTION("""COMPUTED_VALUE"""),"Bus Drop Service not needed") -> Bus Drop Service not needed | AE12: =IFERROR(__xludf.DUMMYFUNCTION("""COMPUTED_VALUE"""),0.0) -> 0
A13: =IFERROR(__xludf.DUMMYFUNCTION("""COMPUTED_VALUE"""),46266.00153799768) -> 46266.002 | B13: =IFERROR(__xludf.DUMMYFUNCTION("""COMPUTED_VALUE"""),"tanmay.mbbs-2020@aiimskalyani.edu.in") -> tanmay.mbbs-2020@aiimskalyani.edu.in | C13: =IFERROR(__xludf.DUMMYFUNCTION("""COMPUTED_VALUE"""),"TANMAY SAHA") -> TANMAY SAHA | D13: =IFERROR(__xludf.DUMMYFUNCTION("""COMPUTED_VALUE"""),"105/202001155") -> 105/202001155 | E13: =IFERROR(__xludf.DUMMYFUNCTION("""COMPUTED_VALUE"""),"MBBS 2020") -> MBBS 2020 | F13: =IFERROR(__xludf.DUMMYFUNCTION("""COMPUTED_VALUE"""),6.290905708E9) -> 6290905708 | G13: =IFERROR(__xludf.DUMMYFUNCTION("""COMPUTED_VALUE"""),"tanmay.mbbs-2020@aiimskalyani.edu.in") -> tanmay.mbbs-2020@aiimskalyani.edu.in | H13: =IFERROR(__xludf.DUMMYFUNCTION("""COMPUTED_VALUE"""),"Yes") -> Yes | I13: =IFERROR(__xludf.DUMMYFUNCTION("""COMPUTED_VALUE"""),"Playing cricket and listening to songs ") -> Playing cricket and listening to songs | J13: =IFERROR(__xludf.DUMMYFUNCTION("""COMPUTED_VALUE"""),"Cricket , football ") -> Cricket , football | K13: =IFERROR(__xludf.DUMMYFUNCTION("""COMPUTED_VALUE"""),"Kolkata") -> Kolkata | L13: =IFERROR(__xludf.DUMMYFUNCTION("""COMPUTED_VALUE"""),"https://drive.google.com/open?id=11goryPOB2TYIacdjkzHvRVM6d1KfI3y1") -> https://drive.google.com/open?id=11goryPOB2TYIacdjkzHvRVM6d1KfI3y1 | M13: =IFERROR(__xludf.DUMMYFUNCTION("""COMPUTED_VALUE"""),"https://drive.google.com/open?id=1FHcUgE3Nn-ylYv8bQf9lYQNBHDDDEIGg") -> https://drive.google.com/open?id=1FHcUgE3Nn-ylYv8bQf9lYQNBHDDDEIGg | N13: =IFERROR(__xludf.DUMMYFUNCTION("""COMPUTED_VALUE"""),"Goutam Saha") -> Goutam Saha | O13: =IFERROR(__xludf.DUMMYFUNCTION("""COMPUTED_VALUE"""),"Businessman ") -> Businessman | P13: =IFERROR(__xludf.DUMMYFUNCTION("""COMPUTED_VALUE"""),"Kolkata") -> Kolkata | Q13: =IFERROR(__xludf.DUMMYFUNCTION("""COMPUTED_VALUE"""),9.051969119E9) -> 9051969119 | R13: =IFERROR(__xludf.DUMMYFUNCTION("""COMPUTED_VALUE"""),"Uma Saha") -> Uma Saha | S13: =IFERROR(__xludf.DUMMYFUNCTION("""COMPUTED_VALUE"""),"Housewife") -> Housewife | T13: =IFERROR(__xludf.DUMMYFUNCTION("""COMPUTED_VALUE"""),"Kolkata") -> Kolkata | U13: =IFERROR(__xludf.DUMMYFUNCTION("""COMPUTED_VALUE"""),7.003264069E9) -> 7003264069 | V13: =IFERROR(__xludf.DUMMYFUNCTION("""COMPUTED_VALUE"""),2.0) -> 2 | W13: =IFERROR(__xludf.DUMMYFUNCTION("""COMPUTED_VALUE"""),"Goutam Saha") -> Goutam Saha | X13: =IFERROR(__xludf.DUMMYFUNCTION("""COMPUTED_VALUE"""),"Father") -> Father | Y13: =IFERROR(__xludf.DUMMYFUNCTION("""COMPUTED_VALUE"""),"Uma Saha") -> Uma Saha | Z13: =IFERROR(__xludf.DUMMYFUNCTION("""COMPUTED_VALUE"""),"Mother") -> Mother | AA13: =IFERROR(__xludf.DUMMYFUNCTION("""COMPUTED_VALUE"""),"Non-Veg") -> Non-Veg | AB13: =IFERROR(__xludf.DUMMYFUNCTION("""COMPUTED_VALUE"""),"Non-Veg") -> Non-Veg | AC13: =IFERROR(__xludf.DUMMYFUNCTION("""COMPUTED_VALUE"""),"Non-Veg") -> Non-Veg | AD13: =IFERROR(__xludf.DUMMYFUNCTION("""COMPUTED_VALUE"""),"Bus Drop Service not needed") -> Bus Drop Service not needed
A14: =IFERROR(__xludf.DUMMYFUNCTION("""COMPUTED_VALUE"""),46265.99744195602) -> 46265.997 | B14: =IFERROR(__xludf.DUMMYFUNCTION("""COMPUTED_VALUE"""),"ambuj.mbbs-2020@aiimskalyani.edu.in") -> ambuj.mbbs-2020@aiimskalyani.edu.in | C14: =IFERROR(__xludf.DUMMYFUNCTION("""COMPUTED_VALUE"""),"AMBUJ PANDEY ") -> AMBUJ PANDEY | D14: =IFERROR(__xludf.DUMMYFUNCTION("""COMPUTED_VALUE"""),"12/20200162") -> 12/20200162 | E14: =IFERROR(__xludf.DUMMYFUNCTION("""COMPUTED_VALUE"""),"MBBS 2020") -> MBBS 2020 | F14: =IFERROR(__xludf.DUMMYFUNCTION("""COMPUTED_VALUE"""),8.858150858E9) -> 8858150858 | G14: =IFERROR(__xludf.DUMMYFUNCTION("""COMPUTED_VALUE"""),"ambuj.mbbs-2020@aiimskalyani.edu.in") -> ambuj.mbbs-2020@aiimskalyani.edu.in | H14: =IFERROR(__xludf.DUMMYFUNCTION("""COMPUTED_VALUE"""),"Yes") -> Yes | I14: =IFERROR(__xludf.DUMMYFUNCTION("""COMPUTED_VALUE"""),"Poem writing and traveling ") -> Poem writing and traveling | J14: =IFERROR(__xludf.DUMMYFUNCTION("""COMPUTED_VALUE"""),"Badminton and cricket ") -> Badminton and cricket | K14: =IFERROR(__xludf.DUMMYFUNCTION("""COMPUTED_VALUE"""),"Pratapgarh Uttar Pradesh ") -> Pratapgarh Uttar Pradesh | L14: =IFERROR(__xludf.DUMMYFUNCTION("""COMPUTED_VALUE"""),"https://drive.google.com/open?id=1yxXcQgKHp03sbWdJCsMI1uVsI9eGmgzX") -> https://drive.google.com/open?id=1yxXcQgKHp03sbWdJCsMI1uVsI9eGmgzX | M14: =IFERROR(__xludf.DUMMYFUNCTION("""COMPUTED_VALUE"""),"https://drive.google.com/open?id=1a5dDewq0XyzTJdj2lmkaQFredhPZ8oiu") -> https://drive.google.com/open?id=1a5dDewq0XyzTJdj2lmkaQFredhPZ8oiu | N14: =IFERROR(__xludf.DUMMYFUNCTION("""COMPUTED_VALUE"""),"Rakesh kumar pandey ") -> Rakesh kumar pandey | O14: =IFERROR(__xludf.DUMMYFUNCTION("""COMPUTED_VALUE"""),"UP government teacher ") -> UP government teacher | P14: =IFERROR(__xludf.DUMMYFUNCTION("""COMPUTED_VALUE"""),"Pratapgarh Uttar Pradesh ") -> Pratapgarh Uttar Pradesh | Q14: =IFERROR(__xludf.DUMMYFUNCTION("""COMPUTED_VALUE"""),9.452691066E9) -> 9452691066 | R14: =IFERROR(__xludf.DUMMYFUNCTION("""COMPUTED_VALUE"""),"Anita Pandey ") -> Anita Pandey | S14: =IFERROR(__xludf.DUMMYFUNCTION("""COMPUTED_VALUE"""),"Homemaker ") -> Homemaker | T14: =IFERROR(__xludf.DUMMYFUNCTION("""COMPUTED_VALUE"""),"Pratapgarh Uttar Pradesh ") -> Pratapgarh Uttar Pradesh | U14: =IFERROR(__xludf.DUMMYFUNCTION("""COMPUTED_VALUE"""),7.880797519E9) -> 7880797519 | V14: =IFERROR(__xludf.DUMMYFUNCTION("""COMPUTED_VALUE"""),0.0) -> 0 | AA14: =IFERROR(__xludf.DUMMYFUNCTION("""COMPUTED_VALUE"""),"Veg") -> Veg | AD14: =IFERROR(__xludf.DUMMYFUNCTION("""COMPUTED_VALUE"""),"Bus Drop Service not needed") -> Bus Drop Service not needed | AE14: =IFERROR(__xludf.DUMMYFUNCTION("""COMPUTED_VALUE"""),0.0) -> 0
A15: =IFERROR(__xludf.DUMMYFUNCTION("""COMPUTED_VALUE"""),46265.986441030094) -> 46265.986 | B15: =IFERROR(__xludf.DUMMYFUNCTION("""COMPUTED_VALUE"""),"shruti.mbbs-2020@aiimskalyani.edu.in") -> shruti.mbbs-2020@aiimskalyani.edu.in | C15: =IFERROR(__xludf.DUMMYFUNCTION("""COMPUTED_VALUE"""),"SHRUTI JOSHI") -> SHRUTI JOSHI | D15: =IFERROR(__xludf.DUMMYFUNCTION("""COMPUTED_VALUE"""),94.0) -> 94 | E15: =IFERROR(__xludf.DUMMYFUNCTION("""COMPUTED_VALUE"""),"MBBS 2020") -> MBBS 2020 | F15: =IFERROR(__xludf.DUMMYFUNCTION("""COMPUTED_VALUE"""),8.696426826E9) -> 8696426826 | G15: =IFERROR(__xludf.DUMMYFUNCTION("""COMPUTED_VALUE"""),"shrutijoshi0304@gmail.com") -> shrutijoshi0304@gmail.com | H15: =IFERROR(__xludf.DUMMYFUNCTION("""COMPUTED_VALUE"""),"Yes") -> Yes | I15: =IFERROR(__xludf.DUMMYFUNCTION("""COMPUTED_VALUE"""),"I enjoy music, travelling, and discovering new cultures. Exploring new places and perspectives is something I find both enriching and inspiring.") -> I enjoy music, travelling, and discovering new cultures. Exploring new places and perspectives is something I find both enriching and inspiring. | J15: =IFERROR(__xludf.DUMMYFUNCTION("""COMPUTED_VALUE"""),"I actively engaged in Table Tennis and Volleyball, while also participating in debates and academic seminars.") -> I actively engaged in Table Tennis and Volleyball, while also participating in debates and academic seminars. | K15: =IFERROR(__xludf.DUMMYFUNCTION("""COMPUTED_VALUE"""),"Sriganganagar ") -> Sriganganagar | L15: =IFERROR(__xludf.DUMMYFUNCTION("""COMPUTED_VALUE"""),"https://drive.google.com/open?id=1Iuo0d78nvubtjbvAZTUSrp3IIgHANyga") -> https://drive.google.com/open?id=1Iuo0d78nvubtjbvAZTUSrp3IIgHANyga | M15: =IFERROR(__xludf.DUMMYFUNCTION("""COMPUTED_VALUE"""),"https://drive.google.com/open?id=1YRsoLSkvFvuYI3QOjozfRsPJ7tcT5nOU") -> https://drive.google.com/open?id=1YRsoLSkvFvuYI3QOjozfRsPJ7tcT5nOU | N15: =IFERROR(__xludf.DUMMYFUNCTION("""COMPUTED_VALUE"""),"Ramesh Kumar Joshi") -> Ramesh Kumar Joshi | O15: =IFERROR(__xludf.DUMMYFUNCTION("""COMPUTED_VALUE"""),"Business Manager") -> Business Manager | P15: =IFERROR(__xludf.DUMMYFUNCTION("""COMPUTED_VALUE"""),"Sriganganagar ") -> Sriganganagar | Q15: =IFERROR(__xludf.DUMMYFUNCTION("""COMPUTED_VALUE"""),9.414948421E9) -> 9414948421 | R15: =IFERROR(__xludf.DUMMYFUNCTION("""COMPUTED_VALUE"""),"Harsha Joshi") -> Harsha Joshi | S15: =IFERROR(__xludf.DUMMYFUNCTION("""COMPUTED_VALUE"""),"Homemaker") -> Homemaker | T15: =IFERROR(__xludf.DUMMYFUNCTION("""COMPUTED_VALUE"""),"Sriganganagar") -> Sriganganagar | U15: =IFERROR(__xludf.DUMMYFUNCTION("""COMPUTED_VALUE"""),8.005540019E9) -> 8005540019 | V15: =IFERROR(__xludf.DUMMYFUNCTION("""COMPUTED_VALUE"""),2.0) -> 2 | W15: =IFERROR(__xludf.DUMMYFUNCTION("""COMPUTED_VALUE"""),"Ramesh Kumar Joshi ") -> Ramesh Kumar Joshi | X15: =IFERROR(__xludf.DUMMYFUNCTION("""COMPUTED_VALUE"""),"Father ") -> Father | Y15: =IFERROR(__xludf.DUMMYFUNCTION("""COMPUTED_VALUE"""),"Harsha Joshi ") -> Harsha Joshi | Z15: =IFERROR(__xludf.DUMMYFUNCTION("""COMPUTED_VALUE"""),"Mother") -> Mother | AA15: =IFERROR(__xludf.DUMMYFUNCTION("""COMPUTED_VALUE"""),"Veg") -> Veg | AB15: =IFERROR(__xludf.DUMMYFUNCTION("""COMPUTED_VALUE"""),"Veg") -> Veg | AC15: =IFERROR(__xludf.DUMMYFUNCTION("""COMPUTED_VALUE"""),"Veg") -> Veg | AD15: =IFERROR(__xludf.DUMMYFUNCTION("""COMPUTED_VALUE"""),"Drop at Kolkata Airport") -> Drop at Kolkata Airport | AE15: =IFERROR(__xludf.DUMMYFUNCTION("""COMPUTED_VALUE"""),3.0) -> 3
A16: =IFERROR(__xludf.DUMMYFUNCTION("""COMPUTED_VALUE"""),46265.98223854166) -> 46265.982 | B16: =IFERROR(__xludf.DUMMYFUNCTION("""COMPUTED_VALUE"""),"anurag.mbbs-2020@aiimskalyani.edu.in") -> anurag.mbbs-2020@aiimskalyani.edu.in | C16: =IFERROR(__xludf.DUMMYFUNCTION("""COMPUTED_VALUE"""),"ANURAG DASH") -> ANURAG DASH | D16: =IFERROR(__xludf.DUMMYFUNCTION("""COMPUTED_VALUE"""),"20/20200170") -> 20/20200170 | E16: =IFERROR(__xludf.DUMMYFUNCTION("""COMPUTED_VALUE"""),"MBBS 2020") -> MBBS 2020 | F16: =IFERROR(__xludf.DUMMYFUNCTION("""COMPUTED_VALUE"""),6.372093986E9) -> 6372093986 | G16: =IFERROR(__xludf.DUMMYFUNCTION("""COMPUTED_VALUE"""),"anurag.mbbs-2020@aiimskalyani.edu.in") -> anurag.mbbs-2020@aiimskalyani.edu.in | H16: =IFERROR(__xludf.DUMMYFUNCTION("""COMPUTED_VALUE"""),"Yes") -> Yes | I16: =IFERROR(__xludf.DUMMYFUNCTION("""COMPUTED_VALUE"""),"Playing chess") -> Playing chess | J16: =IFERROR(__xludf.DUMMYFUNCTION("""COMPUTED_VALUE"""),"Quizzes ") -> Quizzes | K16: =IFERROR(__xludf.DUMMYFUNCTION("""COMPUTED_VALUE"""),"Berhampur, Odisha") -> Berhampur, Odisha | L16: =IFERROR(__xludf.DUMMYFUNCTION("""COMPUTED_VALUE"""),"https://drive.google.com/open?id=186LcgNOSkGAlU3RLkMn2rUPaWAjK7isa") -> https://drive.google.com/open?id=186LcgNOSkGAlU3RLkMn2rUPaWAjK7isa | M16: =IFERROR(__xludf.DUMMYFUNCTION("""COMPUTED_VALUE"""),"https://drive.google.com/open?id=1gxavYVwvB4XMS9LExB-QV4jEsZX5sR-S") -> https://drive.google.com/open?id=1gxavYVwvB4XMS9LExB-QV4jEsZX5sR-S | N16: =IFERROR(__xludf.DUMMYFUNCTION("""COMPUTED_VALUE"""),"Sushanta Kumar Dash") -> Sushanta Kumar Dash | O16: =IFERROR(__xludf.DUMMYFUNCTION("""COMPUTED_VALUE"""),"Pensioner") -> Pensioner | P16: =IFERROR(__xludf.DUMMYFUNCTION("""COMPUTED_VALUE"""),"Berhampur") -> Berhampur | Q16: =IFERROR(__xludf.DUMMYFUNCTION("""COMPUTED_VALUE"""),9.437927325E9) -> 9437927325 | R16: =IFERROR(__xludf.DUMMYFUNCTION("""COMPUTED_VALUE"""),"Swarnalata Dash") -> Swarnalata Dash | S16: =IFERROR(__xludf.DUMMYFUNCTION("""COMPUTED_VALUE"""),"Homemaker") -> Homemaker | T16: =IFERROR(__xludf.DUMMYFUNCTION("""COMPUTED_VALUE"""),"Berhampur") -> Berhampur | U16: =IFERROR(__xludf.DUMMYFUNCTION("""COMPUTED_VALUE"""),9.438617625E9) -> 9438617625 | V16: =IFERROR(__xludf.DUMMYFUNCTION("""COMPUTED_VALUE"""),2.0) -> 2 | W16: =IFERROR(__xludf.DUMMYFUNCTION("""COMPUTED_VALUE"""),"Sushanta Kumar Dash") -> Sushanta Kumar Dash | X16: =IFERROR(__xludf.DUMMYFUNCTION("""COMPUTED_VALUE"""),"Father") -> Father | Y16: =IFERROR(__xludf.DUMMYFUNCTION("""COMPUTED_VALUE"""),"Swarnalata Dash") -> Swarnalata Dash | Z16: =IFERROR(__xludf.DUMMYFUNCTION("""COMPUTED_VALUE"""),"Mother") -> Mother | AA16: =IFERROR(__xludf.DUMMYFUNCTION("""COMPUTED_VALUE"""),"Non-Veg") -> Non-Veg | AB16: =IFERROR(__xludf.DUMMYFUNCTION("""COMPUTED_VALUE"""),"Veg") -> Veg | AC16: =IFERROR(__xludf.DUMMYFUNCTION("""COMPUTED_VALUE"""),"Veg") -> Veg | AD16: =IFERROR(__xludf.DUMMYFUNCTION("""COMPUTED_VALUE"""),"Bus Drop Service not needed") -> Bus Drop Service not needed | AE16: =IFERROR(__xludf.DUMMYFUNCTION("""COMPUTED_VALUE"""),0.0) -> 0
A17: =IFERROR(__xludf.DUMMYFUNCTION("""COMPUTED_VALUE"""),46265.98220789352) -> 46265.982 | B17: =IFERROR(__xludf.DUMMYFUNCTION("""COMPUTED_VALUE"""),"devi.mbbs-2020@aiimskalyani.edu.in") -> devi.mbbs-2020@aiimskalyani.edu.in | C17: =IFERROR(__xludf.DUMMYFUNCTION("""COMPUTED_VALUE"""),"DEVI NAMBIAR") -> DEVI NAMBIAR | D17: =IFERROR(__xludf.DUMMYFUNCTION("""COMPUTED_VALUE"""),2.0200193E7) -> 20200193 | E17: =IFERROR(__xludf.DUMMYFUNCTION("""COMPUTED_VALUE"""),"MBBS 2020") -> MBBS 2020 | F17: =IFERROR(__xludf.DUMMYFUNCTION("""COMPUTED_VALUE"""),7.356912559E9) -> 7356912559 | G17: =IFERROR(__xludf.DUMMYFUNCTION("""COMPUTED_VALUE"""),"devi.d.nambiar@gmail.com") -> devi.d.nambiar@gmail.com | H17: =IFERROR(__xludf.DUMMYFUNCTION("""COMPUTED_VALUE"""),"Yes") -> Yes | I17: =IFERROR(__xludf.DUMMYFUNCTION("""COMPUTED_VALUE"""),"Bharatnatyam watercolor painting Cat lover Literature Quizzing Swimming Tennis ") -> Bharatnatyam watercolor painting Cat lover Literature Quizzing Swimming Tennis | J17: =IFERROR(__xludf.DUMMYFUNCTION("""COMPUTED_VALUE"""),"Ex Cultural secretary Ex SPIC MACAY Secretary Multiple intra college awards for Bharatnatyam watercolor painting Literature Quizzing Ted x patna first prize poster making competition ") -> Ex Cultural secretary Ex SPIC MACAY Secretary Multiple intra college awards for Bharatnatyam watercolor painting Literature Quizzing Ted x patna first prize poster making competition | K17: =IFERROR(__xludf.DUMMYFUNCTION("""COMPUTED_VALUE"""),"BANGALORE ") -> BANGALORE | L17: =IFERROR(__xludf.DUMMYFUNCTION("""COMPUTED_VALUE"""),"https://drive.google.com/open?id=1Y2dZr6oqriAc0VBw54p-NnkUfKaydew5") -> https://drive.google.com/open?id=1Y2dZr6oqriAc0VBw54p-NnkUfKaydew5 | M17: =IFERROR(__xludf.DUMMYFUNCTION("""COMPUTED_VALUE"""),"https://drive.google.com/open?id=11dQChh1KE1x2YIy-noS9o1we8DGi7Mfv") -> https://drive.google.com/open?id=11dQChh1KE1x2YIy-noS9o1we8DGi7Mfv | N17: =IFERROR(__xludf.DUMMYFUNCTION("""COMPUTED_VALUE"""),"DILEEP PURAVANKARA ") -> DILEEP PURAVANKARA | O17: =IFERROR(__xludf.DUMMYFUNCTION("""COMPUTED_VALUE"""),"SOFTWARE ENGINEER ") -> SOFTWARE ENGINEER | P17: =IFERROR(__xludf.DUMMYFUNCTION("""COMPUTED_VALUE"""),"BANGALORE ") -> BANGALORE | Q17: =IFERROR(__xludf.DUMMYFUNCTION("""COMPUTED_VALUE"""),9.88617735E9) -> 9886177350 | R17: =IFERROR(__xludf.DUMMYFUNCTION("""COMPUTED_VALUE"""),"VEENA S N ") -> VEENA S N | S17: =IFERROR(__xludf.DUMMYFUNCTION("""COMPUTED_VALUE"""),"CIVIL ENGINEER") -> CIVIL ENGINEER | T17: =IFERROR(__xludf.DUMMYFUNCTION("""COMPUTED_VALUE"""),"BANGALORE ") -> BANGALORE | U17: =IFERROR(__xludf.DUMMYFUNCTION("""COMPUTED_VALUE"""),9.886101921E9) -> 9886101921 | V17: =IFERROR(__xludf.DUMMYFUNCTION("""COMPUTED_VALUE"""),2.0) -> 2 | W17: =IFERROR(__xludf.DUMMYFUNCTION("""COMPUTED_VALUE"""),"VEENA S N") -> VEENA S N | X17: =IFERROR(__xludf.DUMMYFUNCTION("""COMPUTED_VALUE"""),"MOTHER") -> MOTHER | Y17: =IFERROR(__xludf.DUMMYFUNCTION("""COMPUTED_VALUE"""),"DILEEP PURAVANKARA ") -> DILEEP PURAVANKARA | Z17: =IFERROR(__xludf.DUMMYFUNCTION("""COMPUTED_VALUE"""),"FATHER ") -> FATHER | AA17: =IFERROR(__xludf.DUMMYFUNCTION("""COMPUTED_VALUE"""),"Non-Veg") -> Non-Veg | AB17: =IFERROR(__xludf.DUMMYFUNCTION("""COMPUTED_VALUE"""),"Non-Veg") -> Non-Veg | AC17: =IFERROR(__xludf.DUMMYFUNCTION("""COMPUTED_VALUE"""),"Veg") -> Veg | AD17: =IFERROR(__xludf.DUMMYFUNCTION("""COMPUTED_VALUE"""),"Drop at Kolkata Airport") -> Drop at Kolkata Airport
A18: =IFERROR(__xludf.DUMMYFUNCTION("""COMPUTED_VALUE"""),46265.97097018518) -> 46265.971 | B18: =IFERROR(__xludf.DUMMYFUNCTION("""COMPUTED_VALUE"""),"meenakshi.mbbs-2020@aiimskalyani.edu.in") -> meenakshi.mbbs-2020@aiimskalyani.edu.in | C18: =IFERROR(__xludf.DUMMYFUNCTION("""COMPUTED_VALUE"""),"MEENAKSHI MINA") -> MEENAKSHI MINA | D18: =IFERROR(__xludf.DUMMYFUNCTION("""COMPUTED_VALUE"""),2.02001111E8) -> 202001111 | E18: =IFERROR(__xludf.DUMMYFUNCTION("""COMPUTED_VALUE"""),"MBBS 2020") -> MBBS 2020 | F18: =IFERROR(__xludf.DUMMYFUNCTION("""COMPUTED_VALUE"""),6.367552915E9) -> 6367552915 | G18: =IFERROR(__xludf.DUMMYFUNCTION("""COMPUTED_VALUE"""),"meenakshi.mbbs-2020@aiimskalyani.edu.in") -> meenakshi.mbbs-2020@aiimskalyani.edu.in | H18: =IFERROR(__xludf.DUMMYFUNCTION("""COMPUTED_VALUE"""),"Yes") -> Yes | I18: =IFERROR(__xludf.DUMMYFUNCTION("""COMPUTED_VALUE"""),"Arts , painting ") -> Arts , painting | J18: =IFERROR(__xludf.DUMMYFUNCTION("""COMPUTED_VALUE"""),"Running, swiming,badminton ") -> Running, swiming,badminton | K18: =IFERROR(__xludf.DUMMYFUNCTION("""COMPUTED_VALUE"""),"Jhalawar ") -> Jhalawar | L18: =IFERROR(__xludf.DUMMYFUNCTION("""COMPUTED_VALUE"""),"https://drive.google.com/open?id=1Tpl57DoaUPa_GxVxbIOx1j_egxVgcI7H") -> https://drive.google.com/open?id=1Tpl57DoaUPa_GxVxbIOx1j_egxVgcI7H | M18: =IFERROR(__xludf.DUMMYFUNCTION("""COMPUTED_VALUE"""),"https://drive.google.com/open?id=1HzBSs6YLa97rZJUyb8eoZBRTlxP_rFt8") -> https://drive.google.com/open?id=1HzBSs6YLa97rZJUyb8eoZBRTlxP_rFt8 | N18: =IFERROR(__xludf.DUMMYFUNCTION("""COMPUTED_VALUE"""),"Madan lal mina") -> Madan lal mina | O18: =IFERROR(__xludf.DUMMYFUNCTION("""COMPUTED_VALUE"""),"Business") -> Business | P18: =IFERROR(__xludf.DUMMYFUNCTION("""COMPUTED_VALUE"""),"Jhalawar ") -> Jhalawar | Q18: =IFERROR(__xludf.DUMMYFUNCTION("""COMPUTED_VALUE"""),9.829809231E9) -> 9829809231 | R18: =IFERROR(__xludf.DUMMYFUNCTION("""COMPUTED_VALUE"""),"Sona mina") -> Sona mina | S18: =IFERROR(__xludf.DUMMYFUNCTION("""COMPUTED_VALUE"""),"Housemaker ") -> Housemaker | T18: =IFERROR(__xludf.DUMMYFUNCTION("""COMPUTED_VALUE"""),"Jhalawar ") -> Jhalawar | U18: =IFERROR(__xludf.DUMMYFUNCTION("""COMPUTED_VALUE"""),7.625789646E9) -> 7625789646 | V18: =IFERROR(__xludf.DUMMYFUNCTION("""COMPUTED_VALUE"""),2.0) -> 2 | W18: =IFERROR(__xludf.DUMMYFUNCTION("""COMPUTED_VALUE"""),"Madan lal mina ") -> Madan lal mina | X18: =IFERROR(__xludf.DUMMYFUNCTION("""COMPUTED_VALUE"""),"Father") -> Father | Y18: =IFERROR(__xludf.DUMMYFUNCTION("""COMPUTED_VALUE"""),"Sona mina") -> Sona mina | Z18: =IFERROR(__xludf.DUMMYFUNCTION("""COMPUTED_VALUE"""),"Mother ") -> Mother | AA18: =IFERROR(__xludf.DUMMYFUNCTION("""COMPUTED_VALUE"""),"Veg") -> Veg | AB18: =IFERROR(__xludf.DUMMYFUNCTION("""COMPUTED_VALUE"""),"Veg") -> Veg | AC18: =IFERROR(__xludf.DUMMYFUNCTION("""COMPUTED_VALUE"""),"Veg") -> Veg | AD18: =IFERROR(__xludf.DUMMYFUNCTION("""COMPUTED_VALUE"""),"Bus Drop Service not needed") -> Bus Drop Service not needed | AE18: =IFERROR(__xludf.DUMMYFUNCTION("""COMPUTED_VALUE"""),0.0) -> 0
A19: =IFERROR(__xludf.DUMMYFUNCTION("""COMPUTED_VALUE"""),46265.96833175926) -> 46265.968 | B19: =IFERROR(__xludf.DUMMYFUNCTION("""COMPUTED_VALUE"""),"dannana.mbbs-2020@aiimskalyani.edu.in") -> dannana.mbbs-2020@aiimskalyani.edu.in | C19: =IFERROR(__xludf.DUMMYFUNCTION("""COMPUTED_VALUE"""),"DANNANA GAYATHRI ") -> DANNANA GAYATHRI | D19: =IFERROR(__xludf.DUMMYFUNCTION("""COMPUTED_VALUE"""),2.020019E7) -> 20200190 | E19: =IFERROR(__xludf.DUMMYFUNCTION("""COMPUTED_VALUE"""),"MBBS 2020") -> MBBS 2020 | F19: =IFERROR(__xludf.DUMMYFUNCTION("""COMPUTED_VALUE"""),9.381481345E9) -> 9381481345 | G19: =IFERROR(__xludf.DUMMYFUNCTION("""COMPUTED_VALUE"""),"dannana.mbbs-2020@aiimskalyani.edu.in") -> dannana.mbbs-2020@aiimskalyani.edu.in | H19: =IFERROR(__xludf.DUMMYFUNCTION("""COMPUTED_VALUE"""),"Yes") -> Yes | I19: =IFERROR(__xludf.DUMMYFUNCTION("""COMPUTED_VALUE"""),"Playing badminton, reading novels") -> Playing badminton, reading novels | K19: =IFERROR(__xludf.DUMMYFUNCTION("""COMPUTED_VALUE"""),"Srikakulam ") -> Srikakulam | L19: =IFERROR(__xludf.DUMMYFUNCTION("""COMPUTED_VALUE"""),"https://drive.google.com/open?id=1QgNvJRjBx2uD2u8FCp2CWvw3gahNBdsB") -> https://drive.google.com/open?id=1QgNvJRjBx2uD2u8FCp2CWvw3gahNBdsB | M19: =IFERROR(__xludf.DUMMYFUNCTION("""COMPUTED_VALUE"""),"https://drive.google.com/open?id=1w81KoCwLdyLKxJ-F8wznvKmVk_OBhZuK") -> https://drive.google.com/open?id=1w81KoCwLdyLKxJ-F8wznvKmVk_OBhZuK | N19: =IFERROR(__xludf.DUMMYFUNCTION("""COMPUTED_VALUE"""),"D Gurunadham Naidu") -> D Gurunadham Naidu | O19: =IFERROR(__xludf.DUMMYFUNCTION("""COMPUTED_VALUE"""),"Govt employe (police dept)") -> Govt employe (police dept) | P19: =IFERROR(__xludf.DUMMYFUNCTION("""COMPUTED_VALUE"""),"Srikakulam ") -> Srikakulam | Q19: =IFERROR(__xludf.DUMMYFUNCTION("""COMPUTED_VALUE"""),9.701578607E9) -> 9701578607 | R19: =IFERROR(__xludf.DUMMYFUNCTION("""COMPUTED_VALUE"""),"D Bhanumathi") -> D Bhanumathi | S19: =IFERROR(__xludf.DUMMYFUNCTION("""COMPUTED_VALUE"""),"Home maker") -> Home maker | T19: =IFERROR(__xludf.DUMMYFUNCTION("""COMPUTED_VALUE"""),"Srikakulam ") -> Srikakulam | U19: =IFERROR(__xludf.DUMMYFUNCTION("""COMPUTED_VALUE"""),8.520932901E9) -> 8520932901 | V19: =IFERROR(__xludf.DUMMYFUNCTION("""COMPUTED_VALUE"""),2.0) -> 2 | W19: =IFERROR(__xludf.DUMMYFUNCTION("""COMPUTED_VALUE"""),"D Gurunadham naidu") -> D Gurunadham naidu | X19: =IFERROR(__xludf.DUMMYFUNCTION("""COMPUTED_VALUE"""),"Father") -> Father | Y19: =IFERROR(__xludf.DUMMYFUNCTION("""COMPUTED_VALUE"""),"D Tarun kumar") -> D Tarun kumar | Z19: =IFERROR(__xludf.DUMMYFUNCTION("""COMPUTED_VALUE"""),"Brother") -> Brother | AA19: =IFERROR(__xludf.DUMMYFUNCTION("""COMPUTED_VALUE"""),"Non-Veg") -> Non-Veg | AB19: =IFERROR(__xludf.DUMMYFUNCTION("""COMPUTED_VALUE"""),"Non-Veg") -> Non-Veg | AC19: =IFERROR(__xludf.DUMMYFUNCTION("""COMPUTED_VALUE"""),"Non-Veg") -> Non-Veg | AD19: =IFERROR(__xludf.DUMMYFUNCTION("""COMPUTED_VALUE"""),"Bus Drop Service not needed") -> Bus Drop Service not needed
A20: =IFERROR(__xludf.DUMMYFUNCTION("""COMPUTED_VALUE"""),46265.96573012731) -> 46265.966 | B20: =IFERROR(__xludf.DUMMYFUNCTION("""COMPUTED_VALUE"""),"adithyakiran.mbbs-2019@aiimskalyani.edu.in") -> adithyakiran.mbbs-2019@aiimskalyani.edu.in | C20: =IFERROR(__xludf.DUMMYFUNCTION("""COMPUTED_VALUE"""),"J B ADITHYAKIRAN ") -> J B ADITHYAKIRAN | D20: =IFERROR(__xludf.DUMMYFUNCTION("""COMPUTED_VALUE"""),2.0190115E7) -> 20190115 | E20: =IFERROR(__xludf.DUMMYFUNCTION("""COMPUTED_VALUE"""),"MBBS 2019") -> MBBS 2019 | F20: =IFERROR(__xludf.DUMMYFUNCTION("""COMPUTED_VALUE"""),9.645919222E9) -> 9645919222 | G20: =IFERROR(__xludf.DUMMYFUNCTION("""COMPUTED_VALUE"""),"adithyakiranjb@gmail.com") -> adithyakiranjb@gmail.com | H20: =IFERROR(__xludf.DUMMYFUNCTION("""COMPUTED_VALUE"""),"Yes") -> Yes | I20: =IFERROR(__xludf.DUMMYFUNCTION("""COMPUTED_VALUE"""),"Gym, Sports and gaming.") -> Gym, Sports and gaming. | J20: =IFERROR(__xludf.DUMMYFUNCTION("""COMPUTED_VALUE"""),"Winner of 1st Intra college football tournament. 2 time winner in Interhouse football tournament. Runner up of Inter College football tournament.") -> Winner of 1st Intra college football tournament. 2 time winner in Interhouse football tournament. Runner up of Inter College football tournament. | K20: =IFERROR(__xludf.DUMMYFUNCTION("""COMPUTED_VALUE"""),"Kozhikode ") -> Kozhikode | L20: =IFERROR(__xludf.DUMMYFUNCTION("""COMPUTED_VALUE"""),"https://drive.google.com/open?id=1_uJ0G5RvCcmNXJ8HEPmjeBL_VlgBjVrz") -> https://drive.google.com/open?id=1_uJ0G5RvCcmNXJ8HEPmjeBL_VlgBjVrz | M20: =IFERROR(__xludf.DUMMYFUNCTION("""COMPUTED_VALUE"""),"https://drive.google.com/open?id=1ZHmiZBpRgWbVEJgmEBxuWTKTJs9lHg7I") -> https://drive.google.com/open?id=1ZHmiZBpRgWbVEJgmEBxuWTKTJs9lHg7I | N20: =IFERROR(__xludf.DUMMYFUNCTION("""COMPUTED_VALUE"""),"Jayakumar K N") -> Jayakumar K N | O20: =IFERROR(__xludf.DUMMYFUNCTION("""COMPUTED_VALUE"""),"Advocate ") -> Advocate | P20: =IFERROR(__xludf.DUMMYFUNCTION("""COMPUTED_VALUE"""),"Kozhikode ") -> Kozhikode | Q20: =IFERROR(__xludf.DUMMYFUNCTION("""COMPUTED_VALUE"""),9.447338822E9) -> 9447338822 | R20: =IFERROR(__xludf.DUMMYFUNCTION("""COMPUTED_VALUE"""),"Beena C K ") -> Beena C K | S20: =IFERROR(__xludf.DUMMYFUNCTION("""COMPUTED_VALUE"""),"Joint Registrar, University of Calicut") -> Joint Registrar, University of Calicut | T20: =IFERROR(__xludf.DUMMYFUNCTION("""COMPUTED_VALUE"""),"Kozhikode ") -> Kozhikode | U20: =IFERROR(__xludf.DUMMYFUNCTION("""COMPUTED_VALUE"""),8.547311424E9) -> 8547311424 | V20: =IFERROR(__xludf.DUMMYFUNCTION("""COMPUTED_VALUE"""),2.0) -> 2 | W20: =IFERROR(__xludf.DUMMYFUNCTION("""COMPUTED_VALUE"""),"Jayakumar K N ") -> Jayakumar K N | X20: =IFERROR(__xludf.DUMMYFUNCTION("""COMPUTED_VALUE"""),"Father ") -> Father | Y20: =IFERROR(__xludf.DUMMYFUNCTION("""COMPUTED_VALUE"""),"Beena C K ") -> Beena C K | Z20: =IFERROR(__xludf.DUMMYFUNCTION("""COMPUTED_VALUE"""),"Mother") -> Mother | AA20: =IFERROR(__xludf.DUMMYFUNCTION("""COMPUTED_VALUE"""),"Non-Veg") -> Non-Veg | AB20: =IFERROR(__xludf.DUMMYFUNCTION("""COMPUTED_VALUE"""),"Non-Veg") -> Non-Veg | AC20: =IFERROR(__xludf.DUMMYFUNCTION("""COMPUTED_VALUE"""),"Non-Veg") -> Non-Veg | AD20: =IFERROR(__xludf.DUMMYFUNCTION("""COMPUTED_VALUE"""),"Bus Drop Service not needed") -> Bus Drop Service not needed | AE20: =IFERROR(__xludf.DUMMYFUNCTION("""COMPUTED_VALUE"""),0.0) -> 0
A21: =IFERROR(__xludf.DUMMYFUNCTION("""COMPUTED_VALUE"""),46265.95055366898) -> 46265.951 | B21: =IFERROR(__xludf.DUMMYFUNCTION("""COMPUTED_VALUE"""),"sadia.mbbs-2020@aiimskalyani.edu.in") -> sadia.mbbs-2020@aiimskalyani.edu.in | C21: =IFERROR(__xludf.DUMMYFUNCTION("""COMPUTED_VALUE"""),"SADIA ASAD") -> SADIA ASAD | D21: =IFERROR(__xludf.DUMMYFUNCTION("""COMPUTED_VALUE"""),81.0) -> 81 | E21: =IFERROR(__xludf.DUMMYFUNCTION("""COMPUTED_VALUE"""),"MBBS 2020") -> MBBS 2020 | F21: =IFERROR(__xludf.DUMMYFUNCTION("""COMPUTED_VALUE"""),9.334519662E9) -> 9334519662 | G21: =IFERROR(__xludf.DUMMYFUNCTION("""COMPUTED_VALUE"""),"asad.sadia145@gmail.com") -> asad.sadia145@gmail.com | H21: =IFERROR(__xludf.DUMMYFUNCTION("""COMPUTED_VALUE"""),"Yes") -> Yes | I21: =IFERROR(__xludf.DUMMYFUNCTION("""COMPUTED_VALUE"""),"Reading") -> Reading | K21: =IFERROR(__xludf.DUMMYFUNCTION("""COMPUTED_VALUE"""),"Patna") -> Patna | L21: =IFERROR(__xludf.DUMMYFUNCTION("""COMPUTED_VALUE"""),"https://drive.google.com/open?id=1OboaLdslWSE_VFpgS6LQ6bbGtwL4HwVZ") -> https://drive.google.com/open?id=1OboaLdslWSE_VFpgS6LQ6bbGtwL4HwVZ | M21: =IFERROR(__xludf.DUMMYFUNCTION("""COMPUTED_VALUE"""),"https://drive.google.com/open?id=1M4hyYkBu6Cwfqdle_Jz4K-P6tWLEcVKj") -> https://drive.google.com/open?id=1M4hyYkBu6Cwfqdle_Jz4K-P6tWLEcVKj | N21: =IFERROR(__xludf.DUMMYFUNCTION("""COMPUTED_VALUE"""),"Asad Ahmad") -> Asad Ahmad | O21: =IFERROR(__xludf.DUMMYFUNCTION("""COMPUTED_VALUE"""),"Business man") -> Business man | P21: =IFERROR(__xludf.DUMMYFUNCTION("""COMPUTED_VALUE"""),"Patna") -> Patna | Q21: =IFERROR(__xludf.DUMMYFUNCTION("""COMPUTED_VALUE"""),7.992436561E9) -> 7992436561 | R21: =IFERROR(__xludf.DUMMYFUNCTION("""COMPUTED_VALUE"""),"NIKHAT SULTANA") -> NIKHAT SULTANA | S21: =IFERROR(__xludf.DUMMYFUNCTION("""COMPUTED_VALUE"""),"Homemaker") -> Homemaker | T21: =IFERROR(__xludf.DUMMYFUNCTION("""COMPUTED_VALUE"""),"Patna") -> Patna | U21: =IFERROR(__xludf.DUMMYFUNCTION("""COMPUTED_VALUE"""),7.563980622E9) -> 7563980622 | V21: =IFERROR(__xludf.DUMMYFUNCTION("""COMPUTED_VALUE"""),2.0) -> 2 | W21: =IFERROR(__xludf.DUMMYFUNCTION("""COMPUTED_VALUE"""),"Asad Ahmad") -> Asad Ahmad | X21: =IFERROR(__xludf.DUMMYFUNCTION("""COMPUTED_VALUE"""),"Father") -> Father | Y21: =IFERROR(__xludf.DUMMYFUNCTION("""COMPUTED_VALUE"""),"Nikhat Sultana") -> Nikhat Sultana | Z21: =IFERROR(__xludf.DUMMYFUNCTION("""COMPUTED_VALUE"""),"Mother") -> Mother | AA21: =IFERROR(__xludf.DUMMYFUNCTION("""COMPUTED_VALUE"""),"Non-Veg") -> Non-Veg | AB21: =IFERROR(__xludf.DUMMYFUNCTION("""COMPUTED_VALUE"""),"Non-Veg") -> Non-Veg | AC21: =IFERROR(__xludf.DUMMYFUNCTION("""COMPUTED_VALUE"""),"Non-Veg") -> Non-Veg
A22: =IFERROR(__xludf.DUMMYFUNCTION("""COMPUTED_VALUE"""),46265.93915467593) -> 46265.939 | B22: =IFERROR(__xludf.DUMMYFUNCTION("""COMPUTED_VALUE"""),"raghav.mbbs-2020@aiimskalyani.edu.in") -> raghav.mbbs-2020@aiimskalyani.edu.in | C22: =IFERROR(__xludf.DUMMYFUNCTION("""COMPUTED_VALUE"""),"Jajoo Raghav Bhushan") -> Jajoo Raghav Bhushan | D22: =IFERROR(__xludf.DUMMYFUNCTION("""COMPUTED_VALUE"""),2.02001104E8) -> 202001104 | E22: =IFERROR(__xludf.DUMMYFUNCTION("""COMPUTED_VALUE"""),"MBBS 2020") -> MBBS 2020 | F22: =IFERROR(__xludf.DUMMYFUNCTION("""COMPUTED_VALUE"""),9.028844721E9) -> 9028844721 | G22: =IFERROR(__xludf.DUMMYFUNCTION("""COMPUTED_VALUE"""),"dr.raghavjajoo@gmail.com") -> dr.raghavjajoo@gmail.com | H22: =IFERROR(__xludf.DUMMYFUNCTION("""COMPUTED_VALUE"""),"Yes") -> Yes | I22: =IFERROR(__xludf.DUMMYFUNCTION("""COMPUTED_VALUE"""),"Reading comics, learning about latest technological advancements") -> Reading comics, learning about latest technological advancements | K22: =IFERROR(__xludf.DUMMYFUNCTION("""COMPUTED_VALUE"""),"Akola, Maharashtra") -> Akola, Maharashtra | L22: =IFERROR(__xludf.DUMMYFUNCTION("""COMPUTED_VALUE"""),"https://drive.google.com/open?id=1w-dlCL4gT0_WB-hCqveVhpyrCUzzYjUY") -> https://drive.google.com/open?id=1w-dlCL4gT0_WB-hCqveVhpyrCUzzYjUY | M22: =IFERROR(__xludf.DUMMYFUNCTION("""COMPUTED_VALUE"""),"https://drive.google.com/open?id=1_RQbsyY23VX7jkJaUt516rn0AUuD56It") -> https://drive.google.com/open?id=1_RQbsyY23VX7jkJaUt516rn0AUuD56It | N22: =IFERROR(__xludf.DUMMYFUNCTION("""COMPUTED_VALUE"""),"Bhushan Shyamsunder Jajoo") -> Bhushan Shyamsunder Jajoo | O22: =IFERROR(__xludf.DUMMYFUNCTION("""COMPUTED_VALUE"""),"Chartered Accountant") -> Chartered Accountant | P22: =IFERROR(__xludf.DUMMYFUNCTION("""COMPUTED_VALUE"""),"Akola, Maharashtra") -> Akola, Maharashtra | Q22: =IFERROR(__xludf.DUMMYFUNCTION("""COMPUTED_VALUE"""),9.422164721E9) -> 9422164721 | R22: =IFERROR(__xludf.DUMMYFUNCTION("""COMPUTED_VALUE"""),"Rakhee Bhushan Jajoo") -> Rakhee Bhushan Jajoo | S22: =IFERROR(__xludf.DUMMYFUNCTION("""COMPUTED_VALUE"""),"Homemaker") -> Homemaker | T22: =IFERROR(__xludf.DUMMYFUNCTION("""COMPUTED_VALUE"""),"Akola, Maharashtra") -> Akola, Maharashtra | U22: =IFERROR(__xludf.DUMMYFUNCTION("""COMPUTED_VALUE"""),9.42258866E9) -> 9422588660 | V22: =IFERROR(__xludf.DUMMYFUNCTION("""COMPUTED_VALUE"""),2.0) -> 2 | W22: =IFERROR(__xludf.DUMMYFUNCTION("""COMPUTED_VALUE"""),"Bhushan Shyamsunder Jajoo") -> Bhushan Shyamsunder Jajoo | X22: =IFERROR(__xludf.DUMMYFUNCTION("""COMPUTED_VALUE"""),"Father") -> Father | Y22: =IFERROR(__xludf.DUMMYFUNCTION("""COMPUTED_VALUE"""),"Rakhee Bhushan Jajoo") -> Rakhee Bhushan Jajoo | Z22: =IFERROR(__xludf.DUMMYFUNCTION("""COMPUTED_VALUE"""),"Mother") -> Mother | AA22: =IFERROR(__xludf.DUMMYFUNCTION("""COMPUTED_VALUE"""),"Veg") -> Veg | AB22: =IFERROR(__xludf.DUMMYFUNCTION("""COMPUTED_VALUE"""),"Veg") -> Veg | AC22: =IFERROR(__xludf.DUMMYFUNCTION("""COMPUTED_VALUE"""),"Veg") -> Veg | AD22: =IFERROR(__xludf.DUMMYFUNCTION("""COMPUTED_VALUE"""),"Bus Drop Service not needed") -> Bus Drop Service not needed | AE22: =IFERROR(__xludf.DUMMYFUNCTION("""COMPUTED_VALUE"""),0.0) -> 0
A23: =IFERROR(__xludf.DUMMYFUNCTION("""COMPUTED_VALUE"""),46265.92654341435) -> 46265.927 | B23: =IFERROR(__xludf.DUMMYFUNCTION("""COMPUTED_VALUE"""),"dilshana.mbbs-2020@aiimskalyani.edu.in") -> dilshana.mbbs-2020@aiimskalyani.edu.in | C23: =IFERROR(__xludf.DUMMYFUNCTION("""COMPUTED_VALUE"""),"DILSHANA") -> DILSHANA | D23: =IFERROR(__xludf.DUMMYFUNCTION("""COMPUTED_VALUE"""),2.0200196E7) -> 20200196 | E23: =IFERROR(__xludf.DUMMYFUNCTION("""COMPUTED_VALUE"""),"MBBS 2020") -> MBBS 2020 | F23: =IFERROR(__xludf.DUMMYFUNCTION("""COMPUTED_VALUE"""),9.048548253E9) -> 9048548253 | G23: =IFERROR(__xludf.DUMMYFUNCTION("""COMPUTED_VALUE"""),"dilshana.mbbs-2020@aiimskalyani.edu.in") -> dilshana.mbbs-2020@aiimskalyani.edu.in | H23: =IFERROR(__xludf.DUMMYFUNCTION("""COMPUTED_VALUE"""),"Yes") -> Yes | I23: =IFERROR(__xludf.DUMMYFUNCTION("""COMPUTED_VALUE"""),"Reading books, watching movies and series, and travelling.") -> Reading books, watching movies and series, and travelling. | J23: =IFERROR(__xludf.DUMMYFUNCTION("""COMPUTED_VALUE"""),"Quiz competitions") -> Quiz competitions | K23: =IFERROR(__xludf.DUMMYFUNCTION("""COMPUTED_VALUE"""),"Manjeri ") -> Manjeri | L23: =IFERROR(__xludf.DUMMYFUNCTION("""COMPUTED_VALUE"""),"https://drive.google.com/open?id=1mwvfinyTu_GlNS7PFEptZd9hpZlvKQt7") -> https://drive.google.com/open?id=1mwvfinyTu_GlNS7PFEptZd9hpZlvKQt7 | M23: =IFERROR(__xludf.DUMMYFUNCTION("""COMPUTED_VALUE"""),"https://drive.google.com/open?id=1uR5vsOrSI85HE4CPSUghFcqzikifUj7l") -> https://drive.google.com/open?id=1uR5vsOrSI85HE4CPSUghFcqzikifUj7l | N23: =IFERROR(__xludf.DUMMYFUNCTION("""COMPUTED_VALUE"""),"Nazeer") -> Nazeer | O23: =IFERROR(__xludf.DUMMYFUNCTION("""COMPUTED_VALUE"""),"Business ") -> Business | P23: =IFERROR(__xludf.DUMMYFUNCTION("""COMPUTED_VALUE"""),"Manjeri ") -> Manjeri | Q23: =IFERROR(__xludf.DUMMYFUNCTION("""COMPUTED_VALUE"""),9.495174049E9) -> 9495174049 | R23: =IFERROR(__xludf.DUMMYFUNCTION("""COMPUTED_VALUE"""),"Ameen Rasiyana ") -> Ameen Rasiyana | S23: =IFERROR(__xludf.DUMMYFUNCTION("""COMPUTED_VALUE"""),"Homemaker") -> Homemaker | T23: =IFERROR(__xludf.DUMMYFUNCTION("""COMPUTED_VALUE"""),"Manjeri") -> Manjeri | U23: =IFERROR(__xludf.DUMMYFUNCTION("""COMPUTED_VALUE"""),9.048497082E9) -> 9048497082 | V23: =IFERROR(__xludf.DUMMYFUNCTION("""COMPUTED_VALUE"""),2.0) -> 2 | W23: =IFERROR(__xludf.DUMMYFUNCTION("""COMPUTED_VALUE"""),"Nazeer") -> Nazeer | X23: =IFERROR(__xludf.DUMMYFUNCTION("""COMPUTED_VALUE"""),"Father") -> Father | Y23: =IFERROR(__xludf.DUMMYFUNCTION("""COMPUTED_VALUE"""),"Ameen Rasiyana") -> Ameen Rasiyana | Z23: =IFERROR(__xludf.DUMMYFUNCTION("""COMPUTED_VALUE"""),"Mother") -> Mother | AA23: =IFERROR(__xludf.DUMMYFUNCTION("""COMPUTED_VALUE"""),"Non-Veg") -> Non-Veg | AB23: =IFERROR(__xludf.DUMMYFUNCTION("""COMPUTED_VALUE"""),"Non-Veg") -> Non-Veg | AC23: =IFERROR(__xludf.DUMMYFUNCTION("""COMPUTED_VALUE"""),"Non-Veg") -> Non-Veg
A24: =IFERROR(__xludf.DUMMYFUNCTION("""COMPUTED_VALUE"""),46265.92494744213) -> 46265.925 | B24: =IFERROR(__xludf.DUMMYFUNCTION("""COMPUTED_VALUE"""),"debbani.mbbs-2020@aiimskalyani.edu.in") -> debbani.mbbs-2020@aiimskalyani.edu.in | C24: =IFERROR(__xludf.DUMMYFUNCTION("""COMPUTED_VALUE"""),"DEBBANI BOSE ") -> DEBBANI BOSE | D24: =IFERROR(__xludf.DUMMYFUNCTION("""COMPUTED_VALUE"""),2.0200191E7) -> 20200191 | E24: =IFERROR(__xludf.DUMMYFUNCTION("""COMPUTED_VALUE"""),"MBBS 2020") -> MBBS 2020 | F24: =IFERROR(__xludf.DUMMYFUNCTION("""COMPUTED_VALUE"""),9.945925702E9) -> 9945925702 | G24: =IFERROR(__xludf.DUMMYFUNCTION("""COMPUTED_VALUE"""),"debbanibose@gmail.com") -> debbanibose@gmail.com | H24: =IFERROR(__xludf.DUMMYFUNCTION("""COMPUTED_VALUE"""),"Yes") -> Yes | I24: =IFERROR(__xludf.DUMMYFUNCTION("""COMPUTED_VALUE"""),"Poetry and writing.") -> Poetry and writing. | J24: =IFERROR(__xludf.DUMMYFUNCTION("""COMPUTED_VALUE""")," - Former Literary club Head from 2023-24. - Former Student council member. - 1st place in AIIMS RBL Parichay '21. - 1st place in AIIMS Bathinda Aroha '21. - Published in Jublieum- book of complication of poems, for my piece on teenagers dealing with body"&" image issues and mental health illnesses.") -> - Former Literary club Head from 2023-24. - Former Student council member. - 1st place in AIIMS RBL Parichay '21. - 1st place in AIIMS Bathinda Aroha '21. - Published in Jublieum- book of complication of poems, for my piece on teenagers dealing with body image issues and mental health illnesses. | K24: =IFERROR(__xludf.DUMMYFUNCTION("""COMPUTED_VALUE"""),"Bangalore, Karnataka.") -> Bangalore, Karnataka. | L24: =IFERROR(__xludf.DUMMYFUNCTION("""COMPUTED_VALUE"""),"https://drive.google.com/open?id=1bxSA1M8vDxdA9SRzFjtp8DsGBzonvqE0") -> https://drive.google.com/open?id=1bxSA1M8vDxdA9SRzFjtp8DsGBzonvqE0 | M24: =IFERROR(__xludf.DUMMYFUNCTION("""COMPUTED_VALUE"""),"https://drive.google.com/open?id=1NDNGIUV1WswD5-HvnX6C0v1n_4ZYWLYP") -> https://drive.google.com/open?id=1NDNGIUV1WswD5-HvnX6C0v1n_4ZYWLYP | N24: =IFERROR(__xludf.DUMMYFUNCTION("""COMPUTED_VALUE"""),"DIPTIMAN BOSE") -> DIPTIMAN BOSE | O24: =IFERROR(__xludf.DUMMYFUNCTION("""COMPUTED_VALUE"""),"Software Engineer ") -> Software Engineer | P24: =IFERROR(__xludf.DUMMYFUNCTION("""COMPUTED_VALUE"""),"Bangalore ") -> Bangalore | Q24: =IFERROR(__xludf.DUMMYFUNCTION("""COMPUTED_VALUE"""),9.53571546E9) -> 9535715460 | R24: =IFERROR(__xludf.DUMMYFUNCTION("""COMPUTED_VALUE"""),"MAITRAYEE BOSE") -> MAITRAYEE BOSE | S24: =IFERROR(__xludf.DUMMYFUNCTION("""COMPUTED_VALUE"""),"Civil advocate ") -> Civil advocate | T24: =IFERROR(__xludf.DUMMYFUNCTION("""COMPUTED_VALUE"""),"Bangalore ") -> Bangalore | U24: =IFERROR(__xludf.DUMMYFUNCTION("""COMPUTED_VALUE"""),9.108893316E9) -> 9108893316 | V24: =IFERROR(__xludf.DUMMYFUNCTION("""COMPUTED_VALUE"""),2.0) -> 2 | W24: =IFERROR(__xludf.DUMMYFUNCTION("""COMPUTED_VALUE"""),"ANINDITA BOSE") -> ANINDITA BOSE | X24: =IFERROR(__xludf.DUMMYFUNCTION("""COMPUTED_VALUE"""),"Grandmother") -> Grandmother | Y24: =IFERROR(__xludf.DUMMYFUNCTION("""COMPUTED_VALUE"""),"CHAITALI NAG") -> CHAITALI NAG | Z24: =IFERROR(__xludf.DUMMYFUNCTION("""COMPUTED_VALUE"""),"Grandmother ") -> Grandmother | AA24: =IFERROR(__xludf.DUMMYFUNCTION("""COMPUTED_VALUE"""),"Non-Veg") -> Non-Veg | AB24: =IFERROR(__xludf.DUMMYFUNCTION("""COMPUTED_VALUE"""),"Veg") -> Veg | AC24: =IFERROR(__xludf.DUMMYFUNCTION("""COMPUTED_VALUE"""),"Non-Veg") -> Non-Veg | AD24: =IFERROR(__xludf.DUMMYFUNCTION("""COMPUTED_VALUE"""),"Drop at Kolkata Airport") -> Drop at Kolkata Airport | AE24: =IFERROR(__xludf.DUMMYFUNCTION("""COMPUTED_VALUE"""),3.0) -> 3
A25: =IFERROR(__xludf.DUMMYFUNCTION("""COMPUTED_VALUE"""),46265.92348233797) -> 46265.923 | B25: =IFERROR(__xludf.DUMMYFUNCTION("""COMPUTED_VALUE"""),"rojimandal000@gmail.com") -> rojimandal000@gmail.com | C25: =IFERROR(__xludf.DUMMYFUNCTION("""COMPUTED_VALUE"""),"ROJI MANDAL ") -> ROJI MANDAL | D25: =IFERROR(__xludf.DUMMYFUNCTION("""COMPUTED_VALUE"""),2.024041E7) -> 20240410 | E25: =IFERROR(__xludf.DUMMYFUNCTION("""COMPUTED_VALUE"""),"M.Sc. Nursing 2024") -> M.Sc. Nursing 2024 | F25: =IFERROR(__xludf.DUMMYFUNCTION("""COMPUTED_VALUE"""),6.291421596E9) -> 6291421596 | G25: =IFERROR(__xludf.DUMMYFUNCTION("""COMPUTED_VALUE"""),"rojimandal000@gmail.com") -> rojimandal000@gmail.com | H25: =IFERROR(__xludf.DUMMYFUNCTION("""COMPUTED_VALUE"""),"Yes") -> Yes | I25: =IFERROR(__xludf.DUMMYFUNCTION("""COMPUTED_VALUE"""),"My hobbies include listening to music, watching movies, travelling, and spending time with my family and friends. I’m also interested in learning new things. I enjoy reading and exploring topics that help me grow personally and professionally.") -> My hobbies include listening to music, watching movies, travelling, and spending time with my family and friends. I’m also interested in learning new things. I enjoy reading and exploring topics that help me grow personally and professionally. | J25: =IFERROR(__xludf.DUMMYFUNCTION("""COMPUTED_VALUE"""),"I am a brown belt in karate.") -> I am a brown belt in karate. | K25: =IFERROR(__xludf.DUMMYFUNCTION("""COMPUTED_VALUE"""),"Ranaghat, west bengal ") -> Ranaghat, west bengal | L25: =IFERROR(__xludf.DUMMYFUNCTION("""COMPUTED_VALUE"""),"https://drive.google.com/open?id=19Ufj63siWdyY2o1IyYqcc7TOHpr4iSYv") -> https://drive.google.com/open?id=19Ufj63siWdyY2o1IyYqcc7TOHpr4iSYv | M25: =IFERROR(__xludf.DUMMYFUNCTION("""COMPUTED_VALUE"""),"https://drive.google.com/open?id=1F5T_c4pLztvxFFHJnUrj7TdNSkk4EBJR") -> https://drive.google.com/open?id=1F5T_c4pLztvxFFHJnUrj7TdNSkk4EBJR | N25: =IFERROR(__xludf.DUMMYFUNCTION("""COMPUTED_VALUE"""),"Ranjit Kumar Mandal ") -> Ranjit Kumar Mandal | O25: =IFERROR(__xludf.DUMMYFUNCTION("""COMPUTED_VALUE"""),"Pharmacist ") -> Pharmacist | P25: =IFERROR(__xludf.DUMMYFUNCTION("""COMPUTED_VALUE"""),"Ranaghat, west bengal ") -> Ranaghat, west bengal | Q25: =IFERROR(__xludf.DUMMYFUNCTION("""COMPUTED_VALUE"""),7.654286296E9) -> 7654286296 | R25: =IFERROR(__xludf.DUMMYFUNCTION("""COMPUTED_VALUE"""),"Sheli Mandal ") -> Sheli Mandal | S25: =IFERROR(__xludf.DUMMYFUNCTION("""COMPUTED_VALUE"""),"House wife ") -> House wife | T25: =IFERROR(__xludf.DUMMYFUNCTION("""COMPUTED_VALUE"""),"Ranaghat, west bengal ") -> Ranaghat, west bengal | U25: =IFERROR(__xludf.DUMMYFUNCTION("""COMPUTED_VALUE"""),6.289643354E9) -> 6289643354 | V25: =IFERROR(__xludf.DUMMYFUNCTION("""COMPUTED_VALUE"""),2.0) -> 2 | W25: =IFERROR(__xludf.DUMMYFUNCTION("""COMPUTED_VALUE"""),"Ranjit Kumar Mandal ") -> Ranjit Kumar Mandal | X25: =IFERROR(__xludf.DUMMYFUNCTION("""COMPUTED_VALUE"""),"Father ") -> Father | Y25: =IFERROR(__xludf.DUMMYFUNCTION("""COMPUTED_VALUE"""),"Sheli Mandal ") -> Sheli Mandal | Z25: =IFERROR(__xludf.DUMMYFUNCTION("""COMPUTED_VALUE"""),"Mother ") -> Mother | AA25: =IFERROR(__xludf.DUMMYFUNCTION("""COMPUTED_VALUE"""),"Veg") -> Veg | AB25: =IFERROR(__xludf.DUMMYFUNCTION("""COMPUTED_VALUE"""),"Non-Veg") -> Non-Veg | AC25: =IFERROR(__xludf.DUMMYFUNCTION("""COMPUTED_VALUE"""),"Veg") -> Veg | AD25: =IFERROR(__xludf.DUMMYFUNCTION("""COMPUTED_VALUE"""),"Drop at Kalyani Railway Station") -> Drop at Kalyani Railway Station | AE25: =IFERROR(__xludf.DUMMYFUNCTION("""COMPUTED_VALUE"""),3.0) -> 3
A26: =IFERROR(__xludf.DUMMYFUNCTION("""COMPUTED_VALUE"""),46265.912566122686) -> 46265.913 | B26: =IFERROR(__xludf.DUMMYFUNCTION("""COMPUTED_VALUE"""),"aditya.mbbs-2020@aiimskalyani.edu.in") -> aditya.mbbs-2020@aiimskalyani.edu.in | C26: =IFERROR(__xludf.DUMMYFUNCTION("""COMPUTED_VALUE"""),"ADITYA KUMAR") -> ADITYA KUMAR | D26: =IFERROR(__xludf.DUMMYFUNCTION("""COMPUTED_VALUE"""),2.0200155E7) -> 20200155 | E26: =IFERROR(__xludf.DUMMYFUNCTION("""COMPUTED_VALUE"""),"MBBS 2020") -> MBBS 2020 | F26: =IFERROR(__xludf.DUMMYFUNCTION("""COMPUTED_VALUE"""),8.102771334E9) -> 8102771334 | G26: =IFERROR(__xludf.DUMMYFUNCTION("""COMPUTED_VALUE"""),"draditya1199@gmail.com") -> draditya1199@gmail.com | H26: =IFERROR(__xludf.DUMMYFUNCTION("""COMPUTED_VALUE"""),"Yes") -> Yes | K26: =IFERROR(__xludf.DUMMYFUNCTION("""COMPUTED_VALUE"""),"Pagra, Dalsinghsarai") -> Pagra, Dalsinghsarai | L26: =IFERROR(__xludf.DUMMYFUNCTION("""COMPUTED_VALUE"""),"https://drive.google.com/open?id=1Y1foghnEA07kwud4sQLKKV6zRzOM15n9") -> https://drive.google.com/open?id=1Y1foghnEA07kwud4sQLKKV6zRzOM15n9 | M26: =IFERROR(__xludf.DUMMYFUNCTION("""COMPUTED_VALUE"""),"https://drive.google.com/open?id=1asIqFYiXtPw0r4rZI-vGyuIlVhENGzDl") -> https://drive.google.com/open?id=1asIqFYiXtPw0r4rZI-vGyuIlVhENGzDl | N26: =IFERROR(__xludf.DUMMYFUNCTION("""COMPUTED_VALUE"""),"Krishna kumar singh") -> Krishna kumar singh | O26: =IFERROR(__xludf.DUMMYFUNCTION("""COMPUTED_VALUE"""),"Job") -> Job | P26: =IFERROR(__xludf.DUMMYFUNCTION("""COMPUTED_VALUE"""),"Pagra, Dalsinghsarai") -> Pagra, Dalsinghsarai | Q26: =IFERROR(__xludf.DUMMYFUNCTION("""COMPUTED_VALUE"""),7.004307149E9) -> 7004307149 | R26: =IFERROR(__xludf.DUMMYFUNCTION("""COMPUTED_VALUE"""),"Mala kumari") -> Mala kumari | S26: =IFERROR(__xludf.DUMMYFUNCTION("""COMPUTED_VALUE"""),"Homemaker") -> Homemaker | T26: =IFERROR(__xludf.DUMMYFUNCTION("""COMPUTED_VALUE"""),"Pagra, Dalsinghsarai") -> Pagra, Dalsinghsarai | U26: =IFERROR(__xludf.DUMMYFUNCTION("""COMPUTED_VALUE"""),9.525919009E9) -> 9525919009 | V26: =IFERROR(__xludf.DUMMYFUNCTION("""COMPUTED_VALUE"""),1.0) -> 1 | W26: =IFERROR(__xludf.DUMMYFUNCTION("""COMPUTED_VALUE"""),"Mala kumari") -> Mala kumari | X26: =IFERROR(__xludf.DUMMYFUNCTION("""COMPUTED_VALUE"""),"Mother") -> Mother | AA26: =IFERROR(__xludf.DUMMYFUNCTION("""COMPUTED_VALUE"""),"Non-Veg") -> Non-Veg | AB26: =IFERROR(__xludf.DUMMYFUNCTION("""COMPUTED_VALUE"""),"Veg") -> Veg | AD26: =IFERROR(__xludf.DUMMYFUNCTION("""COMPUTED_VALUE"""),"Bus Drop Service not needed") -> Bus Drop Service not needed
A27: =IFERROR(__xludf.DUMMYFUNCTION("""COMPUTED_VALUE"""),46265.887947372685) -> 46265.888 | B27: =IFERROR(__xludf.DUMMYFUNCTION("""COMPUTED_VALUE"""),"soutrikoff@gmail.com") -> soutrikoff@gmail.com | C27: =IFERROR(__xludf.DUMMYFUNCTION("""COMPUTED_VALUE"""),"SOUTRIK SUR") -> SOUTRIK SUR | D27: =IFERROR(__xludf.DUMMYFUNCTION("""COMPUTED_VALUE"""),"99/202001149") -> 99/202001149 | E27: =IFERROR(__xludf.DUMMYFUNCTION("""COMPUTED_VALUE"""),"MBBS 2020") -> MBBS 2020 | F27: =IFERROR(__xludf.DUMMYFUNCTION("""COMPUTED_VALUE"""),9.073368142E9) -> 9073368142 | G27: =IFERROR(__xludf.DUMMYFUNCTION("""COMPUTED_VALUE"""),"soutrikoff@gmail.com") -> soutrikoff@gmail.com | H27: =IFERROR(__xludf.DUMMYFUNCTION("""COMPUTED_VALUE"""),"Yes") -> Yes | K27: =IFERROR(__xludf.DUMMYFUNCTION("""COMPUTED_VALUE"""),"Mogra Natungram, Hooghly, West Bengal") -> Mogra Natungram, Hooghly, West Bengal | L27: =IFERROR(__xludf.DUMMYFUNCTION("""COMPUTED_VALUE"""),"https://drive.google.com/open?id=1tOkABRd3IDmLi4uocyutdNGXt3rhuheO") -> https://drive.google.com/open?id=1tOkABRd3IDmLi4uocyutdNGXt3rhuheO | M27: =IFERROR(__xludf.DUMMYFUNCTION("""COMPUTED_VALUE"""),"https://drive.google.com/open?id=1bfJEJzu4gXqRKHMMJMBuDis_HF_aQ2JT") -> https://drive.google.com/open?id=1bfJEJzu4gXqRKHMMJMBuDis_HF_aQ2JT | N27: =IFERROR(__xludf.DUMMYFUNCTION("""COMPUTED_VALUE"""),"RAGHUNATH SUR") -> RAGHUNATH SUR | O27: =IFERROR(__xludf.DUMMYFUNCTION("""COMPUTED_VALUE"""),"Retired teacher, PhD in parasitology(Zoology)") -> Retired teacher, PhD in parasitology(Zoology) | P27: =IFERROR(__xludf.DUMMYFUNCTION("""COMPUTED_VALUE"""),"Amra, Hooghly") -> Amra, Hooghly | Q27: =IFERROR(__xludf.DUMMYFUNCTION("""COMPUTED_VALUE"""),9.433873092E9) -> 9433873092 | R27: =IFERROR(__xludf.DUMMYFUNCTION("""COMPUTED_VALUE"""),"Kalpana Sur") -> Kalpana Sur | S27: =IFERROR(__xludf.DUMMYFUNCTION("""COMPUTED_VALUE"""),"Housewife, B.Sc.(Botany), B.A.(Political Science)") -> Housewife, B.Sc.(Botany), B.A.(Political Science) | T27: =IFERROR(__xludf.DUMMYFUNCTION("""COMPUTED_VALUE"""),"Khei, Hooghly") -> Khei, Hooghly | U27: =IFERROR(__xludf.DUMMYFUNCTION("""COMPUTED_VALUE"""),9.163445748E9) -> 9163445748 | V27: =IFERROR(__xludf.DUMMYFUNCTION("""COMPUTED_VALUE"""),2.0) -> 2 | W27: =IFERROR(__xludf.DUMMYFUNCTION("""COMPUTED_VALUE"""),"Raghunath Sur") -> Raghunath Sur | X27: =IFERROR(__xludf.DUMMYFUNCTION("""COMPUTED_VALUE"""),"Father") -> Father | Y27: =IFERROR(__xludf.DUMMYFUNCTION("""COMPUTED_VALUE"""),"Kalpana Sur") -> Kalpana Sur | Z27: =IFERROR(__xludf.DUMMYFUNCTION("""COMPUTED_VALUE"""),"Mother") -> Mother | AA27: =IFERROR(__xludf.DUMMYFUNCTION("""COMPUTED_VALUE"""),"Non-Veg") -> Non-Veg | AB27: =IFERROR(__xludf.DUMMYFUNCTION("""COMPUTED_VALUE"""),"Non-Veg") -> Non-Veg | AC27: =IFERROR(__xludf.DUMMYFUNCTION("""COMPUTED_VALUE"""),"Non-Veg") -> Non-Veg | AD27: =IFERROR(__xludf.DUMMYFUNCTION("""COMPUTED_VALUE"""),"Bus Drop Service not needed") -> Bus Drop Service not needed | AE27: =IFERROR(__xludf.DUMMYFUNCTION("""COMPUTED_VALUE"""),0.0) -> 0
A28: =IFERROR(__xludf.DUMMYFUNCTION("""COMPUTED_VALUE"""),46265.85586752315) -> 46265.856 | B28: =IFERROR(__xludf.DUMMYFUNCTION("""COMPUTED_VALUE"""),"adithya.mbbs-2020@aiimskalyani.edu.in") -> adithya.mbbs-2020@aiimskalyani.edu.in | C28: =IFERROR(__xludf.DUMMYFUNCTION("""COMPUTED_VALUE"""),"ADITHYA BIJITH") -> ADITHYA BIJITH | D28: =IFERROR(__xludf.DUMMYFUNCTION("""COMPUTED_VALUE"""),2.0200153E7) -> 20200153 | E28: =IFERROR(__xludf.DUMMYFUNCTION("""COMPUTED_VALUE"""),"MBBS 2020") -> MBBS 2020 | F28: =IFERROR(__xludf.DUMMYFUNCTION("""COMPUTED_VALUE"""),8.590209664E9) -> 8590209664 | G28: =IFERROR(__xludf.DUMMYFUNCTION("""COMPUTED_VALUE"""),"adibij02mai@gmail.com") -> adibij02mai@gmail.com | H28: =IFERROR(__xludf.DUMMYFUNCTION("""COMPUTED_VALUE"""),"Yes") -> Yes | I28: =IFERROR(__xludf.DUMMYFUNCTION("""COMPUTED_VALUE"""),"My hobbies include dancing, creating arts and crafts, gardening, and reading novels.") -> My hobbies include dancing, creating arts and crafts, gardening, and reading novels. | K28: =IFERROR(__xludf.DUMMYFUNCTION("""COMPUTED_VALUE"""),"Arayoor ,kerala ") -> Arayoor ,kerala | L28: =IFERROR(__xludf.DUMMYFUNCTION("""COMPUTED_VALUE"""),"https://drive.google.com/open?id=1EjeLGgPojspkadV7_8lpv9coQSV4_yLt") -> https://drive.google.com/open?id=1EjeLGgPojspkadV7_8lpv9coQSV4_yLt | M28: =IFERROR(__xludf.DUMMYFUNCTION("""COMPUTED_VALUE"""),"https://drive.google.com/open?id=1azhc8rxgV0Bf_si7gWdESy-jabVIz0Kh") -> https://drive.google.com/open?id=1azhc8rxgV0Bf_si7gWdESy-jabVIz0Kh | N28: =IFERROR(__xludf.DUMMYFUNCTION("""COMPUTED_VALUE"""),"BIJITH T N") -> BIJITH T N | O28: =IFERROR(__xludf.DUMMYFUNCTION("""COMPUTED_VALUE"""),"Health inspector , primary health centre Amboori") -> Health inspector , primary health centre Amboori | P28: =IFERROR(__xludf.DUMMYFUNCTION("""COMPUTED_VALUE"""),"Arayoor, Kerala") -> Arayoor, Kerala | Q28: =IFERROR(__xludf.DUMMYFUNCTION("""COMPUTED_VALUE"""),9.8466436E9) -> 9846643600 | R28: =IFERROR(__xludf.DUMMYFUNCTION("""COMPUTED_VALUE"""),"Brajimla Rejani D G") -> Brajimla Rejani D G | S28: =IFERROR(__xludf.DUMMYFUNCTION("""COMPUTED_VALUE"""),"Teacher, LMS LPS Arayoor ") -> Teacher, LMS LPS Arayoor | T28: =IFERROR(__xludf.DUMMYFUNCTION("""COMPUTED_VALUE"""),"Arayoor, Kerala ") -> Arayoor, Kerala | U28: =IFERROR(__xludf.DUMMYFUNCTION("""COMPUTED_VALUE"""),9.846930343E9) -> 9846930343 | V28: =IFERROR(__xludf.DUMMYFUNCTION("""COMPUTED_VALUE"""),2.0) -> 2 | W28: =IFERROR(__xludf.DUMMYFUNCTION("""COMPUTED_VALUE"""),"Abhijithya Bijith") -> Abhijithya Bijith | X28: =IFERROR(__xludf.DUMMYFUNCTION("""COMPUTED_VALUE"""),"Sister ") -> Sister | Y28: =IFERROR(__xludf.DUMMYFUNCTION("""COMPUTED_VALUE"""),"Brajimla Rejani ") -> Brajimla Rejani | Z28: =IFERROR(__xludf.DUMMYFUNCTION("""COMPUTED_VALUE"""),"Mother ") -> Mother | AA28: =IFERROR(__xludf.DUMMYFUNCTION("""COMPUTED_VALUE"""),"Non-Veg") -> Non-Veg | AB28: =IFERROR(__xludf.DUMMYFUNCTION("""COMPUTED_VALUE"""),"Non-Veg") -> Non-Veg | AC28: =IFERROR(__xludf.DUMMYFUNCTION("""COMPUTED_VALUE"""),"Non-Veg") -> Non-Veg
A29: =IFERROR(__xludf.DUMMYFUNCTION("""COMPUTED_VALUE"""),46265.850309560185) -> 46265.85 | B29: =IFERROR(__xludf.DUMMYFUNCTION("""COMPUTED_VALUE"""),"mihir.mbbs-2020@aiimskalyani.edu.in") -> mihir.mbbs-2020@aiimskalyani.edu.in | C29: =IFERROR(__xludf.DUMMYFUNCTION("""COMPUTED_VALUE"""),"MIHIR SUTRADHAR") -> MIHIR SUTRADHAR | D29: =IFERROR(__xludf.DUMMYFUNCTION("""COMPUTED_VALUE"""),"Roll no. 63/ enrolment no. 202001113") -> Roll no. 63/ enrolment no. 202001113 | E29: =IFERROR(__xludf.DUMMYFUNCTION("""COMPUTED_VALUE"""),"MBBS 2020") -> MBBS 2020 | F29: =IFERROR(__xludf.DUMMYFUNCTION("""COMPUTED_VALUE"""),8.822602193E9) -> 8822602193 | G29: =IFERROR(__xludf.DUMMYFUNCTION("""COMPUTED_VALUE"""),"mihir.sutradhar154@gmail.com") -> mihir.sutradhar154@gmail.com | H29: =IFERROR(__xludf.DUMMYFUNCTION("""COMPUTED_VALUE"""),"Yes") -> Yes | I29: =IFERROR(__xludf.DUMMYFUNCTION("""COMPUTED_VALUE"""),"Music, guitar, exercise") -> Music, guitar, exercise | J29: =IFERROR(__xludf.DUMMYFUNCTION("""COMPUTED_VALUE"""),"Badminton, football, table tennis.") -> Badminton, football, table tennis. | K29: =IFERROR(__xludf.DUMMYFUNCTION("""COMPUTED_VALUE"""),"Silchar,Assam") -> Silchar,Assam | L29: =IFERROR(__xludf.DUMMYFUNCTION("""COMPUTED_VALUE"""),"https://drive.google.com/open?id=1zqLME9eCEfxh830aS4PQ0coa_B1lNzlX") -> https://drive.google.com/open?id=1zqLME9eCEfxh830aS4PQ0coa_B1lNzlX | M29: =IFERROR(__xludf.DUMMYFUNCTION("""COMPUTED_VALUE"""),"https://drive.google.com/open?id=1ot7YL9hmNHcjwMPT5zRrVYmGjOzy7u-_") -> https://drive.google.com/open?id=1ot7YL9hmNHcjwMPT5zRrVYmGjOzy7u-_ | N29: =IFERROR(__xludf.DUMMYFUNCTION("""COMPUTED_VALUE"""),"MOHAN KISHORE SUTRADHAR") -> MOHAN KISHORE SUTRADHAR | O29: =IFERROR(__xludf.DUMMYFUNCTION("""COMPUTED_VALUE"""),"Electrical Engineer ( Designation- Senior manager Affilation- NEEPCO)") -> Electrical Engineer ( Designation- Senior manager Affilation- NEEPCO) | P29: =IFERROR(__xludf.DUMMYFUNCTION("""COMPUTED_VALUE"""),"Silchar, Assam") -> Silchar, Assam | Q29: =IFERROR(__xludf.DUMMYFUNCTION("""COMPUTED_VALUE"""),9.435712779E9) -> 9435712779 | R29: =IFERROR(__xludf.DUMMYFUNCTION("""COMPUTED_VALUE"""),"SAMPA SUTRADHAR") -> SAMPA SUTRADHAR | S29: =IFERROR(__xludf.DUMMYFUNCTION("""COMPUTED_VALUE"""),"House wife") -> House wife | T29: =IFERROR(__xludf.DUMMYFUNCTION("""COMPUTED_VALUE"""),"Silchar, Assam") -> Silchar, Assam | U29: =IFERROR(__xludf.DUMMYFUNCTION("""COMPUTED_VALUE"""),9.387817114E9) -> 9387817114 | V29: =IFERROR(__xludf.DUMMYFUNCTION("""COMPUTED_VALUE"""),2.0) -> 2 | W29: =IFERROR(__xludf.DUMMYFUNCTION("""COMPUTED_VALUE"""),"MOHAN KISHORE SUTRADHAR ") -> MOHAN KISHORE SUTRADHAR | X29: =IFERROR(__xludf.DUMMYFUNCTION("""COMPUTED_VALUE"""),"Father") -> Father | Y29: =IFERROR(__xludf.DUMMYFUNCTION("""COMPUTED_VALUE"""),"SAMPA SUTRADHAR") -> SAMPA SUTRADHAR | Z29: =IFERROR(__xludf.DUMMYFUNCTION("""COMPUTED_VALUE"""),"Mother") -> Mother | AA29: =IFERROR(__xludf.DUMMYFUNCTION("""COMPUTED_VALUE"""),"Non-Veg") -> Non-Veg | AB29: =IFERROR(__xludf.DUMMYFUNCTION("""COMPUTED_VALUE"""),"Non-Veg") -> Non-Veg | AC29: =IFERROR(__xludf.DUMMYFUNCTION("""COMPUTED_VALUE"""),"Non-Veg") -> Non-Veg | AD29: =IFERROR(__xludf.DUMMYFUNCTION("""COMPUTED_VALUE"""),"Drop at Kalyani Railway Station") -> Drop at Kalyani Railway Station | AE29: =IFERROR(__xludf.DUMMYFUNCTION("""COMPUTED_VALUE"""),3.0) -> 3
A30: =IFERROR(__xludf.DUMMYFUNCTION("""COMPUTED_VALUE"""),46265.837623506945) -> 46265.838 | B30: =IFERROR(__xludf.DUMMYFUNCTION("""COMPUTED_VALUE"""),"shubhrajit.mbbs-2020@aiimskalyani.edu.in") -> shubhrajit.mbbs-2020@aiimskalyani.edu.in | C30: =IFERROR(__xludf.DUMMYFUNCTION("""COMPUTED_VALUE"""),"SHUBHRAJIT SAHOO ") -> SHUBHRAJIT SAHOO | D30: =IFERROR(__xludf.DUMMYFUNCTION("""COMPUTED_VALUE"""),2.02001145E8) -> 202001145 | E30: =IFERROR(__xludf.DUMMYFUNCTION("""COMPUTED_VALUE"""),"MBBS 2020") -> MBBS 2020 | F30: =IFERROR(__xludf.DUMMYFUNCTION("""COMPUTED_VALUE"""),7.848805484E9) -> 7848805484 | G30: =IFERROR(__xludf.DUMMYFUNCTION("""COMPUTED_VALUE"""),"shubhrajit2018@gmail.com") -> shubhrajit2018@gmail.com | H30: =IFERROR(__xludf.DUMMYFUNCTION("""COMPUTED_VALUE"""),"Yes") -> Yes | I30: =IFERROR(__xludf.DUMMYFUNCTION("""COMPUTED_VALUE"""),"Watching movies ") -> Watching movies | J30: =IFERROR(__xludf.DUMMYFUNCTION("""COMPUTED_VALUE"""),"Nothing ") -> Nothing | K30: =IFERROR(__xludf.DUMMYFUNCTION("""COMPUTED_VALUE"""),"Bhadrak ") -> Bhadrak | L30: =IFERROR(__xludf.DUMMYFUNCTION("""COMPUTED_VALUE"""),"https://drive.google.com/open?id=1b5rA_CCnxA-KTpJj49WJIbXDgG4DMwgA") -> https://drive.google.com/open?id=1b5rA_CCnxA-KTpJj49WJIbXDgG4DMwgA | M30: =IFERROR(__xludf.DUMMYFUNCTION("""COMPUTED_VALUE"""),"https://drive.google.com/open?id=1U5e44ln6q4wWEv95y0K5W7pbEeSipoBI") -> https://drive.google.com/open?id=1U5e44ln6q4wWEv95y0K5W7pbEeSipoBI | N30: =IFERROR(__xludf.DUMMYFUNCTION("""COMPUTED_VALUE"""),"DILLIP KUMAR SAHOO") -> DILLIP KUMAR SAHOO | O30: =IFERROR(__xludf.DUMMYFUNCTION("""COMPUTED_VALUE"""),"Accountant ") -> Accountant | P30: =IFERROR(__xludf.DUMMYFUNCTION("""COMPUTED_VALUE"""),"Bhadrak ") -> Bhadrak | Q30: =IFERROR(__xludf.DUMMYFUNCTION("""COMPUTED_VALUE"""),9.040091604E9) -> 9040091604 | R30: =IFERROR(__xludf.DUMMYFUNCTION("""COMPUTED_VALUE"""),"SUJATA SAHOO ") -> SUJATA SAHOO | S30: =IFERROR(__xludf.DUMMYFUNCTION("""COMPUTED_VALUE"""),"Home maker") -> Home maker | T30: =IFERROR(__xludf.DUMMYFUNCTION("""COMPUTED_VALUE"""),"Bhadrak ") -> Bhadrak | U30: =IFERROR(__xludf.DUMMYFUNCTION("""COMPUTED_VALUE"""),9.040091604E9) -> 9040091604 | V30: =IFERROR(__xludf.DUMMYFUNCTION("""COMPUTED_VALUE"""),2.0) -> 2 | W30: =IFERROR(__xludf.DUMMYFUNCTION("""COMPUTED_VALUE"""),"DILLIP KUMAR SAHOO") -> DILLIP KUMAR SAHOO | X30: =IFERROR(__xludf.DUMMYFUNCTION("""COMPUTED_VALUE"""),"Father ") -> Father | Y30: =IFERROR(__xludf.DUMMYFUNCTION("""COMPUTED_VALUE"""),"SUJATA SAHOO") -> SUJATA SAHOO | Z30: =IFERROR(__xludf.DUMMYFUNCTION("""COMPUTED_VALUE"""),"Mother") -> Mother | AA30: =IFERROR(__xludf.DUMMYFUNCTION("""COMPUTED_VALUE"""),"Non-Veg") -> Non-Veg | AB30: =IFERROR(__xludf.DUMMYFUNCTION("""COMPUTED_VALUE"""),"Non-Veg") -> Non-Veg | AC30: =IFERROR(__xludf.DUMMYFUNCTION("""COMPUTED_VALUE"""),"Veg") -> Veg | AD30: =IFERROR(__xludf.DUMMYFUNCTION("""COMPUTED_VALUE"""),"Drop at Kalyani Railway Station") -> Drop at Kalyani Railway Station | AE30: =IFERROR(__xludf.DUMMYFUNCTION("""COMPUTED_VALUE"""),2.0) -> 2
A31: =IFERROR(__xludf.DUMMYFUNCTION("""COMPUTED_VALUE"""),46265.83613523148) -> 46265.836 | B31: =IFERROR(__xludf.DUMMYFUNCTION("""COMPUTED_VALUE"""),"mandabi.mscnursing-2024@aiimskalyani.edu.in") -> mandabi.mscnursing-2024@aiimskalyani.edu.in | C31: =IFERROR(__xludf.DUMMYFUNCTION("""COMPUTED_VALUE"""),"MANDABI SARKAR") -> MANDABI SARKAR | D31: =IFERROR(__xludf.DUMMYFUNCTION("""COMPUTED_VALUE"""),2.0240407E7) -> 20240407 | E31: =IFERROR(__xludf.DUMMYFUNCTION("""COMPUTED_VALUE"""),"M.Sc. Nursing 2024") -> M.Sc. Nursing 2024 | F31: =IFERROR(__xludf.DUMMYFUNCTION("""COMPUTED_VALUE"""),8.900105792E9) -> 8900105792 | G31: =IFERROR(__xludf.DUMMYFUNCTION("""COMPUTED_VALUE"""),"mandabisarkar@gmail.com") -> mandabisarkar@gmail.com | H31: =IFERROR(__xludf.DUMMYFUNCTION("""COMPUTED_VALUE"""),"Yes") -> Yes | K31: =IFERROR(__xludf.DUMMYFUNCTION("""COMPUTED_VALUE"""),"Berhampore") -> Berhampore | L31: =IFERROR(__xludf.DUMMYFUNCTION("""COMPUTED_VALUE"""),"https://drive.google.com/open?id=1L82KSdSw_1SggAEgnc1cgro2NE9Xl-LU") -> https://drive.google.com/open?id=1L82KSdSw_1SggAEgnc1cgro2NE9Xl-LU | M31: =IFERROR(__xludf.DUMMYFUNCTION("""COMPUTED_VALUE"""),"https://drive.google.com/open?id=1vuQ6wwR_TNgQ1A7JnFzO74PzrtCIMD2-") -> https://drive.google.com/open?id=1vuQ6wwR_TNgQ1A7JnFzO74PzrtCIMD2- | N31: =IFERROR(__xludf.DUMMYFUNCTION("""COMPUTED_VALUE"""),"Achintya Kumar Sarkar ") -> Achintya Kumar Sarkar | O31: =IFERROR(__xludf.DUMMYFUNCTION("""COMPUTED_VALUE"""),"Retired school teacher ") -> Retired school teacher | P31: =IFERROR(__xludf.DUMMYFUNCTION("""COMPUTED_VALUE"""),"Berhampore, Murshidabad, West Bengal ") -> Berhampore, Murshidabad, West Bengal | Q31: =IFERROR(__xludf.DUMMYFUNCTION("""COMPUTED_VALUE"""),8.900477003E9) -> 8900477003 | R31: =IFERROR(__xludf.DUMMYFUNCTION("""COMPUTED_VALUE"""),"Chandana Sarkar ") -> Chandana Sarkar | S31: =IFERROR(__xludf.DUMMYFUNCTION("""COMPUTED_VALUE"""),"House wife ") -> House wife | T31: =IFERROR(__xludf.DUMMYFUNCTION("""COMPUTED_VALUE"""),"Berhampore, Murshidabad, West Bengal ") -> Berhampore, Murshidabad, West Bengal | U31: =IFERROR(__xludf.DUMMYFUNCTION("""COMPUTED_VALUE"""),7.063529371E9) -> 7063529371 | V31: =IFERROR(__xludf.DUMMYFUNCTION("""COMPUTED_VALUE"""),0.0) -> 0 | AA31: =IFERROR(__xludf.DUMMYFUNCTION("""COMPUTED_VALUE"""),"Non-Veg") -> Non-Veg | AD31: =IFERROR(__xludf.DUMMYFUNCTION("""COMPUTED_VALUE"""),"Drop at Kalyani Railway Station") -> Drop at Kalyani Railway Station | AE31: =IFERROR(__xludf.DUMMYFUNCTION("""COMPUTED_VALUE"""),1.0) -> 1
A32: =IFERROR(__xludf.DUMMYFUNCTION("""COMPUTED_VALUE"""),46265.82512252315) -> 46265.825 | B32: =IFERROR(__xludf.DUMMYFUNCTION("""COMPUTED_VALUE"""),"sayak.mbbs-2020@aiimskalyani.edu.in") -> sayak.mbbs-2020@aiimskalyani.edu.in | C32: =IFERROR(__xludf.DUMMYFUNCTION("""COMPUTED_VALUE"""),"SAYAK SAHA") -> SAYAK SAHA | D32: =IFERROR(__xludf.DUMMYFUNCTION("""COMPUTED_VALUE"""),2.0201137E7) -> 20201137 | E32: =IFERROR(__xludf.DUMMYFUNCTION("""COMPUTED_VALUE"""),"MBBS 2020") -> MBBS 2020 | F32: =IFERROR(__xludf.DUMMYFUNCTION("""COMPUTED_VALUE"""),6.290592637E9) -> 6290592637 | G32: =IFERROR(__xludf.DUMMYFUNCTION("""COMPUTED_VALUE"""),"sayak.mbbs-2020@aiimskalyani.edu.in") -> sayak.mbbs-2020@aiimskalyani.edu.in | H32: =IFERROR(__xludf.DUMMYFUNCTION("""COMPUTED_VALUE"""),"Yes") -> Yes | K32: =IFERROR(__xludf.DUMMYFUNCTION("""COMPUTED_VALUE"""),"Rishra") -> Rishra | L32: =IFERROR(__xludf.DUMMYFUNCTION("""COMPUTED_VALUE"""),"https://drive.google.com/open?id=118nvVBnwe-bVAhmD0QBndxzCqasZUNzH") -> https://drive.google.com/open?id=118nvVBnwe-bVAhmD0QBndxzCqasZUNzH | M32: =IFERROR(__xludf.DUMMYFUNCTION("""COMPUTED_VALUE"""),"https://drive.google.com/open?id=1R9esCf3eInufZvx3OTPxJzfqaYIRDdey") -> https://drive.google.com/open?id=1R9esCf3eInufZvx3OTPxJzfqaYIRDdey | N32: =IFERROR(__xludf.DUMMYFUNCTION("""COMPUTED_VALUE"""),"Prabhat Kumar Saha") -> Prabhat Kumar Saha | O32: =IFERROR(__xludf.DUMMYFUNCTION("""COMPUTED_VALUE"""),"Ex-defence ") -> Ex-defence | P32: =IFERROR(__xludf.DUMMYFUNCTION("""COMPUTED_VALUE"""),"Rishra") -> Rishra | Q32: =IFERROR(__xludf.DUMMYFUNCTION("""COMPUTED_VALUE"""),9.831397625E9) -> 9831397625 | R32: =IFERROR(__xludf.DUMMYFUNCTION("""COMPUTED_VALUE"""),"Kalpana Saha") -> Kalpana Saha | S32: =IFERROR(__xludf.DUMMYFUNCTION("""COMPUTED_VALUE"""),"Housewife") -> Housewife | T32: =IFERROR(__xludf.DUMMYFUNCTION("""COMPUTED_VALUE"""),"Rishra") -> Rishra | U32: =IFERROR(__xludf.DUMMYFUNCTION("""COMPUTED_VALUE"""),9.163705141E9) -> 9163705141 | V32: =IFERROR(__xludf.DUMMYFUNCTION("""COMPUTED_VALUE"""),2.0) -> 2 | W32: =IFERROR(__xludf.DUMMYFUNCTION("""COMPUTED_VALUE"""),"Prabhat Kumar Saha") -> Prabhat Kumar Saha | X32: =IFERROR(__xludf.DUMMYFUNCTION("""COMPUTED_VALUE"""),"Father") -> Father | Y32: =IFERROR(__xludf.DUMMYFUNCTION("""COMPUTED_VALUE"""),"Kalpana Saha") -> Kalpana Saha | Z32: =IFERROR(__xludf.DUMMYFUNCTION("""COMPUTED_VALUE"""),"Mother") -> Mother | AA32: =IFERROR(__xludf.DUMMYFUNCTION("""COMPUTED_VALUE"""),"Non-Veg") -> Non-Veg | AB32: =IFERROR(__xludf.DUMMYFUNCTION("""COMPUTED_VALUE"""),"Non-Veg") -> Non-Veg | AC32: =IFERROR(__xludf.DUMMYFUNCTION("""COMPUTED_VALUE"""),"Non-Veg") -> Non-Veg | AD32: =IFERROR(__xludf.DUMMYFUNCTION("""COMPUTED_VALUE"""),"Drop at Kalyani Railway Station") -> Drop at Kalyani Railway Station | AE32: =IFERROR(__xludf.DUMMYFUNCTION("""COMPUTED_VALUE"""),3.0) -> 3
A33: =IFERROR(__xludf.DUMMYFUNCTION("""COMPUTED_VALUE"""),46265.82132081018) -> 46265.821 | B33: =IFERROR(__xludf.DUMMYFUNCTION("""COMPUTED_VALUE"""),"sharafudheen.mbbs-2020@aiimskalyani.edu.in") -> sharafudheen.mbbs-2020@aiimskalyani.edu.in | C33: =IFERROR(__xludf.DUMMYFUNCTION("""COMPUTED_VALUE"""),"SHARAFUDHEEN EP") -> SHARAFUDHEEN EP | D33: =IFERROR(__xludf.DUMMYFUNCTION("""COMPUTED_VALUE"""),"88/202001138") -> 88/202001138 | E33: =IFERROR(__xludf.DUMMYFUNCTION("""COMPUTED_VALUE"""),"MBBS 2020") -> MBBS 2020 | F33: =IFERROR(__xludf.DUMMYFUNCTION("""COMPUTED_VALUE"""),6.383560594E9) -> 6383560594 | G33: =IFERROR(__xludf.DUMMYFUNCTION("""COMPUTED_VALUE"""),"sharafudheencu@gmail.com") -> sharafudheencu@gmail.com | H33: =IFERROR(__xludf.DUMMYFUNCTION("""COMPUTED_VALUE"""),"Yes") -> Yes | I33: =IFERROR(__xludf.DUMMYFUNCTION("""COMPUTED_VALUE"""),"Beyond clinical medicine, my interests revolve around continuous medical learning, sports, and visual arts. Academically, I am driven by advancements in therapeutics and pathophysiology, frequently keeping up with recent clinical research papers. Outside "&"the wards, I am a dedicated football player—playing primarily as a Defensive Midfielder (DMF) and having had the privilege of captaining my team to multiple tournament titles. I am also an avid photographer, with recognitions from Kaleidoscope and the ann"&"ual Elyssia fest, alongside being a cinephile and reader. ") -> Beyond clinical medicine, my interests revolve around continuous medical learning, sports, and visual arts. Academically, I am driven by advancements in therapeutics and pathophysiology, frequently keeping up with recent clinical research papers. Outside the wards, I am a dedicated football player—playing primarily as a Defensive Midfielder (DMF) and having had the privilege of captaining my team to multiple tournament titles. I am also an avid photographer, with recognitions from Kaleidoscope and the annual Elyssia fest, alongside being a cinephile and reader. | J33: =IFERROR(__xludf.DUMMYFUNCTION("""COMPUTED_VALUE"""),"A dedicated football player and team captain, leading the squad to consistent podium finishes throughout my college career. Under my captaincy, the team reached the finals in every inter-house season contested, clinching one championship trophy alongside "&"several runners-up titles. At the inter-collegiate level, we finished as runners-up at Elyssia Fest and reached the semi-finals at AIIMS Patna, while maintaining a commanding record and decisive victories in local rival fixtures against IISER. ") -> A dedicated football player and team captain, leading the squad to consistent podium finishes throughout my college career. Under my captaincy, the team reached the finals in every inter-house season contested, clinching one championship trophy alongside several runners-up titles. At the inter-collegiate level, we finished as runners-up at Elyssia Fest and reached the semi-finals at AIIMS Patna, while maintaining a commanding record and decisive victories in local rival fixtures against IISER. | K33: =IFERROR(__xludf.DUMMYFUNCTION("""COMPUTED_VALUE"""),"Kozhikode ") -> Kozhikode | L33: =IFERROR(__xludf.DUMMYFUNCTION("""COMPUTED_VALUE"""),"https://drive.google.com/open?id=1JrLI1tyO97IMOYricg8jbMsXKHw_AamJ") -> https://drive.google.com/open?id=1JrLI1tyO97IMOYricg8jbMsXKHw_AamJ | M33: =IFERROR(__xludf.DUMMYFUNCTION("""COMPUTED_VALUE"""),"https://drive.google.com/open?id=1nFQKiLGBPCvfasJiEpHSgEEyzg9EuJNV") -> https://drive.google.com/open?id=1nFQKiLGBPCvfasJiEpHSgEEyzg9EuJNV | N33: =IFERROR(__xludf.DUMMYFUNCTION("""COMPUTED_VALUE"""),"Yuseph EP ") -> Yuseph EP | O33: =IFERROR(__xludf.DUMMYFUNCTION("""COMPUTED_VALUE"""),"business ") -> business | P33: =IFERROR(__xludf.DUMMYFUNCTION("""COMPUTED_VALUE"""),"Chennai") -> Chennai | Q33: =IFERROR(__xludf.DUMMYFUNCTION("""COMPUTED_VALUE"""),9.48640503E9) -> 9486405030 | R33: =IFERROR(__xludf.DUMMYFUNCTION("""COMPUTED_VALUE"""),"Shabana M") -> Shabana M | S33: =IFERROR(__xludf.DUMMYFUNCTION("""COMPUTED_VALUE"""),"Housewife") -> Housewife | T33: =IFERROR(__xludf.DUMMYFUNCTION("""COMPUTED_VALUE"""),"Kozhikode ") -> Kozhikode | U33: =IFERROR(__xludf.DUMMYFUNCTION("""COMPUTED_VALUE"""),9.846603405E9) -> 9846603405 | V33: =IFERROR(__xludf.DUMMYFUNCTION("""COMPUTED_VALUE"""),2.0) -> 2 | W33: =IFERROR(__xludf.DUMMYFUNCTION("""COMPUTED_VALUE"""),"Shabana m") -> Shabana m | X33: =IFERROR(__xludf.DUMMYFUNCTION("""COMPUTED_VALUE"""),"Mother") -> Mother | Y33: =IFERROR(__xludf.DUMMYFUNCTION("""COMPUTED_VALUE"""),"Yuseph ep") -> Yuseph ep | Z33: =IFERROR(__xludf.DUMMYFUNCTION("""COMPUTED_VALUE"""),"Father") -> Father | AA33: =IFERROR(__xludf.DUMMYFUNCTION("""COMPUTED_VALUE"""),"Non-Veg") -> Non-Veg | AB33: =IFERROR(__xludf.DUMMYFUNCTION("""COMPUTED_VALUE"""),"Non-Veg") -> Non-Veg | AC33: =IFERROR(__xludf.DUMMYFUNCTION("""COMPUTED_VALUE"""),"Non-Veg") -> Non-Veg | AD33: =IFERROR(__xludf.DUMMYFUNCTION("""COMPUTED_VALUE"""),"Bus Drop Service not needed") -> Bus Drop Service not needed | AE33: =IFERROR(__xludf.DUMMYFUNCTION("""COMPUTED_VALUE"""),0.0) -> 0
A34: =IFERROR(__xludf.DUMMYFUNCTION("""COMPUTED_VALUE"""),46265.814711493054) -> 46265.815 | B34: =IFERROR(__xludf.DUMMYFUNCTION("""COMPUTED_VALUE"""),"vineeta.mbbs-2020@aiimskalyani.edu.in") -> vineeta.mbbs-2020@aiimskalyani.edu.in | C34: =IFERROR(__xludf.DUMMYFUNCTION("""COMPUTED_VALUE"""),"VINEETA MEENA") -> VINEETA MEENA | D34: =IFERROR(__xludf.DUMMYFUNCTION("""COMPUTED_VALUE"""),2.02001162E8) -> 202001162 | E34: =IFERROR(__xludf.DUMMYFUNCTION("""COMPUTED_VALUE"""),"MBBS 2020") -> MBBS 2020 | F34: =IFERROR(__xludf.DUMMYFUNCTION("""COMPUTED_VALUE"""),8.824036959E9) -> 8824036959 | G34: =IFERROR(__xludf.DUMMYFUNCTION("""COMPUTED_VALUE"""),"vineeta.mbbs-2020@aiimskalyani.edu.in") -> vineeta.mbbs-2020@aiimskalyani.edu.in | H34: =IFERROR(__xludf.DUMMYFUNCTION("""COMPUTED_VALUE"""),"Yes") -> Yes | I34: =IFERROR(__xludf.DUMMYFUNCTION("""COMPUTED_VALUE"""),"Playing volleyball, throwball ") -> Playing volleyball, throwball | K34: =IFERROR(__xludf.DUMMYFUNCTION("""COMPUTED_VALUE"""),"Sikar") -> Sikar | L34: =IFERROR(__xludf.DUMMYFUNCTION("""COMPUTED_VALUE"""),"https://drive.google.com/open?id=1IPDSKNOEeSQb-uBaVCtoCyBaEBJUVMh8") -> https://drive.google.com/open?id=1IPDSKNOEeSQb-uBaVCtoCyBaEBJUVMh8 | M34: =IFERROR(__xludf.DUMMYFUNCTION("""COMPUTED_VALUE"""),"https://drive.google.com/open?id=1ZWe9ogNm9xcbQhRh-OolbkFOQtiDlCO1") -> https://drive.google.com/open?id=1ZWe9ogNm9xcbQhRh-OolbkFOQtiDlCO1 | N34: =IFERROR(__xludf.DUMMYFUNCTION("""COMPUTED_VALUE"""),"Vinod kumar ") -> Vinod kumar | O34: =IFERROR(__xludf.DUMMYFUNCTION("""COMPUTED_VALUE"""),"Supervisor ") -> Supervisor | P34: =IFERROR(__xludf.DUMMYFUNCTION("""COMPUTED_VALUE"""),"Sikar") -> Sikar | Q34: =IFERROR(__xludf.DUMMYFUNCTION("""COMPUTED_VALUE"""),8.112291832E9) -> 8112291832 | R34: =IFERROR(__xludf.DUMMYFUNCTION("""COMPUTED_VALUE"""),"Manju devi ") -> Manju devi | S34: =IFERROR(__xludf.DUMMYFUNCTION("""COMPUTED_VALUE"""),"Housewife ") -> Housewife | T34: =IFERROR(__xludf.DUMMYFUNCTION("""COMPUTED_VALUE"""),"Sikar") -> Sikar | U34: =IFERROR(__xludf.DUMMYFUNCTION("""COMPUTED_VALUE"""),8.432815435E9) -> 8432815435 | V34: =IFERROR(__xludf.DUMMYFUNCTION("""COMPUTED_VALUE"""),2.0) -> 2 | W34: =IFERROR(__xludf.DUMMYFUNCTION("""COMPUTED_VALUE"""),"Vinod kumar ") -> Vinod kumar | X34: =IFERROR(__xludf.DUMMYFUNCTION("""COMPUTED_VALUE"""),"Father") -> Father | Y34: =IFERROR(__xludf.DUMMYFUNCTION("""COMPUTED_VALUE"""),"Ashi ") -> Ashi | Z34: =IFERROR(__xludf.DUMMYFUNCTION("""COMPUTED_VALUE"""),"Sister") -> Sister | AA34: =IFERROR(__xludf.DUMMYFUNCTION("""COMPUTED_VALUE"""),"Veg") -> Veg | AB34: =IFERROR(__xludf.DUMMYFUNCTION("""COMPUTED_VALUE"""),"Veg") -> Veg | AC34: =IFERROR(__xludf.DUMMYFUNCTION("""COMPUTED_VALUE"""),"Veg") -> Veg | AD34: =IFERROR(__xludf.DUMMYFUNCTION("""COMPUTED_VALUE"""),"Drop at Kolkata Airport") -> Drop at Kolkata Airport | AE34: =IFERROR(__xludf.DUMMYFUNCTION("""COMPUTED_VALUE"""),1.0) -> 1
A35: =IFERROR(__xludf.DUMMYFUNCTION("""COMPUTED_VALUE"""),46265.81132795139) -> 46265.811 | B35: =IFERROR(__xludf.DUMMYFUNCTION("""COMPUTED_VALUE"""),"nidhidhandhi29@gmail.com") -> nidhidhandhi29@gmail.com | C35: =IFERROR(__xludf.DUMMYFUNCTION("""COMPUTED_VALUE"""),"Nidhi") -> Nidhi | D35: =IFERROR(__xludf.DUMMYFUNCTION("""COMPUTED_VALUE"""),2.0240412E7) -> 20240412 | E35: =IFERROR(__xludf.DUMMYFUNCTION("""COMPUTED_VALUE"""),"M.Sc. Nursing 2024") -> M.Sc. Nursing 2024 | F35: =IFERROR(__xludf.DUMMYFUNCTION("""COMPUTED_VALUE"""),7.015693798E9) -> 7015693798 | G35: =IFERROR(__xludf.DUMMYFUNCTION("""COMPUTED_VALUE"""),"nidhidhandhi29@gmail.com") -> nidhidhandhi29@gmail.com | H35: =IFERROR(__xludf.DUMMYFUNCTION("""COMPUTED_VALUE"""),"Yes") -> Yes | I35: =IFERROR(__xludf.DUMMYFUNCTION("""COMPUTED_VALUE"""),"Yoga") -> Yoga | J35: =IFERROR(__xludf.DUMMYFUNCTION("""COMPUTED_VALUE"""),"No") -> No | K35: =IFERROR(__xludf.DUMMYFUNCTION("""COMPUTED_VALUE"""),"Haryana") -> Haryana | L35: =IFERROR(__xludf.DUMMYFUNCTION("""COMPUTED_VALUE"""),"https://drive.google.com/open?id=1q4jtwLfwgagaoHjx9Vk-4Au0Nn89GlKY") -> https://drive.google.com/open?id=1q4jtwLfwgagaoHjx9Vk-4Au0Nn89GlKY | M35: =IFERROR(__xludf.DUMMYFUNCTION("""COMPUTED_VALUE"""),"https://drive.google.com/open?id=1uYaBUS1pDb8zNs1myLB9Wfa06w9aEjeg") -> https://drive.google.com/open?id=1uYaBUS1pDb8zNs1myLB9Wfa06w9aEjeg | N35: =IFERROR(__xludf.DUMMYFUNCTION("""COMPUTED_VALUE"""),"Sanjay") -> Sanjay | O35: =IFERROR(__xludf.DUMMYFUNCTION("""COMPUTED_VALUE"""),"Self employment ") -> Self employment | P35: =IFERROR(__xludf.DUMMYFUNCTION("""COMPUTED_VALUE"""),"Mehmudpur") -> Mehmudpur | Q35: =IFERROR(__xludf.DUMMYFUNCTION("""COMPUTED_VALUE"""),9.996577829E9) -> 9996577829 | R35: =IFERROR(__xludf.DUMMYFUNCTION("""COMPUTED_VALUE"""),"Mukesh") -> Mukesh | S35: =IFERROR(__xludf.DUMMYFUNCTION("""COMPUTED_VALUE"""),"Housemaker") -> Housemaker | T35: =IFERROR(__xludf.DUMMYFUNCTION("""COMPUTED_VALUE"""),"Mehmudpur ") -> Mehmudpur | U35: =IFERROR(__xludf.DUMMYFUNCTION("""COMPUTED_VALUE"""),8.930544883E9) -> 8930544883 | V35: =IFERROR(__xludf.DUMMYFUNCTION("""COMPUTED_VALUE"""),2.0) -> 2 | W35: =IFERROR(__xludf.DUMMYFUNCTION("""COMPUTED_VALUE"""),"Barkha ") -> Barkha | X35: =IFERROR(__xludf.DUMMYFUNCTION("""COMPUTED_VALUE"""),"Sister ") -> Sister | Y35: =IFERROR(__xludf.DUMMYFUNCTION("""COMPUTED_VALUE"""),"Sneha") -> Sneha | Z35: =IFERROR(__xludf.DUMMYFUNCTION("""COMPUTED_VALUE"""),"Sister") -> Sister | AA35: =IFERROR(__xludf.DUMMYFUNCTION("""COMPUTED_VALUE"""),"Veg") -> Veg | AB35: =IFERROR(__xludf.DUMMYFUNCTION("""COMPUTED_VALUE"""),"Veg") -> Veg | AC35: =IFERROR(__xludf.DUMMYFUNCTION("""COMPUTED_VALUE"""),"Veg") -> Veg | AD35: =IFERROR(__xludf.DUMMYFUNCTION("""COMPUTED_VALUE"""),"Bus Drop Service not needed") -> Bus Drop Service not needed | AE35: =IFERROR(__xludf.DUMMYFUNCTION("""COMPUTED_VALUE"""),0.0) -> 0
A36: =IFERROR(__xludf.DUMMYFUNCTION("""COMPUTED_VALUE"""),46265.76405421297) -> 46265.764 | B36: =IFERROR(__xludf.DUMMYFUNCTION("""COMPUTED_VALUE"""),"prama.mscnursing-2024@aiimskalyani.edu.in") -> prama.mscnursing-2024@aiimskalyani.edu.in | C36: =IFERROR(__xludf.DUMMYFUNCTION("""COMPUTED_VALUE"""),"PRAMA CHATTERJEE") -> PRAMA CHATTERJEE | D36: =IFERROR(__xludf.DUMMYFUNCTION("""COMPUTED_VALUE"""),2.0240409E7) -> 20240409 | E36: =IFERROR(__xludf.DUMMYFUNCTION("""COMPUTED_VALUE"""),"M.Sc. Nursing 2024") -> M.Sc. Nursing 2024 | F36: =IFERROR(__xludf.DUMMYFUNCTION("""COMPUTED_VALUE"""),8.420623906E9) -> 8420623906 | G36: =IFERROR(__xludf.DUMMYFUNCTION("""COMPUTED_VALUE"""),"prama.mscnursing-2024@aiimskalyani.edu.in") -> prama.mscnursing-2024@aiimskalyani.edu.in | H36: =IFERROR(__xludf.DUMMYFUNCTION("""COMPUTED_VALUE"""),"Yes") -> Yes | I36: =IFERROR(__xludf.DUMMYFUNCTION("""COMPUTED_VALUE"""),"Dancing and singing") -> Dancing and singing | J36: =IFERROR(__xludf.DUMMYFUNCTION("""COMPUTED_VALUE"""),"NA") -> NA | K36: =IFERROR(__xludf.DUMMYFUNCTION("""COMPUTED_VALUE"""),"Kolkata, West Bengal") -> Kolkata, West Bengal | L36: =IFERROR(__xludf.DUMMYFUNCTION("""COMPUTED_VALUE"""),"https://drive.google.com/open?id=1_v9ipshqTAJe0fl6j8fWr8d3eAG2WLHH") -> https://drive.google.com/open?id=1_v9ipshqTAJe0fl6j8fWr8d3eAG2WLHH | M36: =IFERROR(__xludf.DUMMYFUNCTION("""COMPUTED_VALUE"""),"https://drive.google.com/open?id=1xJj6JguZYYZ-Ag7mDWJOZAl5rU7PX0Qk") -> https://drive.google.com/open?id=1xJj6JguZYYZ-Ag7mDWJOZAl5rU7PX0Qk | N36: =IFERROR(__xludf.DUMMYFUNCTION("""COMPUTED_VALUE"""),"TARUN KUMAR CHATTERJEE") -> TARUN KUMAR CHATTERJEE | O36: =IFERROR(__xludf.DUMMYFUNCTION("""COMPUTED_VALUE"""),"GOVT. SERVICE") -> GOVT. SERVICE | P36: =IFERROR(__xludf.DUMMYFUNCTION("""COMPUTED_VALUE"""),"Kolkata, West Bengal") -> Kolkata, West Bengal | Q36: =IFERROR(__xludf.DUMMYFUNCTION("""COMPUTED_VALUE"""),9.477026679E9) -> 9477026679 | R36: =IFERROR(__xludf.DUMMYFUNCTION("""COMPUTED_VALUE"""),"SAMPA CHATTERJEE") -> SAMPA CHATTERJEE | S36: =IFERROR(__xludf.DUMMYFUNCTION("""COMPUTED_VALUE"""),"HOUSEWIFE") -> HOUSEWIFE | T36: =IFERROR(__xludf.DUMMYFUNCTION("""COMPUTED_VALUE"""),"Kolkata, West Bengal") -> Kolkata, West Bengal | U36: =IFERROR(__xludf.DUMMYFUNCTION("""COMPUTED_VALUE"""),8.902338855E9) -> 8902338855 | V36: =IFERROR(__xludf.DUMMYFUNCTION("""COMPUTED_VALUE"""),2.0) -> 2 | W36: =IFERROR(__xludf.DUMMYFUNCTION("""COMPUTED_VALUE"""),"TARUN KUMAR CHATTERJEE") -> TARUN KUMAR CHATTERJEE | X36: =IFERROR(__xludf.DUMMYFUNCTION("""COMPUTED_VALUE"""),"FATHER") -> FATHER | Y36: =IFERROR(__xludf.DUMMYFUNCTION("""COMPUTED_VALUE"""),"SAMPA CHATTERJEE") -> SAMPA CHATTERJEE | Z36: =IFERROR(__xludf.DUMMYFUNCTION("""COMPUTED_VALUE"""),"MOTHER") -> MOTHER | AA36: =IFERROR(__xludf.DUMMYFUNCTION("""COMPUTED_VALUE"""),"Non-Veg") -> Non-Veg | AB36: =IFERROR(__xludf.DUMMYFUNCTION("""COMPUTED_VALUE"""),"Non-Veg") -> Non-Veg | AC36: =IFERROR(__xludf.DUMMYFUNCTION("""COMPUTED_VALUE"""),"Non-Veg") -> Non-Veg | AD36: =IFERROR(__xludf.DUMMYFUNCTION("""COMPUTED_VALUE"""),"Drop at Kalyani Railway Station") -> Drop at Kalyani Railway Station | AE36: =IFERROR(__xludf.DUMMYFUNCTION("""COMPUTED_VALUE"""),3.0) -> 3
A37: =IFERROR(__xludf.DUMMYFUNCTION("""COMPUTED_VALUE"""),46265.75187501157) -> 46265.752 | B37: =IFERROR(__xludf.DUMMYFUNCTION("""COMPUTED_VALUE"""),"sanith.patho_pgt23@aiimskalyani.edu.in") -> sanith.patho_pgt23@aiimskalyani.edu.in | C37: =IFERROR(__xludf.DUMMYFUNCTION("""COMPUTED_VALUE"""),"Dr. Sanith Mani") -> Dr. Sanith Mani | D37: =IFERROR(__xludf.DUMMYFUNCTION("""COMPUTED_VALUE"""),2.0230312E7) -> 20230312 | E37: =IFERROR(__xludf.DUMMYFUNCTION("""COMPUTED_VALUE"""),"MD/MS/MDS 2023") -> MD/MS/MDS 2023 | F37: =IFERROR(__xludf.DUMMYFUNCTION("""COMPUTED_VALUE"""),9.496900091E9) -> 9496900091 | G37: =IFERROR(__xludf.DUMMYFUNCTION("""COMPUTED_VALUE"""),"sanithmani@gmail.com") -> sanithmani@gmail.com | H37: =IFERROR(__xludf.DUMMYFUNCTION("""COMPUTED_VALUE"""),"Yes") -> Yes | I37: =IFERROR(__xludf.DUMMYFUNCTION("""COMPUTED_VALUE"""),"Reading, watching movies, travelling") -> Reading, watching movies, travelling | J37: =IFERROR(__xludf.DUMMYFUNCTION("""COMPUTED_VALUE"""),"Football") -> Football | K37: =IFERROR(__xludf.DUMMYFUNCTION("""COMPUTED_VALUE"""),"Kottayam, kerala") -> Kottayam, kerala | L37: =IFERROR(__xludf.DUMMYFUNCTION("""COMPUTED_VALUE"""),"https://drive.google.com/open?id=1mwdUPbPaO99_i4UyRy4U0ctnJjbfI1wx") -> https://drive.google.com/open?id=1mwdUPbPaO99_i4UyRy4U0ctnJjbfI1wx | M37: =IFERROR(__xludf.DUMMYFUNCTION("""COMPUTED_VALUE"""),"https://drive.google.com/open?id=1aEn6zynYMtTqU82pZLlLnFjsJXaMolgi") -> https://drive.google.com/open?id=1aEn6zynYMtTqU82pZLlLnFjsJXaMolgi | N37: =IFERROR(__xludf.DUMMYFUNCTION("""COMPUTED_VALUE"""),"Lt. Mani Cyriac") -> Lt. Mani Cyriac | O37: =IFERROR(__xludf.DUMMYFUNCTION("""COMPUTED_VALUE"""),"Business man") -> Business man | P37: =IFERROR(__xludf.DUMMYFUNCTION("""COMPUTED_VALUE"""),"Kottayam") -> Kottayam | Q37: =IFERROR(__xludf.DUMMYFUNCTION("""COMPUTED_VALUE"""),8.921105271E9) -> 8921105271 | R37: =IFERROR(__xludf.DUMMYFUNCTION("""COMPUTED_VALUE"""),"Ancy Mani") -> Ancy Mani | S37: =IFERROR(__xludf.DUMMYFUNCTION("""COMPUTED_VALUE"""),"House wife") -> House wife | T37: =IFERROR(__xludf.DUMMYFUNCTION("""COMPUTED_VALUE"""),"Kottayam") -> Kottayam | U37: =IFERROR(__xludf.DUMMYFUNCTION("""COMPUTED_VALUE"""),9.4963153E9) -> 9496315300 | V37: =IFERROR(__xludf.DUMMYFUNCTION("""COMPUTED_VALUE"""),1.0) -> 1 | W37: =IFERROR(__xludf.DUMMYFUNCTION("""COMPUTED_VALUE"""),"MERLIN SABU") -> MERLIN SABU | X37: =IFERROR(__xludf.DUMMYFUNCTION("""COMPUTED_VALUE"""),"SPOUSE") -> SPOUSE | AA37: =IFERROR(__xludf.DUMMYFUNCTION("""COMPUTED_VALUE"""),"Non-Veg") -> Non-Veg | AB37: =IFERROR(__xludf.DUMMYFUNCTION("""COMPUTED_VALUE"""),"Non-Veg") -> Non-Veg | AE37: =IFERROR(__xludf.DUMMYFUNCTION("""COMPUTED_VALUE"""),0.0) -> 0
A38: =IFERROR(__xludf.DUMMYFUNCTION("""COMPUTED_VALUE"""),46265.74408037037) -> 46265.744 | B38: =IFERROR(__xludf.DUMMYFUNCTION("""COMPUTED_VALUE"""),"mohua.bscnursing-2021@aiimskalyani.edu.in") -> mohua.bscnursing-2021@aiimskalyani.edu.in | C38: =IFERROR(__xludf.DUMMYFUNCTION("""COMPUTED_VALUE"""),"MOHUA KHATUN ") -> MOHUA KHATUN | D38: =IFERROR(__xludf.DUMMYFUNCTION("""COMPUTED_VALUE"""),2.0210225E7) -> 20210225 | E38: =IFERROR(__xludf.DUMMYFUNCTION("""COMPUTED_VALUE"""),"B.Sc (Hons) Nursing 2021") -> B.Sc (Hons) Nursing 2021 | F38: =IFERROR(__xludf.DUMMYFUNCTION("""COMPUTED_VALUE"""),7.074559669E9) -> 7074559669 | G38: =IFERROR(__xludf.DUMMYFUNCTION("""COMPUTED_VALUE"""),"mohua.bscnursing-2021@aiimskalyani.edu.in") -> mohua.bscnursing-2021@aiimskalyani.edu.in | H38: =IFERROR(__xludf.DUMMYFUNCTION("""COMPUTED_VALUE"""),"Yes") -> Yes | I38: =IFERROR(__xludf.DUMMYFUNCTION("""COMPUTED_VALUE"""),"Gardening,Cooking,Spending time with family and friends ") -> Gardening,Cooking,Spending time with family and friends | J38: =IFERROR(__xludf.DUMMYFUNCTION("""COMPUTED_VALUE"""),"Health Convener of CON, Aiims Kalyani ") -> Health Convener of CON, Aiims Kalyani | K38: =IFERROR(__xludf.DUMMYFUNCTION("""COMPUTED_VALUE"""),"Arambagh, Hooghly, West Bengal") -> Arambagh, Hooghly, West Bengal | L38: =IFERROR(__xludf.DUMMYFUNCTION("""COMPUTED_VALUE"""),"https://drive.google.com/open?id=1jg--PfomRC8U5u4fxaR52oQRHrvm3LhQ") -> https://drive.google.com/open?id=1jg--PfomRC8U5u4fxaR52oQRHrvm3LhQ | M38: =IFERROR(__xludf.DUMMYFUNCTION("""COMPUTED_VALUE"""),"https://drive.google.com/open?id=15DqgMzqxVTeyVlE8ii224-5hgM0RqaHD") -> https://drive.google.com/open?id=15DqgMzqxVTeyVlE8ii224-5hgM0RqaHD | N38: =IFERROR(__xludf.DUMMYFUNCTION("""COMPUTED_VALUE"""),"Sk Manuar Ali") -> Sk Manuar Ali | O38: =IFERROR(__xludf.DUMMYFUNCTION("""COMPUTED_VALUE"""),"Embroidery Worker") -> Embroidery Worker | P38: =IFERROR(__xludf.DUMMYFUNCTION("""COMPUTED_VALUE"""),"Arambagh, Hooghly, West Bengal ") -> Arambagh, Hooghly, West Bengal | Q38: =IFERROR(__xludf.DUMMYFUNCTION("""COMPUTED_VALUE"""),7.986006157E9) -> 7986006157 | R38: =IFERROR(__xludf.DUMMYFUNCTION("""COMPUTED_VALUE"""),"Abeda Begam") -> Abeda Begam | S38: =IFERROR(__xludf.DUMMYFUNCTION("""COMPUTED_VALUE"""),"Housewife ") -> Housewife | T38: =IFERROR(__xludf.DUMMYFUNCTION("""COMPUTED_VALUE"""),"Arambagh, Hooghly, West Bengal ") -> Arambagh, Hooghly, West Bengal | U38: =IFERROR(__xludf.DUMMYFUNCTION("""COMPUTED_VALUE"""),9.749952213E9) -> 9749952213 | V38: =IFERROR(__xludf.DUMMYFUNCTION("""COMPUTED_VALUE"""),2.0) -> 2 | W38: =IFERROR(__xludf.DUMMYFUNCTION("""COMPUTED_VALUE"""),"Abeda Begam ") -> Abeda Begam | X38: =IFERROR(__xludf.DUMMYFUNCTION("""COMPUTED_VALUE"""),"Mother ") -> Mother | Y38: =IFERROR(__xludf.DUMMYFUNCTION("""COMPUTED_VALUE"""),"Mabuda Begam") -> Mabuda Begam | Z38: =IFERROR(__xludf.DUMMYFUNCTION("""COMPUTED_VALUE"""),"Aunty ") -> Aunty | AA38: =IFERROR(__xludf.DUMMYFUNCTION("""COMPUTED_VALUE"""),"Veg") -> Veg | AB38: =IFERROR(__xludf.DUMMYFUNCTION("""COMPUTED_VALUE"""),"Veg") -> Veg | AC38: =IFERROR(__xludf.DUMMYFUNCTION("""COMPUTED_VALUE"""),"Veg") -> Veg | AD38: =IFERROR(__xludf.DUMMYFUNCTION("""COMPUTED_VALUE"""),"Bus Drop Service not needed") -> Bus Drop Service not needed | AE38: =IFERROR(__xludf.DUMMYFUNCTION("""COMPUTED_VALUE"""),0.0) -> 0
A39: =IFERROR(__xludf.DUMMYFUNCTION("""COMPUTED_VALUE"""),46265.74221628472) -> 46265.742 | B39: =IFERROR(__xludf.DUMMYFUNCTION("""COMPUTED_VALUE"""),"neha.bscnursing-2021@aiimskalyani.edu.in") -> neha.bscnursing-2021@aiimskalyani.edu.in | C39: =IFERROR(__xludf.DUMMYFUNCTION("""COMPUTED_VALUE"""),"Neha Bharti") -> Neha Bharti | D39: =IFERROR(__xludf.DUMMYFUNCTION("""COMPUTED_VALUE"""),2.0210231E7) -> 20210231 | E39: =IFERROR(__xludf.DUMMYFUNCTION("""COMPUTED_VALUE"""),"B.Sc (Hons) Nursing 2021") -> B.Sc (Hons) Nursing 2021 | F39: =IFERROR(__xludf.DUMMYFUNCTION("""COMPUTED_VALUE"""),9.534028858E9) -> 9534028858 | G39: =IFERROR(__xludf.DUMMYFUNCTION("""COMPUTED_VALUE"""),"nehabharti8257@gmail.com") -> nehabharti8257@gmail.com | H39: =IFERROR(__xludf.DUMMYFUNCTION("""COMPUTED_VALUE"""),"Yes") -> Yes | I39: =IFERROR(__xludf.DUMMYFUNCTION("""COMPUTED_VALUE"""),"Like to read books,play badminton ") -> Like to read books,play badminton | J39: =IFERROR(__xludf.DUMMYFUNCTION("""COMPUTED_VALUE"""),"Have achieved medals and certificates for several games in college fest") -> Have achieved medals and certificates for several games in college fest | K39: =IFERROR(__xludf.DUMMYFUNCTION("""COMPUTED_VALUE"""),"Bihar ") -> Bihar | L39: =IFERROR(__xludf.DUMMYFUNCTION("""COMPUTED_VALUE"""),"https://drive.google.com/open?id=1LhzzXJs-UnohE681HgwaOAw45n28JXz3") -> https://drive.google.com/open?id=1LhzzXJs-UnohE681HgwaOAw45n28JXz3 | M39: =IFERROR(__xludf.DUMMYFUNCTION("""COMPUTED_VALUE"""),"https://drive.google.com/open?id=1UZx222ibsk9zHzcsDK6VCCTTZCDJYoi0") -> https://drive.google.com/open?id=1UZx222ibsk9zHzcsDK6VCCTTZCDJYoi0 | N39: =IFERROR(__xludf.DUMMYFUNCTION("""COMPUTED_VALUE"""),"Sanjay Kumar Singh ") -> Sanjay Kumar Singh | O39: =IFERROR(__xludf.DUMMYFUNCTION("""COMPUTED_VALUE"""),"Retired Army Officer ") -> Retired Army Officer | P39: =IFERROR(__xludf.DUMMYFUNCTION("""COMPUTED_VALUE"""),"Kolkata") -> Kolkata | Q39: =IFERROR(__xludf.DUMMYFUNCTION("""COMPUTED_VALUE"""),9.760320316E9) -> 9760320316 | R39: =IFERROR(__xludf.DUMMYFUNCTION("""COMPUTED_VALUE"""),"Pratima singh") -> Pratima singh | S39: =IFERROR(__xludf.DUMMYFUNCTION("""COMPUTED_VALUE"""),"Homemaker") -> Homemaker | T39: =IFERROR(__xludf.DUMMYFUNCTION("""COMPUTED_VALUE"""),"Kolkata") -> Kolkata | U39: =IFERROR(__xludf.DUMMYFUNCTION("""COMPUTED_VALUE"""),9.699868646E9) -> 9699868646 | V39: =IFERROR(__xludf.DUMMYFUNCTION("""COMPUTED_VALUE"""),0.0) -> 0 | AA39: =IFERROR(__xludf.DUMMYFUNCTION("""COMPUTED_VALUE"""),"Non-Veg") -> Non-Veg | AD39: =IFERROR(__xludf.DUMMYFUNCTION("""COMPUTED_VALUE"""),"Bus Drop Service not needed") -> Bus Drop Service not needed | AE39: =IFERROR(__xludf.DUMMYFUNCTION("""COMPUTED_VALUE"""),0.0) -> 0
